Workbook
Name Data: 'Master Data Lot1'!$A$1:$T$1
Name Data: 'Master Data Lot2'!$A$1:$T$92
Name Data2: #REF!

Sheet information
B4: Design | E4: Procurement | H4: Construction/Installation | K4: Inspection
B5: Outline | C5: Definitive Design | D5: Detail Design | E5: Pre-PR | F5: PO/WO | G5: Delivery | H5: Start | I5: WIP | J5: Complete | K5: Inspection | L5: Punch list | M5: Closed

Sheet 00 MASTER WORK REGISTER
B1: MASTER WORK REGISTER
A3: No | B3: Type of Work | C3: Work Code | D3: Lot No. | E3: System | F3: LV1 | G3: LV2 | H3: Description/Title | I3: CK | J3: Location | L3: Submission No. | M3: Ex | N3: Note
A4: 1 | B4: =IF(G4<>"",E4&F4&"."&G4,E4&F4) -> GEN1 | C4: DN01B1700001 | D4: Lot01 | E4: GEN | F4: 1 | H4: Rooms and Building Service Systems Modification in Stations Area | I4: - | K4: Station | L4: MDW-39246-60 | M4: 46235 | O4: =COUNTIF('02 Design'!$C$5:$C$366,'00 MASTER WORK REGISTER'!$B4) -> 10
A5: 2 | B5: =IF(G5<>"",E5&F5&"."&G5,E5&F5) -> GEN1.1 | C5: DN01B1700001 | D5: Lot01 | E5: GEN | F5: 1 | G5: 1 | H5: Power Outlet Installation in SOR, Ticket Office and Cash Handling for OR13 - OR17 | I5: - | K5: Station | L5: MDW-39246 | M5: 46235 | O5: =COUNTIF('02 Design'!$C$5:$C$366,'00 MASTER WORK REGISTER'!$B5) -> 1
A6: 3 | B6: =IF(G6<>"",E6&F6&"."&G6,E6&F6) -> GEN1.2 | C6: DN01B1700001 | D6: Lot01 | E6: GEN | F6: 1 | G6: 2 | H6: Power Outlet Installation in SOR, Ticket Office and Cash Handling for OR18 - OR22 | I6: - | K6: Station | L6: MDW-39247 | M6: 46235 | O6: =COUNTIF('02 Design'!$C$5:$C$366,'00 MASTER WORK REGISTER'!$B6) -> 1
A7: 4 | B7: =IF(G7<>"",E7&F7&"."&G7,E7&F7) -> GEN1.3 | C7: DN01B1700001 | D7: Lot01 | E7: GEN | F7: 1 | G7: 3 | H7: Power Outlet Installation in SOR, Ticket Office and Cash Handling for OR18 - OR22 | I7: - | K7: Station | L7: MDW-39247 | M7: 46235 | O7: =COUNTIF('02 Design'!$C$5:$C$366,'00 MASTER WORK REGISTER'!$B7) -> 1
A8: 5 | B8: =IF(G8<>"",E8&F8&"."&G8,E8&F8) -> GEN1.4 | C8: DN01B1700001 | D8: Lot01 | E8: GEN | F8: 1 | G8: 4 | H8: Power Outlet Installation in SOR, Ticket Office and Cash Handling for OR23 - OR29 | I8: - | K8: Station | L8: MDW-39248 | M8: 46235 | O8: =COUNTIF('02 Design'!$C$5:$C$366,'00 MASTER WORK REGISTER'!$B8) -> 1
A9: 6 | B9: =IF(G9<>"",E9&F9&"."&G9,E9&F9) -> GEN1.5 | C9: DN01B1700001 | D9: Lot01 | E9: GEN | F9: 1 | G9: 5 | H9: Power Outlet Installation in SOR, Ticket Office and Cash Handling for OR23 - OR29 | I9: - | K9: Station | L9: MDW-39248 | M9: 46235 | O9: =COUNTIF('02 Design'!$C$5:$C$366,'00 MASTER WORK REGISTER'!$B9) -> 1
A10: 7 | B10: =IF(G10<>"",E10&F10&"."&G10,E10&F10) -> GEN1.6 | C10: DN01B1700001 | D10: Lot01 | E10: GEN | F10: 1 | G10: 6 | H10: SOR Counter and Workstation Hanging Support Installation on East Section | I10: - | K10: Station | L10: MDW-39249 | M10: 46235 | O10: =COUNTIF('02 Design'!$C$5:$C$366,'00 MASTER WORK REGISTER'!$B10) -> 1
A11: 8 | B11: =IF(G11<>"",E11&F11&"."&G11,E11&F11) -> GEN1.7 | C11: DN01B1700001 | D11: Lot01 | E11: GEN | F11: 1 | G11: 7 | H11: Ticket Office Modification on East Section | I11: - | K11: Station | L11: MDW-39250 | M11: 46235 | N11: งานจบ ส่ง TP แล้ว | O11: =COUNTIF('02 Design'!$C$5:$C$366,'00 MASTER WORK REGISTER'!$B11) -> 1
A12: 9 | B12: =IF(G12<>"",E12&F12&"."&G12,E12&F12) -> GEN1.10 | C12: DN01B1700001 | D12: Lot01 | E12: GEN | F12: 1 | G12: 10 | H12: Modification of Eletrical System in Telecommunication Room at OR14 | I12: - | K12: Station | L12: MDW-39251 | M12: 46235 | O12: =COUNTIF('02 Design'!$C$5:$C$366,'00 MASTER WORK REGISTER'!$B12) -> 1
A13: 10 | B13: =IF(G13<>"",E13&F13&"."&G13,E13&F13) -> GEN1.11 | C13: DN01B1700001 | D13: Lot01 | E13: GEN | F13: 1 | G13: 11 | H13: Modification of Fire Suppression System (N2) in Commerial Room at OR14 | I13: - | K13: Station | L13: MDW-39252 | M13: 46235 | O13: =COUNTIF('02 Design'!$C$5:$C$366,'00 MASTER WORK REGISTER'!$B13) -> 1
A14: 11 | B14: =IF(G14<>"",E14&F14&"."&G14,E14&F14) -> GEN1.12 | C14: DN01B1700001 | D14: Lot01 | E14: GEN | F14: 1 | G14: 12 | H14: Modification of Civil Work in Telecommunication Room at OR14 | I14: - | K14: Station | L14: MDW-39253 | M14: 46235 | O14: =COUNTIF('02 Design'!$C$5:$C$366,'00 MASTER WORK REGISTER'!$B14) -> 1
A15: 12 | B15: =IF(G15<>"",E15&F15&"."&G15,E15&F15) -> GEN1.13 | C15: DN01B1700001 | D15: Lot01 | E15: GEN | F15: 1 | G15: 13 | H15: Modification in Staff Mess Room at OR13-OR17 | I15: - | K15: Station | L15: MDW-39254 | M15: 46235 | O15: =COUNTIF('02 Design'!$C$5:$C$366,'00 MASTER WORK REGISTER'!$B15) -> 1
A16: 13 | B16: =IF(G16<>"",E16&F16&"."&G16,E16&F16) -> GEN1.14 | C16: DN01B1700001 | D16: Lot01 | E16: GEN | F16: 1 | G16: 14 | H16: Modification in Staff Mess Room at OR18-OR22 | I16: - | K16: Station | L16: MDW-39255 | M16: 46235 | O16: =COUNTIF('02 Design'!$C$5:$C$366,'00 MASTER WORK REGISTER'!$B16) -> 1
A17: 14 | B17: =IF(G17<>"",E17&F17&"."&G17,E17&F17) -> GEN1.15 | C17: DN01B1700001 | D17: Lot01 | E17: GEN | F17: 1 | G17: 15 | H17: Modification in Staff Mess Room at OR23-OR29 | I17: - | K17: Station | L17: MDW-39256 | M17: 46235 | O17: =COUNTIF('02 Design'!$C$5:$C$366,'00 MASTER WORK REGISTER'!$B17) -> 1
A18: 15 | B18: =IF(G18<>"",E18&F18&"."&G18,E18&F18) -> GEN1.16 | C18: DN01B1700001 | D18: Lot01 | E18: GEN | F18: 1 | G18: 16 | H18: Modification of Air Conditioning in CER and SER at OR13-OR19 | I18: - | K18: Station | L18: MDW-39257 | M18: 46235 | O18: =COUNTIF('02 Design'!$C$5:$C$366,'00 MASTER WORK REGISTER'!$B18) -> 1
A19: 16 | B19: =IF(G19<>"",E19&F19&"."&G19,E19&F19) -> GEN1.17 | C19: DN01B1700001 | D19: Lot01 | E19: GEN | F19: 1 | G19: 17 | H19: Modification of Air Conditioning in CER and SER at OR20-OR22 | I19: - | K19: Station | L19: MDW-39258 | M19: 46235 | O19: =COUNTIF('02 Design'!$C$5:$C$366,'00 MASTER WORK REGISTER'!$B19) -> 1
A20: 17 | B20: =IF(G20<>"",E20&F20&"."&G20,E20&F20) -> GEN1.19 | C20: DN01B1700001 | D20: Lot01 | E20: GEN | F20: 1 | G20: 19 | H20: Modification of Air Conditioning in CER and SER at OR23-OR29 | I20: - | K20: Station | L20: MDW-39259 | M20: 46235 | O20: =COUNTIF('02 Design'!$C$5:$C$366,'00 MASTER WORK REGISTER'!$B20) -> 1
A21: 18 | B21: =IF(G21<>"",E21&F21&"."&G21,E21&F21) -> GEN1.20 | C21: DN01B1700001 | D21: Lot01 | E21: GEN | F21: 1 | G21: 20 | H21: Modification of Air Conditioning in M&E Room at OCC Building | I21: - | K21: Depot | L21: MDW-39260 | M21: 46235 | O21: =COUNTIF('02 Design'!$C$5:$C$366,'00 MASTER WORK REGISTER'!$B21) -> 1
A22: 19 | B22: =IF(G22<>"",E22&F22&"."&G22,E22&F22) -> GEN2 | C22: DN01B1700002 | D22: Lot01 | E22: GEN | F22: 2 | H22: Rooms and Building Service Systems Modification in Depot Area | I22: - | K22: Depot | L22: MDW-39261 | M22: 46235 | O22: =COUNTIF('02 Design'!$C$5:$C$366,'00 MASTER WORK REGISTER'!$B22) -> 17
A23: 20 | B23: =IF(G23<>"",E23&F23&"."&G23,E23&F23) -> GEN3 | C23: DN01B1700003 | D23: Lot01 | E23: GEN | F23: 3 | H23: Cable Containment Modification | I23: - | K23: Station | L23: MDW-39200-31 | M23: 45805 | O23: =COUNTIF('02 Design'!$C$5:$C$366,'00 MASTER WORK REGISTER'!$B23) -> 32
A24: 21 | B24: =IF(G24<>"",E24&F24&"."&G24,E24&F24) -> GEN4 | C24: DN01B1700004 | D24: Lot01 | E24: GEN | F24: 4 | H24: Training Room and Workshop Room | I24: - | K24: Depot | L24: - | M24: 46113 | O24: =COUNTIF('02 Design'!$C$5:$C$366,'00 MASTER WORK REGISTER'!$B24) -> 2
A25: 22 | B25: =IF(G25<>"",E25&F25&"."&G25,E25&F25) -> GEN4.0 | C25: DN01B1700004 | D25: Lot01 | E25: GEN | F25: 4 | G25: 0 | H25: Modification Works for Training Room at Ratchada Station | I25: ประธาน | K25: BL | L25: MDW-39242 | M25: 46113 | O25: =COUNTIF('02 Design'!$C$5:$C$366,'00 MASTER WORK REGISTER'!$B25) -> 1
A26: 23 | B26: =IF(G26<>"",E26&F26&"."&G26,E26&F26) -> GEN4.1 | C26: DN01B1700004 | D26: Lot01 | E26: GEN | F26: 4 | G26: 1 | H26: AFC Training Room Modification - Civil & AR | I26: สหชาติ | J26: MWS | K26: Depot | L26: MDW-39244 | M26: 46255 | O26: =COUNTIF('02 Design'!$C$5:$C$366,'00 MASTER WORK REGISTER'!$B26) -> 1
A27: 24 | B27: =IF(G27<>"",E27&F27&"."&G27,E27&F27) -> GEN4.2 | C27: DN01B1700004 | D27: Lot01 | E27: GEN | F27: 4 | G27: 2 | H27: AFC Training Room Modification - Building Services | I27: ประธาน | J27: MWS | K27: Depot | L27: MDW-39245 | M27: 46255 | O27: =COUNTIF('02 Design'!$C$5:$C$366,'00 MASTER WORK REGISTER'!$B27) -> 1
A28: 25 | B28: =IF(G28<>"",E28&F28&"."&G28,E28&F28) -> GEN5 | C28: DN01B1700005 | D28: Lot01 | E28: GEN | F28: 5 | H28: Raised Floor | I28: สหชาติ | K28: Station | L28: MDW-39235 | M28: 46174 | O28: =COUNTIF('02 Design'!$C$5:$C$366,'00 MASTER WORK REGISTER'!$B28) -> 1
A29: 26 | B29: =IF(G29<>"",E29&F29&"."&G29,E29&F29) -> GEN6 | C29: DN01B1700006 | D29: Lot01 | E29: GEN | F29: 6 | H29: Wayside Cable Containment in Depot | I29: - | L29: MDW-39271 | M29: 46075 | O29: =COUNTIF('02 Design'!$C$5:$C$366,'00 MASTER WORK REGISTER'!$B29) -> 2
A30: 27 | B30: =IF(G30<>"",E30&F30&"."&G30,E30&F30) -> GEN6.1 | C30: DN01B1700006 | D30: Lot01 | E30: GEN | F30: 6 | G30: 1 | H30: PSY Wayside Cable Containment for 24 Kv Cable under the Depot slab | I30: ประธาน | L30: MDW-39269 | M30: 46075 | N30: CANCLE | O30: =COUNTIF('02 Design'!$C$5:$C$366,'00 MASTER WORK REGISTER'!$B30) -> 1
A31: 28 | B31: =IF(G31<>"",E31&F31&"."&G31,E31&F31) -> GEN6.2 | C31: DN01B1700006 | D31: Lot01 | E31: GEN | F31: 6 | G31: 2 | H31: COM/SIG Wayside Cable Containment in the Depot | I31: มนตรี/ประธาน | L31: MDW-39270 | M31: 46075 | N31: CANCLE | O31: =COUNTIF('02 Design'!$C$5:$C$366,'00 MASTER WORK REGISTER'!$B31) -> 1
A32: 29 | B32: =IF(G32<>"",E32&F32&"."&G32,E32&F32) -> GEN7 | C32: DN01B1700007 | D32: Lot01 | E32: GEN | F32: 7 | H32: Dangerous Waste Storage Building in Depot | I32: สหชาติ/ประธาน | L32: - | M32: 46285 | O32: =COUNTIF('02 Design'!$C$5:$C$366,'00 MASTER WORK REGISTER'!$B32) -> 0
A33: 30 | B33: =IF(G33<>"",E33&F33&"."&G33,E33&F33) -> GEN7.1 | C33: DN01B1700007 | D33: Lot01 | E33: GEN | F33: 7 | G33: 1 | H33: Dangerous Waste Storage Building in Depot - Civil & AR | I33: สหชาติ | L33: DWE-39024 | M33: 46285 | O33: =COUNTIF('02 Design'!$C$5:$C$366,'00 MASTER WORK REGISTER'!$B33) -> 1
A34: 31 | B34: =IF(G34<>"",E34&F34&"."&G34,E34&F34) -> GEN7.2 | C34: DN01B1700007 | D34: Lot01 | E34: GEN | F34: 7 | G34: 2 | H34: Dangerous Waste Storage Building in Depot - Building service | I34: ประธาน | L34: DWE-39025 | M34: 46285 | O34: =COUNTIF('02 Design'!$C$5:$C$366,'00 MASTER WORK REGISTER'!$B34) -> 1
A35: 32 | B35: =IF(G35<>"",E35&F35&"."&G35,E35&F35) -> GEN8 | C35: DN01B1700008 | D35: Lot01 | E35: GEN | F35: 8 | H35: General Waste Storage Building in Depot | I35: สหชาติ/ประธาน | L35: - | M35: 46285 | O35: =COUNTIF('02 Design'!$C$5:$C$366,'00 MASTER WORK REGISTER'!$B35) -> 0
A36: 33 | B36: =IF(G36<>"",E36&F36&"."&G36,E36&F36) -> GEN8.1 | C36: DN01B1700008 | D36: Lot01 | E36: GEN | F36: 8 | G36: 1 | H36: General Waste Storage Building in Depot - Civil & AR | I36: สหชาติ | L36: DWE-39026 | M36: 46285 | O36: =COUNTIF('02 Design'!$C$5:$C$366,'00 MASTER WORK REGISTER'!$B36) -> 1
A37: 34 | B37: =IF(G37<>"",E37&F37&"."&G37,E37&F37) -> GEN8.2 | C37: DN01B1700008 | D37: Lot01 | E37: GEN | F37: 8 | G37: 2 | H37: General Waste Storage Building in Depot - Building service | I37: ประธาน | L37: DWE-39025 | M37: 46285 | O37: =COUNTIF('02 Design'!$C$5:$C$366,'00 MASTER WORK REGISTER'!$B37) -> 1
A38: 35 | B38: =IF(G38<>"",E38&F38&"."&G38,E38&F38) -> GEN9 | C38: DN01B1700009 | D38: Lot01 | E38: GEN | F38: 9 | H38: Operation Support Equipment | I38: สมศักดิ์ | L38: DWE-39021 | M38: 46255 | O38: =COUNTIF('02 Design'!$C$5:$C$366,'00 MASTER WORK REGISTER'!$B38) -> 1
A39: 36 | B39: =IF(G39<>"",E39&F39&"."&G39,E39&F39) -> GEN10.1 | C39: DN01B1700010 | D39: Lot01 | E39: GEN | F39: 10 | G39: 1 | H39: Graphic and Signage Station | I39: สหชาติ | L39: GRS-39001-40 | M39: 46255 | O39: =COUNTIF('02 Design'!$C$5:$C$366,'00 MASTER WORK REGISTER'!$B39) -> 0
A40: 37 | B40: =IF(G40<>"",E40&F40&"."&G40,E40&F40) -> GEN10.2 | C40: DN01B1700010 | D40: Lot01 | E40: GEN | F40: 10 | G40: 2 | H40: Graphic and Signage Mainline & IVS,VS | I40: สหชาติ | L40: GRS-39001-40 | M40: 46255 | O40: =COUNTIF('02 Design'!$C$5:$C$366,'00 MASTER WORK REGISTER'!$B40) -> 0
A41: 38 | B41: =IF(G41<>"",E41&F41&"."&G41,E41&F41) -> GEN10.3 | C41: DN01B1700010 | D41: Lot01 | E41: GEN | F41: 10 | G41: 3 | H41: Graphic and Signage Depot | I41: สหชาติ | L41: GRS-39001-40 | M41: 46255 | O41: =COUNTIF('02 Design'!$C$5:$C$366,'00 MASTER WORK REGISTER'!$B41) -> 0
A42: 39 | B42: =IF(G42<>"",E42&F42&"."&G42,E42&F42) -> GEN11 | C42: DN01B1700011 | D42: Lot01 | E42: GEN | F42: 11 | H42: Earthing and Bonding Modification | I42: ประธาน | L42: MDW-39289 | M42: 46082 | O42: =COUNTIF('02 Design'!$C$5:$C$366,'00 MASTER WORK REGISTER'!$B42) -> 3
A43: 40 | B43: =IF(G43<>"",E43&F43&"."&G43,E43&F43) -> GEN12 | C43: DN01B1700012 | D43: Lot01 | E43: GEN | F43: 12 | H43: Mainline Cable Trough Modification on East Section | I43: - | L43: - | M43: 46195 | O43: =COUNTIF('02 Design'!$C$5:$C$366,'00 MASTER WORK REGISTER'!$B43) -> 1
A44: 41 | B44: =IF(G44<>"",E44&F44&"."&G44,E44&F44) -> GEN12.1 | C44: DN01B1700012 | D44: Lot01 | E44: GEN | F44: 12 | G44: 1 | H44: Main Line Cable Trough Modification (PSY) | I44: มนต์ชัย | L44: MDW-39233 | M44: 46195 | O44: =COUNTIF('02 Design'!$C$5:$C$366,'00 MASTER WORK REGISTER'!$B44) -> 1
A45: 42 | B45: =IF(G45<>"",E45&F45&"."&G45,E45&F45) -> GEN12.2 | C45: DN01B1700012 | D45: Lot01 | E45: GEN | F45: 12 | G45: 2 | H45: Main Line Cable Trough Modification (SIG/COM) | I45: มนตรี | L45: MDW-39234 | M45: 46195 | O45: =COUNTIF('02 Design'!$C$5:$C$366,'00 MASTER WORK REGISTER'!$B45) -> 1
A46: 43 | B46: =IF(G46<>"",E46&F46&"."&G46,E46&F46) -> GEN13 | C46: DN01B1700013 | D46: Lot01 | E46: GEN | F46: 13 | H46: Bird Protection System | I46: สหชาติ | L46: MDW-39236 | M46: 46345 | O46: =COUNTIF('02 Design'!$C$5:$C$366,'00 MASTER WORK REGISTER'!$B46) -> 1
A47: 44 | B47: =IF(G47<>"",E47&F47&"."&G47,E47&F47) -> GEN14 | C47: DN01B1700014 | D47: Lot01 | E47: GEN | F47: 14 | H47: Train Crew Office at Thailand Cultural Centre Station | I47: สหชาติ | L47: - | M47: 46255 | O47: =COUNTIF('02 Design'!$C$5:$C$366,'00 MASTER WORK REGISTER'!$B47) -> 0
A48: 45 | B48: =IF(G48<>"",E48&F48&"."&G48,E48&F48) -> GEN14.1 | C48: DN01B1700014 | D48: Lot01 | E48: GEN | F48: 14 | G48: 1 | H48: Driver Train Simulation Room and Train Crew Office at OR18 - Civil & AR | I48: สหชาติ | L48: MDW-39240 | M48: 46255 | O48: =COUNTIF('02 Design'!$C$5:$C$366,'00 MASTER WORK REGISTER'!$B48) -> 1
A49: 46 | B49: =IF(G49<>"",E49&F49&"."&G49,E49&F49) -> GEN14.2 | C49: DN01B1700014 | D49: Lot01 | E49: GEN | F49: 14 | G49: 2 | H49: Driver Train Simulation Room and Train Crew Office at OR18 - Building Services | I49: ประธาน | L49: MDW-39241 | M49: 46255 | O49: =COUNTIF('02 Design'!$C$5:$C$366,'00 MASTER WORK REGISTER'!$B49) -> 1
A50: 47 | B50: =IF(G50<>"",E50&F50&"."&G50,E50&F50) -> GEN15 | C50: DN01B1700015 | D50: Lot01 | E50: GEN | F50: 15 | H50: Access Panel Closeout for Traction Substation Room in Main Workshop | I50: สหชาติ | K50: Depot | L50: MDW-39239 | M50: 46105 | O50: =COUNTIF('02 Design'!$C$5:$C$366,'00 MASTER WORK REGISTER'!$B50) -> 1
A51: 48 | B51: =IF(G51<>"",E51&F51&"."&G51,E51&F51) -> GEN16 | C51: DN01B1700016 | D51: Lot01 | E51: GEN | F51: 16 | H51: Level Crossing at Turnout | I51: กำพล | L51: MDW-39232 | M51: 46255 | N51: CANCLE | O51: =COUNTIF('02 Design'!$C$5:$C$366,'00 MASTER WORK REGISTER'!$B51) -> 1
A52: 49 | B52: =IF(G52<>"",E52&F52&"."&G52,E52&F52) -> GEN17 | C52: DN01B1700017 | D52: Lot01 | E52: GEN | F52: 17 | H52: Track Slab Crossing | I52: ชฎิล/กำพล | L52: MDW-39232 | M52: 46255 | N52: CANCLE | O52: =COUNTIF('02 Design'!$C$5:$C$366,'00 MASTER WORK REGISTER'!$B52) -> 0
A53: 50 | B53: =IF(G53<>"",E53&F53&"."&G53,E53&F53) -> GEN18 | C53: DN01B1700018 | D53: Lot01 | E53: GEN | F53: 18 | H53: Eye Adaptation Lighting (Lighting at Tunnel to Expose) | I53: ประธาน | L53: MDW-39243 | M53: 46345 | O53: =COUNTIF('02 Design'!$C$5:$C$366,'00 MASTER WORK REGISTER'!$B53) -> 1
A54: 51 | B54: =IF(G54<>"",E54&F54&"."&G54,E54&F54) -> GEN19 | C54: DN01B1700019 | D54: Lot01 | E54: GEN | F54: 19 | H54: Train Simulation Room and AFC Training Room | I54: สหชาติ/ประธาน | L54: - | M54: 46255 | O54: =COUNTIF('02 Design'!$C$5:$C$366,'00 MASTER WORK REGISTER'!$B54) -> 0
A55: 52 | B55: =IF(G55<>"",E55&F55&"."&G55,E55&F55) -> GEN19.1 | C55: DN01B1700019 | D55: Lot01 | E55: GEN | F55: 19 | G55: 1 | H55: Modification AFC Training Center at OR19 - Civil & AR | I55: สหชาติ | J55: MWS | L55: MDW-39244 | M55: 46356 | O55: =COUNTIF('02 Design'!$C$5:$C$366,'00 MASTER WORK REGISTER'!$B55) -> 1
A56: 53 | B56: =IF(G56<>"",E56&F56&"."&G56,E56&F56) -> GEN19.2 | C56: DN01B1700019 | D56: Lot01 | E56: GEN | F56: 19 | G56: 2 | H56: Modification AFC Training Center at OR19 - Building Services | I56: ประธาน | J56: MWS | L56: MDW-39245 | M56: 46356 | O56: =COUNTIF('02 Design'!$C$5:$C$366,'00 MASTER WORK REGISTER'!$B56) -> 1
A57: 54 | B57: =IF(G57<>"",E57&F57&"."&G57,E57&F57) -> GEN20 | C57: DN01B1700020 | D57: Lot01 | E57: GEN | F57: 20 | H57: Dormitory Cable Containments (if any) | I57: - | L57: - | M57: - | N57: CANCLE | O57: =COUNTIF('02 Design'!$C$5:$C$366,'00 MASTER WORK REGISTER'!$B57) -> 0
A58: 55 | B58: =IF(G58<>"",E58&F58&"."&G58,E58&F58) -> GEN21 | C58: DN01B1700021 | D58: Lot01 | E58: GEN | F58: 21 | H58: Project Information Management System (PIMS) | I58: บัณฑิต | M58: 45565 | O58: =COUNTIF('02 Design'!$C$5:$C$366,'00 MASTER WORK REGISTER'!$B58) -> 0
A59: 56 | B59: =IF(G59<>"",E59&F59&"."&G59,E59&F59) -> GEN22 | C59: DN01B1700022 | D59: Lot01 | E59: GEN | F59: 22 | H59: Central BEMS for the MRT Orange Line System | I59: บัณฑิต | L59: MDW-39237 | M59: 46255 | O59: =COUNTIF('02 Design'!$C$5:$C$366,'00 MASTER WORK REGISTER'!$B59) -> 2
A60: 57 | B60: =IF(G60<>"",E60&F60&"."&G60,E60&F60) -> GEN23 | C60: DN01B1700023 | D60: Lot01 | E60: GEN | F60: 23 | H60: Asset Information | I60: บัณฑิต | M60: 46345 | O60: =COUNTIF('02 Design'!$C$5:$C$366,'00 MASTER WORK REGISTER'!$B60) -> 0
A61: 58 | B61: =IF(G61<>"",E61&F61&"."&G61,E61&F61) -> PSD1 | C61: DN01B1700031 | D61: Lot01 | E61: PSD | F61: 1 | H61: Holes for PSD Cable Wiring | I61: กำพล | L61: MDW-39282 | M61: 46255 | N61: CANCLE | O61: =COUNTIF('02 Design'!$C$5:$C$366,'00 MASTER WORK REGISTER'!$B61) -> 1
A62: 59 | B62: =IF(G62<>"",E62&F62&"."&G62,E62&F62) -> PSD2 | C62: DN01B1700032 | D62: Lot01 | E62: PSD | F62: 2 | H62: Rubber Gap Fillers on Platform Edge | I62: กำพล | L62: MDW-39004 | M62: 46255 | O62: =COUNTIF('02 Design'!$C$5:$C$366,'00 MASTER WORK REGISTER'!$B62) -> 1
A63: 60 | B63: =IF(G63<>"",E63&F63&"."&G63,E63&F63) -> PSD3 | C63: DN01B1700033 | D63: Lot01 | E63: PSD | F63: 3 | H63: Platform Finishing | I63: กำพล | L63: MDW-39280 | M63: 46255 | O63: =COUNTIF('02 Design'!$C$5:$C$366,'00 MASTER WORK REGISTER'!$B63) -> 1
A64: 61 | B64: =IF(G64<>"",E64&F64&"."&G64,E64&F64) -> PSD4 | C64: DN01B1700034 | D64: Lot01 | E64: PSD | F64: 4 | H64: Cladding Barrier between EWD and Station Structure | I64: กำพล | L64: MDW-39281 | M64: 46255 | O64: =COUNTIF('02 Design'!$C$5:$C$366,'00 MASTER WORK REGISTER'!$B64) -> 1
A65: 62 | B65: =IF(G65<>"",E65&F65&"."&G65,E65&F65) -> AFC1 | C65: DN01B1700041 | D65: Lot01 | E65: AFC | F65: 1 | H65: Park and Ride System | I65: บัณฑิต/สหชาติ | L65: - | M65: 46315 | N65: CANCLE | O65: =COUNTIF('02 Design'!$C$5:$C$366,'00 MASTER WORK REGISTER'!$B65) -> 0
A66: 63 | B66: =IF(G66<>"",E66&F66&"."&G66,E66&F66) -> AFC2 | C66: DN01B1700042 | D66: Lot01 | E66: AFC | F66: 2 | H66: Ticket Issuing Machine (TIM) Wall Opening and Closing | I66: สหชาติ | L66: MDW-39276 | M66: 46285 | O66: =COUNTIF('02 Design'!$C$5:$C$366,'00 MASTER WORK REGISTER'!$B66) -> 1
A67: 64 | B67: =IF(G67<>"",E67&F67&"."&G67,E67&F67) -> AFC3 | C67: DN01B1700043 | D67: Lot01 | E67: AFC | F67: 3 | H67: Balustrade Modification Along AFC Gate Line | I67: สหชาติ | L67: MDW-39279 | M67: 46285 | O67: =COUNTIF('02 Design'!$C$5:$C$366,'00 MASTER WORK REGISTER'!$B67) -> 2
A68: 65 | B68: =IF(G68<>"",E68&F68&"."&G68,E68&F68) -> AFC4 | C68: DN01B1700044 | D68: Lot01 | E68: AFC | F68: 4 | H68: Underfloor Embedded Duct Modification for AFC Gates Line | I68: สหชาติ | L68: MDW-39278 | M68: 46285 | O68: =COUNTIF('02 Design'!$C$5:$C$366,'00 MASTER WORK REGISTER'!$B68) -> 1
A69: 66 | B69: =IF(G69<>"",E69&F69&"."&G69,E69&F69) -> SIG1 | C69: DN01B1700051 | D69: Lot01 | E69: SIG | F69: 1 | H69: Test Track Shelters and Test Track Building | I69: สหชาติ | K69: Depot | L69: MDW-39002 | M69: 46195 | O69: =COUNTIF('02 Design'!$C$5:$C$366,'00 MASTER WORK REGISTER'!$B69) -> 3
A70: 67 | B70: =IF(G70<>"",E70&F70&"."&G70,E70&F70) -> SIG2 | C70: DN01B1700052 | D70: Lot01 | E70: SIG | F70: 2 | H70: Rearrangement of track crossing walkway at stabling yard to consistent with the layout of 4-car train parking | I70: กำพล | K70: Depot | L70: MDW-39293 | M70: 46195 | O70: =COUNTIF('02 Design'!$C$5:$C$366,'00 MASTER WORK REGISTER'!$B70) -> 1
A71: 68 | B71: =IF(G71<>"",E71&F71&"."&G71,E71&F71) -> SIG3 | C71: DN01B1700053 | D71: Lot01 | E71: SIG | F71: 3 | H71: Point Machine Foundation Construction | I71: กำพล | L71: MDW-39288 | M71: 46255 | O71: =COUNTIF('02 Design'!$C$5:$C$366,'00 MASTER WORK REGISTER'!$B71) -> 1
A72: 69 | B72: =IF(G72<>"",E72&F72&"."&G72,E72&F72) -> SIG4 | C72: DN01B1700054 | D72: Lot01 | E72: SIG | F72: 4 | H72: Modification of Depot Track Route Line to Stabling Yard | I72: สู่โชค | K72: Depot | L72: MDW-39001 | M72: 46195 | O72: =COUNTIF('02 Design'!$C$5:$C$366,'00 MASTER WORK REGISTER'!$B72) -> 1
A73: 70 | B73: =IF(G73<>"",E73&F73&"."&G73,E73&F73) -> SIG5 | C73: DN01B1700055 | D73: Lot01 | E73: SIG | F73: 5 | H73: Strobe Light at Buffer Stops | I73: ประธาน | L73: MDW-39287 | M73: 46255 | O73: =COUNTIF('02 Design'!$C$5:$C$366,'00 MASTER WORK REGISTER'!$B73) -> 1
A74: 71 | B74: =IF(G74<>"",E74&F74&"."&G74,E74&F74) -> DWE1 | C74: DN01B1800001 | D74: Lot01 | E74: DWE | F74: 1 | H74: Diesel Fuel Storage Tank for Maintenance Vehicle | I74: สมศักดิ์ | K74: Depot | L74: DWE-39016 | M74: 46285 | O74: =COUNTIF('02 Design'!$C$5:$C$366,'00 MASTER WORK REGISTER'!$B74) -> 1
A75: 72 | B75: =IF(G75<>"",E75&F75&"."&G75,E75&F75) -> DWE2 | C75: DN01B1800002 | D75: Lot01 | E75: DWE | F75: 2 | H75: Movable Height Maintenance Platform Vehicle (Boom Lift) | I75: สมศักดิ์ | K75: Depot | L75: DWE-39011 | M75: 46285 | O75: =COUNTIF('02 Design'!$C$5:$C$366,'00 MASTER WORK REGISTER'!$B75) -> 1
A76: 73 | B76: =IF(G76<>"",E76&F76&"."&G76,E76&F76) -> DWE3 | C76: DN01B1800003 | D76: Lot01 | E76: DWE | F76: 3 | H76: Fork Lift Vehicle | I76: สมศักดิ์ | K76: Depot | L76: DWE-39012 | M76: 46285 | O76: =COUNTIF('02 Design'!$C$5:$C$366,'00 MASTER WORK REGISTER'!$B76) -> 1
A77: 74 | B77: =IF(G77<>"",E77&F77&"."&G77,E77&F77) -> DWE4 | C77: DN01B1800004 | D77: Lot01 | E77: DWE | F77: 4 | H77: Compressed Air System and Portable Air Compressor for Depot | I77: สมศักดิ์ | K77: Depot | L77: DWE-39015 | M77: 46285 | O77: =COUNTIF('02 Design'!$C$5:$C$366,'00 MASTER WORK REGISTER'!$B77) -> 1
A78: 75 | B78: =IF(G78<>"",E78&F78&"."&G78,E78&F78) -> DWE5 | C78: DN01B1800005 | D78: Lot01 | E78: DWE | F78: 5 | H78: Pallet Storage Shelves in Hazardous Storage | I78: สมศักดิ์ | K78: Depot | L78: DWE-39017 | M78: 46285 | O78: =COUNTIF('02 Design'!$C$5:$C$366,'00 MASTER WORK REGISTER'!$B78) -> 0
A79: 76 | B79: =IF(G79<>"",E79&F79&"."&G79,E79&F79) -> DWE6 | C79: DN01B1800006 | D79: Lot01 | E79: DWE | F79: 6 | H79: Pallet Storage in Main Storage Room | I79: สมศักดิ์ | K79: Depot | L79: DWE-39017 | M79: 46285 | O79: =COUNTIF('02 Design'!$C$5:$C$366,'00 MASTER WORK REGISTER'!$B79) -> 6
A80: 77 | B80: =IF(G80<>"",E80&F80&"."&G80,E80&F80) -> DWE7 | C80: DN01B1800007 | D80: Lot01 | E80: DWE | F80: 7 | H80: Two-Tier Shelf | I80: สมศักดิ์ | K80: Depot | L80: DWE-39017 | M80: 46285 | O80: =COUNTIF('02 Design'!$C$5:$C$366,'00 MASTER WORK REGISTER'!$B80) -> 0
A81: 78 | B81: =IF(G81<>"",E81&F81&"."&G81,E81&F81) -> DWE8 | C81: DN01B1800008 | D81: Lot01 | E81: DWE | F81: 8 | H81: Tool Storage | I81: สมศักดิ์ | K81: Depot | L81: DWE-39017 | M81: 46285 | O81: =COUNTIF('02 Design'!$C$5:$C$366,'00 MASTER WORK REGISTER'!$B81) -> 0
A82: 79 | B82: =IF(G82<>"",E82&F82&"."&G82,E82&F82) -> DWE9 | C82: DN01B1800009 | D82: Lot01 | E82: DWE | F82: 9 | H82: Repair Equipment | I82: สมศักดิ์ | K82: Depot | L82: DWE-39018 | M82: 46285 | O82: =COUNTIF('02 Design'!$C$5:$C$366,'00 MASTER WORK REGISTER'!$B82) -> 1
A83: 80 | B83: =IF(G83<>"",E83&F83&"."&G83,E83&F83) -> DWE10 | C83: DN01B1800010 | D83: Lot01 | E83: DWE | F83: 10 | H83: Oil & Grease Disposal | I83: สมศักดิ์ | K83: Depot | L83: DWE-39020 | M83: 46285 | O83: =COUNTIF('02 Design'!$C$5:$C$366,'00 MASTER WORK REGISTER'!$B83) -> 1
A84: 81 | B84: =IF(G84<>"",E84&F84&"."&G84,E84&F84) -> DWE11 | C84: DN01B1800011 | D84: Lot01 | E84: DWE | F84: 11 | H84: Grease Dispensers | I84: สมศักดิ์ | K84: Depot | L84: DWE-39020 | M84: 46285 | O84: =COUNTIF('02 Design'!$C$5:$C$366,'00 MASTER WORK REGISTER'!$B84) -> 0
A85: 82 | B85: =IF(G85<>"",E85&F85&"."&G85,E85&F85) -> DWE12 | C85: DN01B1800012 | D85: Lot01 | E85: DWE | F85: 12 | H85: Waste Disposal | I85: สมศักดิ์ | K85: Depot | L85: DWE-39020 | M85: 46285 | O85: =COUNTIF('02 Design'!$C$5:$C$366,'00 MASTER WORK REGISTER'!$B85) -> 0
A86: 83 | B86: =IF(G86<>"",E86&F86&"."&G86,E86&F86) -> DWE13 | C86: DN01B1800013 | D86: Lot01 | E86: DWE | F86: 13 | H86: Safety Provision for Maintenance Pits | I86: สหชาติ | K86: Depot | L86: MDW-39305 | M86: 46285 | O86: =COUNTIF('02 Design'!$C$5:$C$366,'00 MASTER WORK REGISTER'!$B86) -> 2
A87: 84 | B87: =IF(G87<>"",E87&F87&"."&G87,E87&F87) -> DWE14 | C87: DN01B1800014 | D87: Lot01 | E87: DWE | F87: 14 | H87: Pit Drainage System in Main Workshop | I87: สมศักดิ์ | K87: Depot | L87: DWE-39xxx | M87: 46285 | N87: CANCLE | O87: =COUNTIF('02 Design'!$C$5:$C$366,'00 MASTER WORK REGISTER'!$B87) -> 1
A88: 85 | B88: =IF(G88<>"",E88&F88&"."&G88,E88&F88) -> DWE15 | C88: DN01B1800015 | D88: Lot01 | E88: DWE | F88: 15 | H88: Provision of Civil Works and Building Services to support Train Washing Equipment | I88: สหชาติ | K88: Depot | L88: DWE-39023 | M88: 46235 | O88: =COUNTIF('02 Design'!$C$5:$C$366,'00 MASTER WORK REGISTER'!$B88) -> 1
A89: 86 | B89: =IF(G89<>"",E89&F89&"."&G89,E89&F89) -> DWE16 | C89: DN01B1800016 | D89: Lot01 | E89: DWE | F89: 16 | H89: Overhead Traveling Crane | I89: สมศักดิ์ | K89: Depot | L89: DWE-39013 | M89: 46285 | O89: =COUNTIF('02 Design'!$C$5:$C$366,'00 MASTER WORK REGISTER'!$B89) -> 3
A90: 87 | B90: =IF(G90<>"",E90&F90&"."&G90,E90&F90) -> DWE17 | C90: DN01B1800017 | D90: Lot01 | E90: DWE | F90: 17 | H90: Vehicle Inspection and Servicing Facilities | I90: สมศักดิ์ | K90: Depot | L90: DWE-39009 | M90: 46285 | N90: Rail/Road Shunting Vehicel | O90: =COUNTIF('02 Design'!$C$5:$C$366,'00 MASTER WORK REGISTER'!$B90) -> 1
A91: 88 | B91: =IF(G91<>"",E91&F91&"."&G91,E91&F91) -> DWE18 | C91: DN01B1800018 | D91: Lot01 | E91: DWE | F91: 18 | H91: Permanent Way Maintenance Facility | I91: สมศักดิ์ | K91: Depot | L91: DWE-39014 | M91: 46285 | N91: Trackwork Equipment and hand tools | O91: =COUNTIF('02 Design'!$C$5:$C$366,'00 MASTER WORK REGISTER'!$B91) -> 1
A92: 89 | B92: =IF(G92<>"",E92&F92&"."&G92,E92&F92) -> DWE19 | C92: DN01B1800019 | D92: Lot01 | E92: DWE | F92: 19 | H92: Permanent Way Vehicles | I92: สมศักดิ์ | K92: Depot | L92: - | M92: 46285 | O92: =COUNTIF('02 Design'!$C$5:$C$366,'00 MASTER WORK REGISTER'!$B92) -> 0
A93: 90 | B93: =IF(G93<>"",E93&F93&"."&G93,E93&F93) -> DWE19.1 | C93: DN01B1800019 | D93: Lot01 | E93: DWE | F93: 19 | G93: 1 | H93: Shunting Locomotive | I93: สมศักดิ์ | K93: Depot | L93: DWE-39001 | M93: 46285 | O93: =COUNTIF('02 Design'!$C$5:$C$366,'00 MASTER WORK REGISTER'!$B93) -> 1
A94: 91 | B94: =IF(G94<>"",E94&F94&"."&G94,E94&F94) -> DWE19.2 | C94: DN01B1800019 | D94: Lot01 | E94: DWE | F94: 19 | G94: 2 | H94: Tunnel Inspection and Cleaning Vehicle | I94: สมศักดิ์ | K94: Depot | L94: DWE-39002 | M94: 46285 | O94: =COUNTIF('02 Design'!$C$5:$C$366,'00 MASTER WORK REGISTER'!$B94) -> 1
A95: 92 | B95: =IF(G95<>"",E95&F95&"."&G95,E95&F95) -> DWE19.3 | C95: DN01B1800019 | D95: Lot01 | E95: DWE | F95: 19 | G95: 3 | H95: Hi/Rail Maintenance Vehicle | I95: สมศักดิ์ | K95: Depot | L95: DWE-39003 | M95: 46285 | O95: =COUNTIF('02 Design'!$C$5:$C$366,'00 MASTER WORK REGISTER'!$B95) -> 1
A96: 93 | B96: =IF(G96<>"",E96&F96&"."&G96,E96&F96) -> DWE19.4 | C96: DN01B1800019 | D96: Lot01 | E96: DWE | F96: 19 | G96: 4 | H96: Flat wagon | I96: สมศักดิ์ | K96: Depot | L96: DWE-39004 | M96: 46285 | O96: =COUNTIF('02 Design'!$C$5:$C$366,'00 MASTER WORK REGISTER'!$B96) -> 1
A97: 94 | B97: =IF(G97<>"",E97&F97&"."&G97,E97&F97) -> DWE19.5 | C97: DN01B1800019 | D97: Lot01 | E97: DWE | F97: 19 | G97: 5 | H97: Re-railing Equipment | I97: สมศักดิ์ | K97: Depot | L97: DWE-39005 | M97: 46285 | O97: =COUNTIF('02 Design'!$C$5:$C$366,'00 MASTER WORK REGISTER'!$B97) -> 1
A98: 95 | B98: =IF(G98<>"",E98&F98&"."&G98,E98&F98) -> DWE19.6 | C98: DN01B1800019 | D98: Lot01 | E98: DWE | F98: 19 | G98: 6 | H98: Self-Propelled Rail Based Inspection Vehicle | I98: สมศักดิ์ | K98: Depot | L98: DWE-39006 | M98: 46285 | O98: =COUNTIF('02 Design'!$C$5:$C$366,'00 MASTER WORK REGISTER'!$B98) -> 1
A99: 96 | B99: =IF(G99<>"",E99&F99&"."&G99,E99&F99) -> DWE19.7 | C99: DN01B1800019 | D99: Lot01 | E99: DWE | F99: 19 | G99: 7 | H99: Rail Head Grinding Machine Vehicle | I99: สมศักดิ์ | K99: Depot | L99: DWE-39007 | M99: 46285 | O99: =COUNTIF('02 Design'!$C$5:$C$366,'00 MASTER WORK REGISTER'!$B99) -> 1
A100: 97 | B100: =IF(G100<>"",E100&F100&"."&G100,E100&F100) -> DWE19.8 | C100: DN01B1800019 | D100: Lot01 | E100: DWE | F100: 19 | G100: 8 | H100: Multi Measuring Rail Vehicle | I100: สมศักดิ์ | K100: Depot | L100: DWE-39008 | M100: 46285 | N100: CANCLE | O100: =COUNTIF('02 Design'!$C$5:$C$366,'00 MASTER WORK REGISTER'!$B100) -> 1
A101: 98 | B101: =IF(G101<>"",E101&F101&"."&G101,E101&F101) -> DWE19.9 | C101: DN01B1800019 | D101: Lot01 | E101: DWE | F101: 19 | G101: 9 | H101: High Work Inspection Vehicle | I101: สมศักดิ์ | L101: DWE-39010 | M101: 46285 | N101: CANCLE | O101: =COUNTIF('02 Design'!$C$5:$C$366,'00 MASTER WORK REGISTER'!$B101) -> 1
...

Sheet 01 Summary
L1: D | M1: 0.1 | O1: P | P1: 0.1 | R1: M | S1: 0.1 | U1: C&I | V1: 0.6 | X1: T | Y1: 0.05 | AA1: TP | AB1: 0.01 | AD1: I | AE1: 0.01 | AG1: TR | AH1: 0.03 | AK1: =M1+P1+S1+V1+Y1+AB1+AE1+AH1 -> 1
L2: Design | O2: Procurement | R2: Manufacturing / Delivery Process | U2: Construction/Installation | X2: T&C | AA2: Test Procedure | AD2: Inspection | AG2: Test Report | AP2: CV/AR | AQ2: E&M | AR2: CV/AR+E&M
B3: No. | C3: Design Submission | D3: Lot No. | E3: Code | F3: System | G3: Activity Name | H3: CK Responsible Person | I3: Priority | J3: Location | K3: Expected Completion Month | L3: Design (PLAN) | M3: Design (%) | N3: Design (Status) | O3: Procurement (PLAN) | P3: Procurement (%) | Q3: Procurement (Status) | R3: Manufacturing / Delivery Process (PLAN) | S3: Manufacturing / Delivery Process (%) | T3: Manufacturing / Delivery (Status) | U3: Construction /Installation (PLAN) | V3: Construction /Installation (%) | W3: Construction /Installation (Status) | X3: T&C (PLAN) | Y3: T&C (%) | Z3: T&C (Status) | AA3: Test Procedure (PLAN) | AB3: Test Procedure (%) | AC3: Test Procedure (Status) | AD3: Inspection (PLAN) | AE3: Inspection (%) | AF3: Inspection (Status) | AG3: Test Report (PLAN) | AH3: Test Report (%) | AI3: Test Report (Status) | AJ3: Forecast Finish | AK3: Overall (%) | AL3: Overall (Status) | AM3: Note | AN3: remark | AO3: Detail | AQ3: แผนก | AS3: de | AT3: pro | AU3: re
A4: 1 | B4: 1 | C4: =_xlfn.XLOOKUP($E4,'00 MASTER WORK REGISTER'!B:B,'00 MASTER WORK REGISTER'!L:L) -> MDW-39246-60 | D4: Lot01 | E4: GEN1 | F4: GEN | G4: =_xlfn.XLOOKUP($E4,'00 MASTER WORK REGISTER'!B:B,'00 MASTER WORK REGISTER'!H:H) -> Rooms and Building Service Systems Modification in Stations Area | H4: - | K4: =_xlfn.XLOOKUP($E4,'00 MASTER WORK REGISTER'!$B:$B,'00 MASTER WORK REGISTER'!$M:$M,"") -> 46235 | AK4: =IFERROR(SUMPRODUCT(($M$1:$AH$1),(M4:AH4))/SUMIF((M4:AH4),"<>",($M$1:$AH$1)),"") | AL4: =IF($AK4=1, "Completed", IF($K4<TODAY(), "Late", "On Schedule")) -> Late | AN4: =_xlfn.XLOOKUP($E4,'00 MASTER WORK REGISTER'!B:B,'00 MASTER WORK REGISTER'!N:N,"") -> 0 | AP4: =_xlfn.XLOOKUP($F4,#REF!,#REF!,"") -> #REF! | AS4: MDW-39246 | AT4: =_xlfn.XLOOKUP($AS4,'02 Design'!F:F,'02 Design'!AE:AE," ") -> MDW-69259 | AU4: =_xlfn.XLOOKUP($AS4,'02 Design'!F:F,'02 Design'!AF:AF," ") -> MDW-69260
A5: 2 | B5: 2 | C5: MDW-39246 | D5: Lot01 | E5: GEN1.1 | F5: GEN | G5: Power Outlet Installation in SOR, Ticket Office and Cash Handling for OR13 - OR17 | H5: ประธาน | K5: 46235 | L5: =O5-30 -> 46052 | M5: 1 | N5: =IF($M5=1, "Completed", IF($L5<TODAY(), "Late", "On Schedule")) -> Completed | O5: =U5-30 -> 46082 | P5: 1 | Q5: =IF($P5=1, "Completed", IF($O5<TODAY(), "Late", "On Schedule")) -> Completed | U5: 46112 | V5: 1 | W5: =IF($V5=1, "Completed", IF($U5<TODAY(), "Late", "On Schedule")) -> Completed | AA5: 46295 | AB5: 1 | AC5: =IF($AB5=1, "Completed", IF($AA5<TODAY(), "Late", "On Schedule")) -> Completed | AD5: 46326 | AE5: 1 | AF5: =IF($AE5=1, "Completed", IF($AD5<TODAY(), "Late", "On Schedule")) -> Completed | AG5: 46326 | AH5: 0 | AI5: =IF($AH5=1, "Completed", IF($AG5<TODAY(), "Late", "On Schedule")) -> On Schedule | AK5: =IFERROR(SUMPRODUCT(($M$1:$AH$1),(M5:AH5))/SUMIF((M5:AH5),"<>",($M$1:$AH$1)),"") -> 0.96470588 | AL5: =IF($AK5=1, "Completed", IF($K5<TODAY(), "Late", "On Schedule")) -> Late | AN5: =_xlfn.XLOOKUP($E5,'00 MASTER WORK REGISTER'!B:B,'00 MASTER WORK REGISTER'!N:N,"") -> 0 | AO5: เพิ่มปลั๊ก ที่ห้อง SOR/Ticket Office/Cash handling room | AS5: MDW-39246 | AT5: MDW-69259 | AU5: MDW-69260
A6: 3 | B6: 3 | C6: MDW-39247 | D6: Lot01 | E6: GEN1.2 | F6: GEN | G6: Power Outlet Installation in SOR, Ticket Office and Cash Handling for OR18 - OR22 | H6: ประธาน | K6: 46235 | L6: =O6-30 -> 46021 | M6: 1 | N6: =IF($M6=1, "Completed", IF($L6<TODAY(), "Late", "On Schedule")) -> Completed | O6: =U6-30 -> 46051 | P6: 1 | Q6: =IF($P6=1, "Completed", IF($O6<TODAY(), "Late", "On Schedule")) -> Completed | U6: 46081 | V6: 1 | W6: =IF($V6=1, "Completed", IF($U6<TODAY(), "Late", "On Schedule")) -> Completed | AA6: 46295 | AB6: 1 | AC6: =IF($AB6=1, "Completed", IF($AA6<TODAY(), "Late", "On Schedule")) -> Completed | AD6: 46326 | AE6: 1 | AF6: =IF($AE6=1, "Completed", IF($AD6<TODAY(), "Late", "On Schedule")) -> Completed | AG6: 46326 | AH6: 0 | AI6: =IF($AH6=1, "Completed", IF($AG6<TODAY(), "Late", "On Schedule")) -> On Schedule | AK6: =IFERROR(SUMPRODUCT(($M$1:$AH$1),(M6:AH6))/SUMIF((M6:AH6),"<>",($M$1:$AH$1)),"") -> 0.96470588 | AL6: =IF($AK6=1, "Completed", IF($K6<TODAY(), "Late", "On Schedule")) -> Late | AN6: =_xlfn.XLOOKUP($E6,'00 MASTER WORK REGISTER'!B:B,'00 MASTER WORK REGISTER'!N:N,"") -> 0 | AO6: เพิ่มปลั๊ก ที่ห้อง SOR/Ticket Office/Cash handling room | AS6: MDW-39247 | AT6: MDW-69259 | AU6: MDW-69261
A7: 4 | B7: 4 | C7: MDW-39248 | D7: Lot01 | E7: GEN1.3 | F7: GEN | G7: Power Outlet Installation in SOR, Ticket Office and Cash Handling for OR23 - OR29 | H7: ประธาน | K7: 46235 | L7: =O7-30 -> 46052 | M7: 1 | N7: =IF($M7=1, "Completed", IF($L7<TODAY(), "Late", "On Schedule")) -> Completed | O7: =U7-30 -> 46082 | P7: 1 | Q7: =IF($P7=1, "Completed", IF($O7<TODAY(), "Late", "On Schedule")) -> Completed | U7: 46112 | V7: 1 | W7: =IF($V7=1, "Completed", IF($U7<TODAY(), "Late", "On Schedule")) -> Completed | AA7: 46295 | AB7: 1 | AC7: =IF($AB7=1, "Completed", IF($AA7<TODAY(), "Late", "On Schedule")) -> Completed | AD7: 46326 | AE7: 1 | AF7: =IF($AE7=1, "Completed", IF($AD7<TODAY(), "Late", "On Schedule")) -> Completed | AG7: 46326 | AH7: 0 | AI7: =IF($AH7=1, "Completed", IF($AG7<TODAY(), "Late", "On Schedule")) -> On Schedule | AK7: =IFERROR(SUMPRODUCT(($M$1:$AH$1),(M7:AH7))/SUMIF((M7:AH7),"<>",($M$1:$AH$1)),"") -> 0.96470588 | AL7: =IF($AK7=1, "Completed", IF($K7<TODAY(), "Late", "On Schedule")) -> Late | AN7: =_xlfn.XLOOKUP($E7,'00 MASTER WORK REGISTER'!B:B,'00 MASTER WORK REGISTER'!N:N,"") -> 0 | AO7: เพิ่มปลั๊ก ที่ห้อง SOR/Ticket Office/Cash handling room | AS7: MDW-39248 | AT7: MDW-69259 | AU7: MDW-69262
A8: 5 | B8: 5 | C8: MDW-39252 | D8: Lot01 | E8: GEN1.4 | F8: GEN | G8: Modification of Fire Suppression System (N2) in Commerial Room at OR14 | H8: ประธาน | K8: 46235 | L8: =O8-30 -> 46021 | M8: 1 | N8: =IF($M8=1, "Completed", IF($L8<TODAY(), "Late", "On Schedule")) -> Completed | O8: =U8-30 -> 46051 | P8: 1 | Q8: =IF($P8=1, "Completed", IF($O8<TODAY(), "Late", "On Schedule")) -> Completed | U8: 46081 | V8: 1 | W8: =IF($V8=1, "Completed", IF($U8<TODAY(), "Late", "On Schedule")) -> Completed | AA8: 46295 | AB8: 1 | AC8: =IF($AB8=1, "Completed", IF($AA8<TODAY(), "Late", "On Schedule")) -> Completed | AD8: 46326 | AE8: 1 | AF8: =IF($AE8=1, "Completed", IF($AD8<TODAY(), "Late", "On Schedule")) -> Completed | AG8: 46326 | AH8: 0 | AI8: =IF($AH8=1, "Completed", IF($AG8<TODAY(), "Late", "On Schedule")) -> On Schedule | AK8: =IFERROR(SUMPRODUCT(($M$1:$AH$1),(M8:AH8))/SUMIF((M8:AH8),"<>",($M$1:$AH$1)),"") -> 0.96470588 | AL8: =IF($AK8=1, "Completed", IF($K8<TODAY(), "Late", "On Schedule")) -> Late | AN8: =_xlfn.XLOOKUP($E8,'00 MASTER WORK REGISTER'!B:B,'00 MASTER WORK REGISTER'!N:N,"") -> 0 | AS8: MDW-39252 | AT8: MDW-69269 | AU8: MDW-69270
A9: 6 | B9: 6 | C9: MDW-39253 | D9: Lot01 | E9: GEN1.5 | F9: GEN | G9: Modification of Civil Work in Telecommunication Room at OR14 | H9: สหชาติ | K9: 46235 | L9: =O9-30 -> 46021 | M9: 1 | N9: =IF($M9=1, "Completed", IF($L9<TODAY(), "Late", "On Schedule")) -> Completed | O9: =U9-30 -> 46051 | P9: 1 | Q9: =IF($P9=1, "Completed", IF($O9<TODAY(), "Late", "On Schedule")) -> Completed | U9: 46081 | V9: 1 | W9: =IF($V9=1, "Completed", IF($U9<TODAY(), "Late", "On Schedule")) -> Completed | AA9: 46295 | AB9: 1 | AC9: =IF($AB9=1, "Completed", IF($AA9<TODAY(), "Late", "On Schedule")) -> Completed | AG9: 46326 | AH9: 0 | AI9: =IF($AH9=1, "Completed", IF($AG9<TODAY(), "Late", "On Schedule")) -> On Schedule | AK9: =IFERROR(SUMPRODUCT(($M$1:$AH$1),(M9:AH9))/SUMIF((M9:AH9),"<>",($M$1:$AH$1)),"") -> 0.96428571 | AL9: =IF($AK9=1, "Completed", IF($K9<TODAY(), "Late", "On Schedule")) -> Late | AN9: =_xlfn.XLOOKUP($E9,'00 MASTER WORK REGISTER'!B:B,'00 MASTER WORK REGISTER'!N:N,"") -> 0 | AS9: MDW-39253 | AT9: MDW-69271 | AU9: MDW-69272
A10: 7 | B10: 7 | C10: MDW-39254 | D10: Lot01 | E10: GEN1.6 | F10: GEN | G10: Modification in Staff Mess Room at OR13-OR17 | H10: ประธาน | K10: 46235 | L10: =O10-30 -> 46052 | M10: 1 | N10: =IF($M10=1, "Completed", IF($L10<TODAY(), "Late", "On Schedule")) -> Completed | O10: =U10-30 -> 46082 | P10: 1 | Q10: =IF($P10=1, "Completed", IF($O10<TODAY(), "Late", "On Schedule")) -> Completed | U10: 46112 | V10: 1 | W10: =IF($V10=1, "Completed", IF($U10<TODAY(), "Late", "On Schedule")) -> Completed | AA10: 46295 | AB10: 1 | AC10: =IF($AB10=1, "Completed", IF($AA10<TODAY(), "Late", "On Schedule")) -> Completed | AD10: 46326 | AE10: 1 | AF10: =IF($AE10=1, "Completed", IF($AD10<TODAY(), "Late", "On Schedule")) -> Completed | AG10: 46326 | AH10: 0 | AI10: =IF($AH10=1, "Completed", IF($AG10<TODAY(), "Late", "On Schedule")) -> On Schedule | AK10: =IFERROR(SUMPRODUCT(($M$1:$AH$1),(M10:AH10))/SUMIF((M10:AH10),"<>",($M$1:$AH$1)),"") -> 0.96470588 | AL10: =IF($AK10=1, "Completed", IF($K10<TODAY(), "Late", "On Schedule")) -> Late | AN10: =_xlfn.XLOOKUP($E10,'00 MASTER WORK REGISTER'!B:B,'00 MASTER WORK REGISTER'!N:N,"") -> 0 | AS10: MDW-39254 | AT10: MDW-69273 | AU10: MDW-69274
A11: 8 | B11: 8 | C11: MDW-39255 | D11: Lot01 | E11: GEN1.7 | F11: GEN | G11: Modification in Staff Mess Room at OR18-OR22 | H11: ประธาน | K11: 46235 | L11: =O11-30 -> 46235 | M11: 1 | N11: =IF($M11=1, "Completed", IF($L11<TODAY(), "Late", "On Schedule")) -> Completed | O11: =U11-30 -> 46265 | P11: 1 | Q11: =IF($P11=1, "Completed", IF($O11<TODAY(), "Late", "On Schedule")) -> Completed | U11: 46295 | V11: 1 | W11: =IF($V11=1, "Completed", IF($U11<TODAY(), "Late", "On Schedule")) -> Completed | AA11: 46295 | AB11: 1 | AC11: =IF($AB11=1, "Completed", IF($AA11<TODAY(), "Late", "On Schedule")) -> Completed | AD11: 46326 | AE11: 0 | AF11: =IF($AE11=1, "Completed", IF($AD11<TODAY(), "Late", "On Schedule")) -> On Schedule | AG11: 46326 | AH11: 0 | AI11: =IF($AH11=1, "Completed", IF($AG11<TODAY(), "Late", "On Schedule")) -> On Schedule | AK11: =IFERROR(SUMPRODUCT(($M$1:$AH$1),(M11:AH11))/SUMIF((M11:AH11),"<>",($M$1:$AH$1)),"") -> 0.95294118 | AL11: =IF($AK11=1, "Completed", IF($K11<TODAY(), "Late", "On Schedule")) -> Late | AN11: =_xlfn.XLOOKUP($E11,'00 MASTER WORK REGISTER'!B:B,'00 MASTER WORK REGISTER'!N:N,"") -> งานจบ ส่ง TP แล้ว | AS11: MDW-39255 | AT11: MDW-69273 | AU11: MDW-69275
A12: 9 | B12: 9 | C12: MDW-39256 | D12: Lot01 | E12: GEN1.8 | F12: GEN | G12: Modification in Staff Mess Room at OR23-OR29 | H12: ประธาน | K12: 46235 | L12: =O12-30 -> 46235 | M12: 1 | N12: =IF($M12=1, "Completed", IF($L12<TODAY(), "Late", "On Schedule")) -> Completed | O12: =U12-30 -> 46265 | P12: 1 | Q12: =IF($P12=1, "Completed", IF($O12<TODAY(), "Late", "On Schedule")) -> Completed | U12: 46295 | V12: 1 | W12: =IF($V12=1, "Completed", IF($U12<TODAY(), "Late", "On Schedule")) -> Completed | AA12: 46295 | AB12: 1 | AC12: =IF($AB12=1, "Completed", IF($AA12<TODAY(), "Late", "On Schedule")) -> Completed | AD12: 46356 | AE12: 0 | AF12: =IF($AE12=1, "Completed", IF($AD12<TODAY(), "Late", "On Schedule")) -> On Schedule | AG12: 46326 | AH12: 0 | AI12: =IF($AH12=1, "Completed", IF($AG12<TODAY(), "Late", "On Schedule")) -> On Schedule | AK12: =IFERROR(SUMPRODUCT(($M$1:$AH$1),(M12:AH12))/SUMIF((M12:AH12),"<>",($M$1:$AH$1)),"") -> 0.95294118 | AL12: =IF($AK12=1, "Completed", IF($K12<TODAY(), "Late", "On Schedule")) -> Late | AN12: =_xlfn.XLOOKUP($E12,'00 MASTER WORK REGISTER'!B:B,'00 MASTER WORK REGISTER'!N:N,"") | AS12: MDW-39256 | AT12: MDW-69273 | AU12: MDW-69276
A13: 10 | B13: 10 | C13: MDW-39257 | D13: Lot01 | E13: GEN1.9 | F13: GEN | G13: Modification of Air Conditioning in CER and SER at OR13-OR19 | H13: ประธาน | K13: 46235 | L13: =O13-30 -> 46235 | M13: 1 | N13: =IF($M13=1, "Completed", IF($L13<TODAY(), "Late", "On Schedule")) -> Completed | O13: =U13-30 -> 46265 | P13: 1 | Q13: =IF($P13=1, "Completed", IF($O13<TODAY(), "Late", "On Schedule")) -> Completed | U13: 46295 | V13: 0.99 | W13: =IF($V13=1, "Completed", IF($U13<TODAY(), "Late", "On Schedule")) -> Late | AA13: 46295 | AB13: 1 | AC13: =IF($AB13=1, "Completed", IF($AA13<TODAY(), "Late", "On Schedule")) -> Completed | AD13: 46356 | AE13: 0 | AF13: =IF($AE13=1, "Completed", IF($AD13<TODAY(), "Late", "On Schedule")) -> On Schedule | AG13: 46326 | AH13: 0 | AI13: =IF($AH13=1, "Completed", IF($AG13<TODAY(), "Late", "On Schedule")) -> On Schedule | AK13: =IFERROR(SUMPRODUCT(($M$1:$AH$1),(M13:AH13))/SUMIF((M13:AH13),"<>",($M$1:$AH$1)),"") -> 0.94588235 | AL13: =IF($AK13=1, "Completed", IF($K13<TODAY(), "Late", "On Schedule")) -> Late | AN13: =_xlfn.XLOOKUP($E13,'00 MASTER WORK REGISTER'!B:B,'00 MASTER WORK REGISTER'!N:N,"") | AS13: MDW-39257 | AT13: MDW-69277 | AU13: MDW-69278
A14: 11 | B14: 11 | C14: MDW-39258 | D14: Lot01 | E14: GEN1.10 | F14: GEN | G14: Modification of Air Conditioning in CER and SER at OR20-OR22 | H14: ประธาน | K14: 46235 | L14: =O14-30 -> 46235 | M14: 1 | N14: =IF($M14=1, "Completed", IF($L14<TODAY(), "Late", "On Schedule")) -> Completed | O14: =U14-30 -> 46265 | P14: 1 | Q14: =IF($P14=1, "Completed", IF($O14<TODAY(), "Late", "On Schedule")) -> Completed | U14: 46295 | V14: 0.99 | W14: =IF($V14=1, "Completed", IF($U14<TODAY(), "Late", "On Schedule")) -> Late | AA14: 46295 | AB14: 1 | AC14: =IF($AB14=1, "Completed", IF($AA14<TODAY(), "Late", "On Schedule")) -> Completed | AD14: 46356 | AE14: 0 | AF14: =IF($AE14=1, "Completed", IF($AD14<TODAY(), "Late", "On Schedule")) -> On Schedule | AG14: 46326 | AH14: 0 | AI14: =IF($AH14=1, "Completed", IF($AG14<TODAY(), "Late", "On Schedule")) -> On Schedule | AK14: =IFERROR(SUMPRODUCT(($M$1:$AH$1),(M14:AH14))/SUMIF((M14:AH14),"<>",($M$1:$AH$1)),"") -> 0.94588235 | AL14: =IF($AK14=1, "Completed", IF($K14<TODAY(), "Late", "On Schedule")) -> Late | AN14: =_xlfn.XLOOKUP($E14,'00 MASTER WORK REGISTER'!B:B,'00 MASTER WORK REGISTER'!N:N,"") -> 0 | AS14: MDW-39258 | AT14: MDW-69277 | AU14: MDW-69279
A15: 12 | B15: 12 | C15: MDW-39259 | D15: Lot01 | E15: GEN1.11 | F15: GEN | G15: Modification of Air Conditioning in CER and SER at OR23-OR29 | H15: ประธาน | K15: 46235 | L15: =O15-30 -> 46235 | M15: 1 | N15: =IF($M15=1, "Completed", IF($L15<TODAY(), "Late", "On Schedule")) -> Completed | O15: =U15-30 -> 46265 | P15: 1 | Q15: =IF($P15=1, "Completed", IF($O15<TODAY(), "Late", "On Schedule")) -> Completed | U15: 46295 | V15: 0.99 | W15: =IF($V15=1, "Completed", IF($U15<TODAY(), "Late", "On Schedule")) -> Late | AA15: 46295 | AB15: 1 | AC15: =IF($AB15=1, "Completed", IF($AA15<TODAY(), "Late", "On Schedule")) -> Completed | AD15: 46356 | AE15: 0 | AF15: =IF($AE15=1, "Completed", IF($AD15<TODAY(), "Late", "On Schedule")) -> On Schedule | AG15: 46326 | AH15: 0 | AI15: =IF($AH15=1, "Completed", IF($AG15<TODAY(), "Late", "On Schedule")) -> On Schedule | AK15: =IFERROR(SUMPRODUCT(($M$1:$AH$1),(M15:AH15))/SUMIF((M15:AH15),"<>",($M$1:$AH$1)),"") -> 0.94588235 | AL15: =IF($AK15=1, "Completed", IF($K15<TODAY(), "Late", "On Schedule")) -> Late | AN15: =_xlfn.XLOOKUP($E15,'00 MASTER WORK REGISTER'!B:B,'00 MASTER WORK REGISTER'!N:N,"") -> 0 | AS15: MDW-39259 | AT15: MDW-69277 | AU15: MDW-69280
A16: 13 | B16: 13 | C16: MDW-39272 | D16: Lot01 | E16: GEN1.12 | F16: GEN | G16: Modification of New M&E Room at IVS15 - IVS17 Civil & AR | H16: สหชาติ | K16: 46235 | L16: =O16-30 -> 46235 | M16: 1 | N16: =IF($M16=1, "Completed", IF($L16<TODAY(), "Late", "On Schedule")) -> Completed | O16: =U16-30 -> 46265 | P16: 1 | Q16: =IF($P16=1, "Completed", IF($O16<TODAY(), "Late", "On Schedule")) -> Completed | U16: 46295 | V16: 1 | W16: =IF($V16=1, "Completed", IF($U16<TODAY(), "Late", "On Schedule")) -> Completed | AA16: 46295 | AB16: 1 | AC16: =IF($AB16=1, "Completed", IF($AA16<TODAY(), "Late", "On Schedule")) -> Completed | AG16: 46326 | AH16: 0 | AI16: =IF($AH16=1, "Completed", IF($AG16<TODAY(), "Late", "On Schedule")) -> On Schedule | AK16: =IFERROR(SUMPRODUCT(($M$1:$AH$1),(M16:AH16))/SUMIF((M16:AH16),"<>",($M$1:$AH$1)),"") -> 0.96428571 | AL16: =IF($AK16=1, "Completed", IF($K16<TODAY(), "Late", "On Schedule")) -> Late | AN16: =_xlfn.XLOOKUP($E16,'00 MASTER WORK REGISTER'!B:B,'00 MASTER WORK REGISTER'!N:N,"") -> 0 | AS16: MDW-39272 | AT16: MDW-69299 | AU16: MDW-69300
A17: 14 | B17: 14 | C17: MDW-39273 | D17: Lot01 | E17: GEN1.13 | F17: GEN | G17: Modification of New M&E UPS Room at IVS15-IVS17 - Building Services | H17: ประธาน | K17: 46235 | L17: =O17-30 -> 46235 | M17: 1 | N17: =IF($M17=1, "Completed", IF($L17<TODAY(), "Late", "On Schedule")) -> Completed | O17: =U17-30 -> 46265 | P17: 1 | Q17: =IF($P17=1, "Completed", IF($O17<TODAY(), "Late", "On Schedule")) -> Completed | U17: 46295 | V17: 0.99 | W17: =IF($V17=1, "Completed", IF($U17<TODAY(), "Late", "On Schedule")) -> Late | AA17: 46295 | AB17: 1 | AC17: =IF($AB17=1, "Completed", IF($AA17<TODAY(), "Late", "On Schedule")) -> Completed | AD17: 46356 | AE17: 0 | AF17: =IF($AE17=1, "Completed", IF($AD17<TODAY(), "Late", "On Schedule")) -> On Schedule | AG17: 46326 | AH17: 0 | AI17: =IF($AH17=1, "Completed", IF($AG17<TODAY(), "Late", "On Schedule")) -> On Schedule | AK17: =IFERROR(SUMPRODUCT(($M$1:$AH$1),(M17:AH17))/SUMIF((M17:AH17),"<>",($M$1:$AH$1)),"") -> 0.94588235 | AL17: =IF($AK17=1, "Completed", IF($K17<TODAY(), "Late", "On Schedule")) -> Late | AN17: =_xlfn.XLOOKUP($E17,'00 MASTER WORK REGISTER'!B:B,'00 MASTER WORK REGISTER'!N:N,"") -> 0 | AS17: MDW-39273 | AT17: MDW-69301 | AU17: MDW-69302
A18: 15 | B18: 15 | C18: MDW-39294 | D18: Lot01 | E18: GEN1.14 | F18: GEN | G18: Provision of Architectural Work in new M&E UPS room at OR23 | H18: สหชาติ | K18: 46235 | L18: =O18-30 -> 46235 | M18: 1 | N18: =IF($M18=1, "Completed", IF($L18<TODAY(), "Late", "On Schedule")) -> Completed | O18: =U18-30 -> 46265 | P18: 1 | Q18: =IF($P18=1, "Completed", IF($O18<TODAY(), "Late", "On Schedule")) -> Completed | U18: 46295 | V18: 1 | W18: =IF($V18=1, "Completed", IF($U18<TODAY(), "Late", "On Schedule")) -> Completed | AA18: 46295 | AB18: 1 | AC18: =IF($AB18=1, "Completed", IF($AA18<TODAY(), "Late", "On Schedule")) -> Completed | AG18: 46326 | AH18: 0 | AI18: =IF($AH18=1, "Completed", IF($AG18<TODAY(), "Late", "On Schedule")) -> On Schedule | AK18: =IFERROR(SUMPRODUCT(($M$1:$AH$1),(M18:AH18))/SUMIF((M18:AH18),"<>",($M$1:$AH$1)),"") -> 0.96428571 | AL18: =IF($AK18=1, "Completed", IF($K18<TODAY(), "Late", "On Schedule")) -> Late | AN18: =_xlfn.XLOOKUP($E18,'00 MASTER WORK REGISTER'!B:B,'00 MASTER WORK REGISTER'!N:N,"") -> 0 | AS18: MDW-39294 | AT18: MDW-69339 | AU18: MDW-69340
A19: 16 | B19: 16 | C19: MDW-39299 | D19: Lot01 | E19: GEN1.15 | F19: GEN | G19: Provision of Air Conditioning System in Commercial Room at OR13-OR19 | H19: ประธาน | K19: 46235 | L19: =O19-30 -> 46235 | M19: 1 | N19: =IF($M19=1, "Completed", IF($L19<TODAY(), "Late", "On Schedule")) -> Completed | O19: =U19-30 -> 46265 | P19: 1 | Q19: =IF($P19=1, "Completed", IF($O19<TODAY(), "Late", "On Schedule")) -> Completed | U19: 46295 | V19: 1 | W19: =IF($V19=1, "Completed", IF($U19<TODAY(), "Late", "On Schedule")) -> Completed | AA19: 46295 | AB19: 1 | AC19: =IF($AB19=1, "Completed", IF($AA19<TODAY(), "Late", "On Schedule")) -> Completed | AD19: 46326 | AE19: 0 | AF19: =IF($AE19=1, "Completed", IF($AD19<TODAY(), "Late", "On Schedule")) -> On Schedule | AG19: 46326 | AH19: 0 | AI19: =IF($AH19=1, "Completed", IF($AG19<TODAY(), "Late", "On Schedule")) -> On Schedule | AK19: =IFERROR(SUMPRODUCT(($M$1:$AH$1),(M19:AH19))/SUMIF((M19:AH19),"<>",($M$1:$AH$1)),"") -> 0.95294118 | AL19: =IF($AK19=1, "Completed", IF($K19<TODAY(), "Late", "On Schedule")) -> Late | AN19: =_xlfn.XLOOKUP($E19,'00 MASTER WORK REGISTER'!B:B,'00 MASTER WORK REGISTER'!N:N,"") -> 0 | AS19: MDW-39299 | AT19: MDW-69349 | AU19: MDW-69350
A20: 17 | B20: 17 | C20: MDW-39306 | D20: Lot01 | E20: GEN1.16 | F20: GEN | G20: Modification CER and First Aid Room at OR14 - Building Services | H20: ประธาน | K20: 46235 | L20: =O20-30 -> 46235 | M20: 1 | N20: =IF($M20=1, "Completed", IF($L20<TODAY(), "Late", "On Schedule")) -> Completed | O20: =U20-30 -> 46265 | P20: 1 | Q20: =IF($P20=1, "Completed", IF($O20<TODAY(), "Late", "On Schedule")) -> Completed | U20: 46295 | V20: 1 | W20: =IF($V20=1, "Completed", IF($U20<TODAY(), "Late", "On Schedule")) -> Completed | AA20: 46295 | AB20: 1 | AC20: =IF($AB20=1, "Completed", IF($AA20<TODAY(), "Late", "On Schedule")) -> Completed | AD20: 46326 | AE20: 1 | AF20: =IF($AE20=1, "Completed", IF($AD20<TODAY(), "Late", "On Schedule")) -> Completed | AG20: 46326 | AH20: 0 | AI20: =IF($AH20=1, "Completed", IF($AG20<TODAY(), "Late", "On Schedule")) -> On Schedule | AK20: =IFERROR(SUMPRODUCT(($M$1:$AH$1),(M20:AH20))/SUMIF((M20:AH20),"<>",($M$1:$AH$1)),"") -> 0.96470588 | AL20: =IF($AK20=1, "Completed", IF($K20<TODAY(), "Late", "On Schedule")) -> Late | AN20: =_xlfn.XLOOKUP($E20,'00 MASTER WORK REGISTER'!B:B,'00 MASTER WORK REGISTER'!N:N,"") -> 0 | AS20: MDW-39306 | AT20: MDW-69363 | AU20: MDW-69364
A21: 18 | B21: 18 | C21: MDW-39307 | D21: Lot01 | E21: GEN1.17 | F21: GEN | G21: Additional Fence at Back of House OR13 - OR22 and IVS East Section | H21: สหชาติ | K21: 46235 | L21: 46295 | M21: 1 | N21: =IF($M21=1, "Completed", IF($L21<TODAY(), "Late", "On Schedule")) -> Completed | O21: 46326 | P21: 0.5 | Q21: =IF($P21=1, "Completed", IF($O21<TODAY(), "Late", "On Schedule")) -> On Schedule | U21: 46387 | V21: 0 | W21: =IF($V21=1, "Completed", IF($U21<TODAY(), "Late", "On Schedule")) -> On Schedule | AA21: 46295 | AB21: 1 | AC21: =IF($AB21=1, "Completed", IF($AA21<TODAY(), "Late", "On Schedule")) -> Completed | AG21: =U21+30 -> 46417 | AH21: 0 | AI21: =IF($AH21=1, "Completed", IF($AG21<TODAY(), "Late", "On Schedule")) -> On Schedule | AK21: =IFERROR(SUMPRODUCT(($M$1:$AH$1),(M21:AH21))/SUMIF((M21:AH21),"<>",($M$1:$AH$1)),"") -> 0.19047619 | AL21: =IF($AK21=1, "Completed", IF($K21<TODAY(), "Late", "On Schedule")) -> Late | AN21: =_xlfn.XLOOKUP($E21,'00 MASTER WORK REGISTER'!B:B,'00 MASTER WORK REGISTER'!N:N,"") -> 0 | AS21: MDW-39307 | AT21: MDW-69365 | AU21: MDW-69366
A22: 19 | B22: 19 | C22: MDW-39249 | D22: Lot01 | E22: GEN1.18 | F22: GEN | G22: SOR Counter and Workstation Hanging Support Installation on East Section | H22: สหชาติ | K22: 46235 | L22: 46235 | M22: 1 | N22: =IF($M22=1, "Completed", IF($L22<TODAY(), "Late", "On Schedule")) -> Completed | O22: 46265 | P22: 1 | Q22: =IF($P22=1, "Completed", IF($O22<TODAY(), "Late", "On Schedule")) -> Completed | U22: 46295 | V22: 1 | W22: =IF($V22=1, "Completed", IF($U22<TODAY(), "Late", "On Schedule")) -> Completed | AA22: 46295 | AB22: 1 | AC22: =IF($AB22=1, "Completed", IF($AA22<TODAY(), "Late", "On Schedule")) -> Completed | AG22: 46326 | AH22: 0 | AI22: =IF($AH22=1, "Completed", IF($AG22<TODAY(), "Late", "On Schedule")) -> On Schedule | AK22: =IFERROR(SUMPRODUCT(($M$1:$AH$1),(M22:AH22))/SUMIF((M22:AH22),"<>",($M$1:$AH$1)),"") -> 0.96428571 | AL22: =IF($AK22=1, "Completed", IF($K22<TODAY(), "Late", "On Schedule")) -> Late | AN22: =_xlfn.XLOOKUP($E22,'00 MASTER WORK REGISTER'!B:B,'00 MASTER WORK REGISTER'!N:N,"") | AO22: เพิ่ม Counter และ Workstation Hanging Support ที่ SOR at all Station | AS22: MDW-39249 | AT22: MDW-69263 | AU22: MDW-69264
A23: 20 | B23: 20 | C23: MDW-39250 | D23: Lot01 | E23: GEN1.19 | F23: GEN | G23: Ticket Office Modification on East Section | H23: สหชาติ | K23: 46235 | L23: 46235 | M23: 1 | N23: =IF($M23=1, "Completed", IF($L23<TODAY(), "Late", "On Schedule")) -> Completed | O23: 46265 | P23: 1 | Q23: =IF($P23=1, "Completed", IF($O23<TODAY(), "Late", "On Schedule")) -> Completed | U23: 46295 | V23: 1 | W23: =IF($V23=1, "Completed", IF($U23<TODAY(), "Late", "On Schedule")) -> Completed | AA23: 46295 | AB23: 1 | AC23: =IF($AB23=1, "Completed", IF($AA23<TODAY(), "Late", "On Schedule")) -> Completed | AG23: 46326 | AH23: 0 | AI23: =IF($AH23=1, "Completed", IF($AG23<TODAY(), "Late", "On Schedule")) -> On Schedule | AK23: =IFERROR(SUMPRODUCT(($M$1:$AH$1),(M23:AH23))/SUMIF((M23:AH23),"<>",($M$1:$AH$1)),"") -> 0.96428571 | AL23: =IF($AK23=1, "Completed", IF($K23<TODAY(), "Late", "On Schedule")) -> Late | AN23: =_xlfn.XLOOKUP($E23,'00 MASTER WORK REGISTER'!B:B,'00 MASTER WORK REGISTER'!N:N,"") -> 0 | AO23: ปรับ Raise floor เพื่อเพิ่มช่องว่างระหว่าง Counter กับพื้นให้ได้ 65cm. (รวมความสูงจากบนCounterถึงพื้นคือ75cm) ทำ Counter ใหม่ให้ได้ระดับกับ Raise floor (รวมรื้อ Counterเดิมออก) | AS23: MDW-39250 | AT23: MDW-69265 | AU23: MDW-69266
A24: 21 | B24: 21 | C24: =_xlfn.XLOOKUP($E24,'00 MASTER WORK REGISTER'!B:B,'00 MASTER WORK REGISTER'!L:L) -> MDW-39261 | D24: Lot01 | E24: GEN2 | F24: GEN | G24: =_xlfn.XLOOKUP($E24,'00 MASTER WORK REGISTER'!B:B,'00 MASTER WORK REGISTER'!H:H) -> Rooms and Building Service Systems Modification in Depot Area | H24: =_xlfn.XLOOKUP($E24,'00 MASTER WORK REGISTER'!B:B,'00 MASTER WORK REGISTER'!$I:$I,"") -> - | J24: Depot | K24: =_xlfn.XLOOKUP($E24,'00 MASTER WORK REGISTER'!$B:$B,'00 MASTER WORK REGISTER'!$M:$M,"") -> 46235 | AK24: =IFERROR(SUMPRODUCT(($M$1:$AH$1),(M24:AH24))/SUMIF((M24:AH24),"<>",($M$1:$AH$1)),"") | AN24: =_xlfn.XLOOKUP($E24,'00 MASTER WORK REGISTER'!B:B,'00 MASTER WORK REGISTER'!N:N,"") -> 0 | AP24: =_xlfn.XLOOKUP($F24,#REF!,#REF!,"") -> #REF! | AS24: MDW-39261 | AT24: =_xlfn.XLOOKUP($AS24,'02 Design'!F:F,'02 Design'!AE:AE," ") -> MDW-69283 | AU24: =_xlfn.XLOOKUP($AS24,'02 Design'!F:F,'02 Design'!AF:AF," ") -> MDW-69284
A25: 22 | B25: 22 | C25: MDW-39260 | D25: Lot01 | E25: GEN2.1 | F25: GEN | G25: Modification of Air Conditioning in M&E Room at OCC Building | H25: ประธาน | K25: 46235 | L25: 46021 | M25: 1 | N25: =IF($M25=1, "Completed", IF($L25<TODAY(), "Late", "On Schedule")) -> Completed | O25: 46051 | P25: 1 | Q25: =IF($P25=1, "Completed", IF($O25<TODAY(), "Late", "On Schedule")) -> Completed | U25: 46081 | V25: 1 | W25: =IF($V25=1, "Completed", IF($U25<TODAY(), "Late", "On Schedule")) -> Completed | AA25: 46295 | AB25: 1 | AC25: =IF($AB25=1, "Completed", IF($AA25<TODAY(), "Late", "On Schedule")) -> Completed | AD25: 46326 | AE25: 1 | AF25: =IF($AE25=1, "Completed", IF($AD25<TODAY(), "Late", "On Schedule")) -> Completed | AG25: 46326 | AH25: 0 | AI25: =IF($AH25=1, "Completed", IF($AG25<TODAY(), "Late", "On Schedule")) -> On Schedule | AK25: =IFERROR(SUMPRODUCT(($M$1:$AH$1),(M25:AH25))/SUMIF((M25:AH25),"<>",($M$1:$AH$1)),"") -> 0.96470588 | AL25: =IF($AK25=1, "Completed", IF($K25<TODAY(), "Late", "On Schedule")) -> Late | AN25: =_xlfn.XLOOKUP($E25,'00 MASTER WORK REGISTER'!B:B,'00 MASTER WORK REGISTER'!N:N,"") | AS25: MDW-39260 | AT25: MDW-69281 | AU25: MDW-69282
A26: 23 | B26: 23 | C26: MDW-39261 | D26: Lot01 | E26: GEN2.2 | F26: GEN | G26: Provision of UPS for MDB Control at Main Workshop, OCC Building, Admin Building, Stabling Yard and Train Washing Plant | H26: ประธาน | K26: 46235 | L26: 46266 | M26: 1 | N26: =IF($M26=1, "Completed", IF($L26<TODAY(), "Late", "On Schedule")) -> Completed | O26: 46296 | P26: 1 | Q26: =IF($P26=1, "Completed", IF($O26<TODAY(), "Late", "On Schedule")) -> Completed | U26: 46326 | V26: 0.9 | W26: =IF($V26=1, "Completed", IF($U26<TODAY(), "Late", "On Schedule")) -> On Schedule | AA26: 46295 | AB26: 1 | AC26: =IF($AB26=1, "Completed", IF($AA26<TODAY(), "Late", "On Schedule")) -> Completed | AD26: 46326 | AE26: 0 | AF26: =IF($AE26=1, "Completed", IF($AD26<TODAY(), "Late", "On Schedule")) -> On Schedule | AG26: =U26+30 -> 46356 | AH26: 0 | AI26: =IF($AH26=1, "Completed", IF($AG26<TODAY(), "Late", "On Schedule")) -> On Schedule | AK26: =IFERROR(SUMPRODUCT(($M$1:$AH$1),(M26:AH26))/SUMIF((M26:AH26),"<>",($M$1:$AH$1)),"") -> 0.88235294 | AL26: =IF($AK26=1, "Completed", IF($K26<TODAY(), "Late", "On Schedule")) -> Late | AN26: =_xlfn.XLOOKUP($E26,'00 MASTER WORK REGISTER'!B:B,'00 MASTER WORK REGISTER'!N:N,"") | AO26: Add small UPS for MDB Control at MMW/OCC/Admin/Stabling/Train Washing Plant | AS26: MDW-39261 | AT26: MDW-69283 | AU26: MDW-69284
A27: 24 | B27: 24 | C27: MDW-39262 | D27: Lot01 | E27: GEN2.3 | F27: GEN | G27: Provision of Redundant MDB at OCC Building, Admin Building and Canteen | H27: ประธาน | K27: 46235 | L27: 46266 | M27: 1 | N27: =IF($M27=1, "Completed", IF($L27<TODAY(), "Late", "On Schedule")) -> Completed | O27: 46296 | P27: 1 | Q27: =IF($P27=1, "Completed", IF($O27<TODAY(), "Late", "On Schedule")) -> Completed | U27: 46326 | V27: 0.95 | W27: =IF($V27=1, "Completed", IF($U27<TODAY(), "Late", "On Schedule")) -> On Schedule | AA27: 46295 | AB27: 1 | AC27: =IF($AB27=1, "Completed", IF($AA27<TODAY(), "Late", "On Schedule")) -> Completed | AD27: 46326 | AE27: 0 | AF27: =IF($AE27=1, "Completed", IF($AD27<TODAY(), "Late", "On Schedule")) -> On Schedule | AG27: =U27+30 -> 46356 | AH27: 0 | AI27: =IF($AH27=1, "Completed", IF($AG27<TODAY(), "Late", "On Schedule")) -> On Schedule | AK27: =IFERROR(SUMPRODUCT(($M$1:$AH$1),(M27:AH27))/SUMIF((M27:AH27),"<>",($M$1:$AH$1)),"") -> 0.91764706 | AL27: =IF($AK27=1, "Completed", IF($K27<TODAY(), "Late", "On Schedule")) -> Late | AN27: =_xlfn.XLOOKUP($E27,'00 MASTER WORK REGISTER'!B:B,'00 MASTER WORK REGISTER'!N:N,"") | AS27: MDW-39262 | AT27: MDW-69285 | AU27: MDW-69286
A28: 25 | B28: 25 | C28: MDW-39263 | D28: Lot01 | E28: GEN2.4 | F28: GEN | G28: Additonal Lighting System at Depot Area | H28: ประธาน | K28: 46235 | L28: 46113 | M28: 1 | N28: =IF($M28=1, "Completed", IF($L28<TODAY(), "Late", "On Schedule")) -> Completed | O28: 46143 | P28: 1 | Q28: =IF($P28=1, "Completed", IF($O28<TODAY(), "Late", "On Schedule")) -> Completed | U28: 46173 | V28: 1 | W28: =IF($V28=1, "Completed", IF($U28<TODAY(), "Late", "On Schedule")) -> Completed | AA28: 46295 | AB28: 1 | AC28: =IF($AB28=1, "Completed", IF($AA28<TODAY(), "Late", "On Schedule")) -> Completed | AD28: 46326 | AE28: 1 | AF28: =IF($AE28=1, "Completed", IF($AD28<TODAY(), "Late", "On Schedule")) -> Completed | AG28: 46326 | AH28: 0 | AI28: =IF($AH28=1, "Completed", IF($AG28<TODAY(), "Late", "On Schedule")) -> On Schedule | AK28: =IFERROR(SUMPRODUCT(($M$1:$AH$1),(M28:AH28))/SUMIF((M28:AH28),"<>",($M$1:$AH$1)),"") -> 0.96470588 | AL28: =IF($AK28=1, "Completed", IF($K28<TODAY(), "Late", "On Schedule")) -> Late | AN28: =_xlfn.XLOOKUP($E28,'00 MASTER WORK REGISTER'!B:B,'00 MASTER WORK REGISTER'!N:N,"") | AS28: MDW-39263 | AT28: MDW-69287 | AU28: MDW-69288
A29: 26 | B29: 26 | C29: MDW-39290 | D29: Lot01 | E29: GEN2.5 | F29: GEN | G29: Modification Room for PSY at Depot Buildings - Building Services | H29: ประธาน | K29: 46235 | L29: 46235 | M29: 1 | N29: =IF($M29=1, "Completed", IF($L29<TODAY(), "Late", "On Schedule")) -> Completed | O29: 46265 | P29: 1 | Q29: =IF($P29=1, "Completed", IF($O29<TODAY(), "Late", "On Schedule")) -> Completed | U29: 46295 | V29: 1 | W29: =IF($V29=1, "Completed", IF($U29<TODAY(), "Late", "On Schedule")) -> Completed | AA29: 46295 | AB29: 1 | AC29: =IF($AB29=1, "Completed", IF($AA29<TODAY(), "Late", "On Schedule")) -> Completed | AD29: 46326 | AE29: 0 | AF29: =IF($AE29=1, "Completed", IF($AD29<TODAY(), "Late", "On Schedule")) -> On Schedule | AG29: 46326 | AH29: 0 | AI29: =IF($AH29=1, "Completed", IF($AG29<TODAY(), "Late", "On Schedule")) -> On Schedule | AK29: =IFERROR(SUMPRODUCT(($M$1:$AH$1),(M29:AH29))/SUMIF((M29:AH29),"<>",($M$1:$AH$1)),"") -> 0.95294118 | AL29: =IF($AK29=1, "Completed", IF($K29<TODAY(), "Late", "On Schedule")) -> Late | AN29: =_xlfn.XLOOKUP($E29,'00 MASTER WORK REGISTER'!B:B,'00 MASTER WORK REGISTER'!N:N,"") | AS29: MDW-39290 | AT29: MDW-69331 | AU29: MDW-69332
A30: 27 | B30: 27 | C30: MDW-39300 | D30: Lot01 | E30: GEN2.6 | F30: GEN | G30: Modification SIG-PSD Office at Main Workshop - Building Services | H30: ประธาน | K30: 46235 | L30: 46235 | M30: 1 | N30: =IF($M30=1, "Completed", IF($L30<TODAY(), "Late", "On Schedule")) -> Completed | O30: 46265 | P30: 1 | Q30: =IF($P30=1, "Completed", IF($O30<TODAY(), "Late", "On Schedule")) -> Completed | U30: 46295 | V30: 1 | W30: =IF($V30=1, "Completed", IF($U30<TODAY(), "Late", "On Schedule")) -> Completed | AA30: 46295 | AB30: 1 | AC30: =IF($AB30=1, "Completed", IF($AA30<TODAY(), "Late", "On Schedule")) -> Completed | AD30: 46326 | AE30: 0 | AF30: =IF($AE30=1, "Completed", IF($AD30<TODAY(), "Late", "On Schedule")) -> On Schedule | AG30: 46326 | AH30: 0 | AI30: =IF($AH30=1, "Completed", IF($AG30<TODAY(), "Late", "On Schedule")) -> On Schedule | AK30: =IFERROR(SUMPRODUCT(($M$1:$AH$1),(M30:AH30))/SUMIF((M30:AH30),"<>",($M$1:$AH$1)),"") -> 0.95294118 | AL30: =IF($AK30=1, "Completed", IF($K30<TODAY(), "Late", "On Schedule")) -> Late | AN30: =_xlfn.XLOOKUP($E30,'00 MASTER WORK REGISTER'!B:B,'00 MASTER WORK REGISTER'!N:N,"") | AS30: MDW-39300 | AT30: MDW-69351 | AU30: MDW-69352
A31: 28 | B31: 28 | C31: MDW-39301 | D31: Lot01 | E31: GEN2.7 | F31: GEN | G31: Modification Backup CCR Room at Main Workshop - Building Services | H31: ประธาน | K31: 46235 | L31: 46235 | M31: 1 | N31: =IF($M31=1, "Completed", IF($L31<TODAY(), "Late", "On Schedule")) -> Completed | O31: 46265 | P31: 1 | Q31: =IF($P31=1, "Completed", IF($O31<TODAY(), "Late", "On Schedule")) -> Completed | U31: 46295 | V31: 1 | W31: =IF($V31=1, "Completed", IF($U31<TODAY(), "Late", "On Schedule")) -> Completed | AA31: 46295 | AB31: 1 | AC31: =IF($AB31=1, "Completed", IF($AA31<TODAY(), "Late", "On Schedule")) -> Completed | AD31: 46326 | AE31: 0 | AF31: =IF($AE31=1, "Completed", IF($AD31<TODAY(), "Late", "On Schedule")) -> On Schedule | AG31: 46326 | AH31: 0 | AI31: =IF($AH31=1, "Completed", IF($AG31<TODAY(), "Late", "On Schedule")) -> On Schedule | AK31: =IFERROR(SUMPRODUCT(($M$1:$AH$1),(M31:AH31))/SUMIF((M31:AH31),"<>",($M$1:$AH$1)),"") -> 0.95294118 | AL31: =IF($AK31=1, "Completed", IF($K31<TODAY(), "Late", "On Schedule")) -> Late | AN31: =_xlfn.XLOOKUP($E31,'00 MASTER WORK REGISTER'!B:B,'00 MASTER WORK REGISTER'!N:N,"") | AS31: MDW-39301 | AT31: MDW-69353 | AU31: MDW-69354
A32: 29 | B32: 29 | C32: MDW-39302 | D32: Lot01 | E32: GEN2.8 | F32: GEN | G32: Modification SER at Main Workshop - Building Services | H32: ประธาน | K32: 46235 | L32: 46235 | M32: 1 | N32: =IF($M32=1, "Completed", IF($L32<TODAY(), "Late", "On Schedule")) -> Completed | O32: 46265 | P32: 1 | Q32: =IF($P32=1, "Completed", IF($O32<TODAY(), "Late", "On Schedule")) -> Completed | U32: 46295 | V32: 1 | W32: =IF($V32=1, "Completed", IF($U32<TODAY(), "Late", "On Schedule")) -> Completed | AA32: 46295 | AB32: 1 | AC32: =IF($AB32=1, "Completed", IF($AA32<TODAY(), "Late", "On Schedule")) -> Completed | AD32: 46326 | AE32: 0 | AF32: =IF($AE32=1, "Completed", IF($AD32<TODAY(), "Late", "On Schedule")) -> On Schedule | AG32: 46326 | AH32: 0 | AI32: =IF($AH32=1, "Completed", IF($AG32<TODAY(), "Late", "On Schedule")) -> On Schedule | AK32: =IFERROR(SUMPRODUCT(($M$1:$AH$1),(M32:AH32))/SUMIF((M32:AH32),"<>",($M$1:$AH$1)),"") -> 0.95294118 | AL32: =IF($AK32=1, "Completed", IF($K32<TODAY(), "Late", "On Schedule")) -> Late | AN32: =_xlfn.XLOOKUP($E32,'00 MASTER WORK REGISTER'!B:B,'00 MASTER WORK REGISTER'!N:N,"") | AS32: MDW-39302 | AT32: MDW-69355 | AU32: MDW-69356
A33: 30 | B33: 30 | C33: MDW-39303 | D33: Lot01 | E33: GEN2.9 | F33: GEN | G33: Modification CER & SCADA Room at Main Workshop - Building Services | H33: ประธาน | K33: 46235 | L33: 46235 | M33: 1 | N33: =IF($M33=1, "Completed", IF($L33<TODAY(), "Late", "On Schedule")) -> Completed | O33: 46265 | P33: 1 | Q33: =IF($P33=1, "Completed", IF($O33<TODAY(), "Late", "On Schedule")) -> Completed | U33: 46295 | V33: 1 | W33: =IF($V33=1, "Completed", IF($U33<TODAY(), "Late", "On Schedule")) -> Completed | AA33: 46295 | AB33: 1 | AC33: =IF($AB33=1, "Completed", IF($AA33<TODAY(), "Late", "On Schedule")) -> Completed | AD33: 46326 | AE33: 0 | AF33: =IF($AE33=1, "Completed", IF($AD33<TODAY(), "Late", "On Schedule")) -> On Schedule | AG33: 46326 | AH33: 0 | AI33: =IF($AH33=1, "Completed", IF($AG33<TODAY(), "Late", "On Schedule")) -> On Schedule | AK33: =IFERROR(SUMPRODUCT(($M$1:$AH$1),(M33:AH33))/SUMIF((M33:AH33),"<>",($M$1:$AH$1)),"") -> 0.95294118 | AL33: =IF($AK33=1, "Completed", IF($K33<TODAY(), "Late", "On Schedule")) -> Late | AN33: =_xlfn.XLOOKUP($E33,'00 MASTER WORK REGISTER'!B:B,'00 MASTER WORK REGISTER'!N:N,"") | AS33: MDW-39303 | AT33: MDW-69357 | AU33: MDW-69358
A34: 31 | B34: 31 | C34: MDW-39309 | D34: Lot01 | E34: GEN2.10 | F34: GEN | G34: Modification Air Conditioning System at CCR | H34: ประธาน | K34: 46235 | L34: 46296 | M34: 1 | N34: =IF($M34=1, "Completed", IF($L34<TODAY(), "Late", "On Schedule")) -> Completed | O34: 46326 | P34: 1 | Q34: =IF($P34=1, "Completed", IF($O34<TODAY(), "Late", "On Schedule")) -> Completed | U34: 46387 | V34: 0.8 | W34: =IF($V34=1, "Completed", IF($U34<TODAY(), "Late", "On Schedule")) -> On Schedule | AA34: 46295 | AB34: 1 | AC34: =IF($AB34=1, "Completed", IF($AA34<TODAY(), "Late", "On Schedule")) -> Completed | AD34: 46326 | AE34: 0 | AF34: =IF($AE34=1, "Completed", IF($AD34<TODAY(), "Late", "On Schedule")) -> On Schedule | AG34: =U34+30 -> 46417 | AH34: 0 | AI34: =IF($AH34=1, "Completed", IF($AG34<TODAY(), "Late", "On Schedule")) -> On Schedule | AK34: =IFERROR(SUMPRODUCT(($M$1:$AH$1),(M34:AH34))/SUMIF((M34:AH34),"<>",($M$1:$AH$1)),"") -> 0.81176471 | AL34: =IF($AK34=1, "Completed", IF($K34<TODAY(), "Late", "On Schedule")) -> Late | AN34: =_xlfn.XLOOKUP($E34,'00 MASTER WORK REGISTER'!B:B,'00 MASTER WORK REGISTER'!N:N,"") | AS34: MDW-39309 | AT34: MDW-69369 | AU34: MDW-69370
A35: 32 | B35: 32 | C35: MDW-39312 | D35: Lot01 | E35: GEN2.11 | F35: GEN | G35: Modification Electronic Workshop at Main Workshop - Building Services | H35: ประธาน | K35: 46235 | L35: 46326 | M35: 1 | N35: =IF($M35=1, "Completed", IF($L35<TODAY(), "Late", "On Schedule")) -> Completed | O35: 46356 | P35: 1 | Q35: =IF($P35=1, "Completed", IF($O35<TODAY(), "Late", "On Schedule")) -> Completed | U35: 46387 | V35: 0 | W35: =IF($V35=1, "Completed", IF($U35<TODAY(), "Late", "On Schedule")) -> On Schedule | AA35: 46356 | AB35: 0 | AC35: =IF($AB35=1, "Completed", IF($AA35<TODAY(), "Late", "On Schedule")) -> On Schedule | AD35: 46326 | AE35: 0 | AF35: =IF($AE35=1, "Completed", IF($AD35<TODAY(), "Late", "On Schedule")) -> On Schedule | AG35: =U35+30 -> 46417 | AH35: 0 | AI35: =IF($AH35=1, "Completed", IF($AG35<TODAY(), "Late", "On Schedule")) -> On Schedule | AK35: =IFERROR(SUMPRODUCT(($M$1:$AH$1),(M35:AH35))/SUMIF((M35:AH35),"<>",($M$1:$AH$1)),"") -> 0.23529412 | AL35: =IF($AK35=1, "Completed", IF($K35<TODAY(), "Late", "On Schedule")) -> Late | AN35: =_xlfn.XLOOKUP($E35,'00 MASTER WORK REGISTER'!B:B,'00 MASTER WORK REGISTER'!N:N,"") | AS35: MDW-39312 | AT35: MDW-69375 | AU35: MDW-69376
A36: 33 | B36: 33 | C36: MDW-39313 | D36: Lot01 | E36: GEN2.12 | F36: GEN | G36: Modification Battery Charger Room at Main Workshop - Building Services | H36: ประธาน | K36: 46235 | L36: 46326 | M36: 1 | N36: =IF($M36=1, "Completed", IF($L36<TODAY(), "Late", "On Schedule")) -> Completed | O36: 46356 | P36: 1 | Q36: =IF($P36=1, "Completed", IF($O36<TODAY(), "Late", "On Schedule")) -> Completed | U36: 46387 | V36: 0 | W36: =IF($V36=1, "Completed", IF($U36<TODAY(), "Late", "On Schedule")) -> On Schedule | AA36: 46356 | AB36: 0 | AC36: =IF($AB36=1, "Completed", IF($AA36<TODAY(), "Late", "On Schedule")) -> On Schedule | AD36: 46326 | AE36: 0 | AF36: =IF($AE36=1, "Completed", IF($AD36<TODAY(), "Late", "On Schedule")) -> On Schedule | AG36: =U36+30 -> 46417 | AH36: 0 | AI36: =IF($AH36=1, "Completed", IF($AG36<TODAY(), "Late", "On Schedule")) -> On Schedule | AK36: =IFERROR(SUMPRODUCT(($M$1:$AH$1),(M36:AH36))/SUMIF((M36:AH36),"<>",($M$1:$AH$1)),"") -> 0.23529412 | AL36: =IF($AK36=1, "Completed", IF($K36<TODAY(), "Late", "On Schedule")) -> Late | AN36: =_xlfn.XLOOKUP($E36,'00 MASTER WORK REGISTER'!B:B,'00 MASTER WORK REGISTER'!N:N,"") | AS36: MDW-39313 | AT36: MDW-69377 | AU36: MDW-69378
A37: 34 | B37: 34 | C37: MDW-39314 | D37: Lot01 | E37: GEN2.13 | F37: GEN | G37: Modification Machining Room at Main Workshop - Building Services | H37: ประธาน | K37: 46235 | L37: 46326 | M37: 0.9 | N37: =IF($M37=1, "Completed", IF($L37<TODAY(), "Late", "On Schedule")) -> On Schedule | O37: 46356 | P37: 0 | Q37: =IF($P37=1, "Completed", IF($O37<TODAY(), "Late", "On Schedule")) -> On Schedule | U37: 46387 | V37: 0 | W37: =IF($V37=1, "Completed", IF($U37<TODAY(), "Late", "On Schedule")) -> On Schedule | AA37: 46356 | AB37: 0 | AC37: =IF($AB37=1, "Completed", IF($AA37<TODAY(), "Late", "On Schedule")) -> On Schedule | AD37: 46326 | AE37: 0 | AF37: =IF($AE37=1, "Completed", IF($AD37<TODAY(), "Late", "On Schedule")) -> On Schedule | AG37: =U37+30 -> 46417 | AH37: 0 | AI37: =IF($AH37=1, "Completed", IF($AG37<TODAY(), "Late", "On Schedule")) -> On Schedule | AK37: =IFERROR(SUMPRODUCT(($M$1:$AH$1),(M37:AH37))/SUMIF((M37:AH37),"<>",($M$1:$AH$1)),"") -> 0.10588235 | AL37: =IF($AK37=1, "Completed", IF($K37<TODAY(), "Late", "On Schedule")) -> Late | AN37: =_xlfn.XLOOKUP($E37,'00 MASTER WORK REGISTER'!B:B,'00 MASTER WORK REGISTER'!N:N,"") | AS37: MDW-39314 | AT37: MDW-69379 | AU37: MDW-69380
A38: 35 | B38: 35 | C38: MDW-39315 | D38: Lot01 | E38: GEN2.14 | F38: GEN | G38: Modification Electronic Workshop, Battery Charger and Machining Room at Main Workshop - Civil & AR | H38: สหชาติ | K38: 46235 | L38: 46326 | M38: 0.7 | N38: =IF($M38=1, "Completed", IF($L38<TODAY(), "Late", "On Schedule")) -> On Schedule | O38: 46356 | P38: 0.9 | Q38: =IF($P38=1, "Completed", IF($O38<TODAY(), "Late", "On Schedule")) -> On Schedule | U38: 46387 | V38: 0 | W38: =IF($V38=1, "Completed", IF($U38<TODAY(), "Late", "On Schedule")) -> On Schedule | AA38: 46356 | AB38: 0 | AC38: =IF($AB38=1, "Completed", IF($AA38<TODAY(), "Late", "On Schedule")) -> On Schedule | AG38: =U38+30 -> 46417 | AH38: 0 | AI38: =IF($AH38=1, "Completed", IF($AG38<TODAY(), "Late", "On Schedule")) -> On Schedule | AK38: =IFERROR(SUMPRODUCT(($M$1:$AH$1),(M38:AH38))/SUMIF((M38:AH38),"<>",($M$1:$AH$1)),"") -> 0.19047619 | AL38: =IF($AK38=1, "Completed", IF($K38<TODAY(), "Late", "On Schedule")) -> Late | AN38: =_xlfn.XLOOKUP($E38,'00 MASTER WORK REGISTER'!B:B,'00 MASTER WORK REGISTER'!N:N,"") | AS38: MDW-39315 | AT38: MDW-69383 | AU38: MDW-69384
A39: 36 | B39: 36 | C39: MDW-39297 | D39: Lot01 | E39: GEN2.15 | F39: GEN | G39: Training Room at Ratchada Station (Part 2) | H39: สหชาติ | K39: 46235 | L39: 46235 | M39: 0 | N39: =IF($M39=1, "Completed", IF($L39<TODAY(), "Late", "On Schedule")) -> Late | O39: 46265 | P39: 1 | Q39: =IF($P39=1, "Completed", IF($O39<TODAY(), "Late", "On Schedule")) -> Completed | U39: 46295 | V39: 1 | W39: =IF($V39=1, "Completed", IF($U39<TODAY(), "Late", "On Schedule")) -> Completed | AA39: 46356 | AB39: 0 | AC39: =IF($AB39=1, "Completed", IF($AA39<TODAY(), "Late", "On Schedule")) -> On Schedule | AG39: =U39+30 -> 46325 | AH39: 0 | AI39: =IF($AH39=1, "Completed", IF($AG39<TODAY(), "Late", "On Schedule")) -> On Schedule | AK39: =IFERROR(SUMPRODUCT(($M$1:$AH$1),(M39:AH39))/SUMIF((M39:AH39),"<>",($M$1:$AH$1)),"") -> 0.83333333 | AL39: =IF($AK39=1, "Completed", IF($K39<TODAY(), "Late", "On Schedule")) -> Late | AN39: =_xlfn.XLOOKUP($E39,'00 MASTER WORK REGISTER'!B:B,'00 MASTER WORK REGISTER'!N:N,"") | AS39: MDW-39297 | AT39: MDW-69345 | AU39: MDW-69346
A40: 37 | B40: 37 | C40: MDW-39291 | D40: Lot01 | E40: GEN2.16 | F40: GEN | G40: Conductor Rail Arrangement Modification at Main Line East Section | H40: กำพล | K40: 46235 | L40: 46295 | M40: 1 | N40: =IF($M40=1, "Completed", IF($L40<TODAY(), "Late", "On Schedule")) -> Completed | O40: 46295 | P40: 1 | Q40: =IF($P40=1, "Completed", IF($O40<TODAY(), "Late", "On Schedule")) -> Completed | U40: 46387 | V40: 0.9 | W40: =IF($V40=1, "Completed", IF($U40<TODAY(), "Late", "On Schedule")) -> On Schedule | AA40: 46356 | AB40: 0 | AC40: =IF($AB40=1, "Completed", IF($AA40<TODAY(), "Late", "On Schedule")) -> On Schedule | AG40: =U40+30 -> 46417 | AH40: 0 | AI40: =IF($AH40=1, "Completed", IF($AG40<TODAY(), "Late", "On Schedule")) -> On Schedule | AK40: =IFERROR(SUMPRODUCT(($M$1:$AH$1),(M40:AH40))/SUMIF((M40:AH40),"<>",($M$1:$AH$1)),"") -> 0.88095238 | AL40: =IF($AK40=1, "Completed", IF($K40<TODAY(), "Late", "On Schedule")) -> Late | AN40: =_xlfn.XLOOKUP($E40,'00 MASTER WORK REGISTER'!B:B,'00 MASTER WORK REGISTER'!N:N,"") | AS40: MDW-39291 | AT40: MDW-69333 | AU40: MDW-69334
A41: 38 | B41: 38 | C41: MDW-39292 | D41: Lot01 | E41: GEN2.17 | F41: GEN | G41: Conductor Rail Arrangement Modification at Depot | H41: กำพล | K41: 46235 | L41: 46295 | M41: 1 | N41: =IF($M41=1, "Completed", IF($L41<TODAY(), "Late", "On Schedule")) -> Completed | O41: 46295 | P41: 1 | Q41: =IF($P41=1, "Completed", IF($O41<TODAY(), "Late", "On Schedule")) -> Completed | U41: 46387 | V41: 0.9 | W41: =IF($V41=1, "Completed", IF($U41<TODAY(), "Late", "On Schedule")) -> On Schedule | AA41: 46356 | AB41: 0 | AC41: =IF($AB41=1, "Completed", IF($AA41<TODAY(), "Late", "On Schedule")) -> On Schedule | AG41: =U41+30 -> 46417 | AH41: 0 | AI41: =IF($AH41=1, "Completed", IF($AG41<TODAY(), "Late", "On Schedule")) -> On Schedule | AK41: =IFERROR(SUMPRODUCT(($M$1:$AH$1),(M41:AH41))/SUMIF((M41:AH41),"<>",($M$1:$AH$1)),"") -> 0.88095238 | AL41: =IF($AK41=1, "Completed", IF($K41<TODAY(), "Late", "On Schedule")) -> Late | AN41: =_xlfn.XLOOKUP($E41,'00 MASTER WORK REGISTER'!B:B,'00 MASTER WORK REGISTER'!N:N,"") | AS41: MDW-39292 | AT41: MDW-69335 | AU41: MDW-69336
A42: 39 | B42: 39 | C42: MDW-39295 | D42: Lot01 | E42: GEN2.18 | F42: GEN | G42: Dangerous Goods Building in Depot - Civil & AR | H42: สหชาติ | K42: 46235 | L42: 46049 | M42: 1 | N42: =IF($M42=1, "Completed", IF($L42<TODAY(), "Late", "On Schedule")) -> Completed | O42: 46080 | P42: 1 | Q42: =IF($P42=1, "Completed", IF($O42<TODAY(), "Late", "On Schedule")) -> Completed | U42: 46142 | V42: 1 | W42: =IF($V42=1, "Completed", IF($U42<TODAY(), "Late", "On Schedule")) -> Completed | AA42: 46142 | AB42: 1 | AC42: =IF($AB42=1, "Completed", IF($AA42<TODAY(), "Late", "On Schedule")) -> Completed | AG42: 46326 | AH42: 0 | AI42: =IF($AH42=1, "Completed", IF($AG42<TODAY(), "Late", "On Schedule")) -> On Schedule | AK42: =IFERROR(SUMPRODUCT(($M$1:$AH$1),(M42:AH42))/SUMIF((M42:AH42),"<>",($M$1:$AH$1)),"") -> 0.96428571 | AL42: =IF($AK42=1, "Completed", IF($K42<TODAY(), "Late", "On Schedule")) -> Late | AN42: =_xlfn.XLOOKUP($E42,'00 MASTER WORK REGISTER'!B:B,'00 MASTER WORK REGISTER'!N:N,"") | AS42: MDW-39295 | AT42: MDW-69341 | AU42: MDW-69342
A43: 40 | B43: 40 | C43: MDW-39296 | D43: Lot01 | E43: GEN2.19 | F43: GEN | G43: Dangerous Goods Building in Depot - Building Services | H43: ประธาน | K43: 46235 | L43: 46004 | M43: 1 | N43: =IF($M43=1, "Completed", IF($L43<TODAY(), "Late", "On Schedule")) -> Completed | O43: 46050 | P43: 1 | Q43: =IF($P43=1, "Completed", IF($O43<TODAY(), "Late", "On Schedule")) -> Completed | U43: 46142 | V43: 1 | W43: =IF($V43=1, "Completed", IF($U43<TODAY(), "Late", "On Schedule")) -> Completed | AA43: 46142 | AB43: 1 | AC43: =IF($AB43=1, "Completed", IF($AA43<TODAY(), "Late", "On Schedule")) -> Completed | AD43: 46326 | AE43: 0 | AF43: =IF($AE43=1, "Completed", IF($AD43<TODAY(), "Late", "On Schedule")) -> On Schedule | AG43: 46326 | AH43: 0 | AI43: =IF($AH43=1, "Completed", IF($AG43<TODAY(), "Late", "On Schedule")) -> On Schedule | AK43: =IFERROR(SUMPRODUCT(($M$1:$AH$1),(M43:AH43))/SUMIF((M43:AH43),"<>",($M$1:$AH$1)),"") -> 0.95294118 | AL43: =IF($AK43=1, "Completed", IF($K43<TODAY(), "Late", "On Schedule")) -> Late | AN43: =_xlfn.XLOOKUP($E43,'00 MASTER WORK REGISTER'!B:B,'00 MASTER WORK REGISTER'!N:N,"") | AS43: MDW-39296 | AT43: MDW-69343 | AU43: MDW-69344
A44: 41 | B44: 41 | C44: MDW-39308 | D44: Lot01 | E44: GEN2.20 | F44: GEN | G44: Additional Locking Devices for Main Line Tandem Turnouts 2007, 2010 & 2013 and Depot Turnout D16 | H44: กำพล | K44: 46235 | L44: 46356 | M44: 0.5 | N44: =IF($M44=1, "Completed", IF($L44<TODAY(), "Late", "On Schedule")) -> On Schedule | O44: 46295 | P44: 1 | Q44: =IF($P44=1, "Completed", IF($O44<TODAY(), "Late", "On Schedule")) -> Completed | U44: 46387 | V44: 0 | W44: =IF($V44=1, "Completed", IF($U44<TODAY(), "Late", "On Schedule")) -> On Schedule | AA44: 46356 | AB44: 0 | AC44: =IF($AB44=1, "Completed", IF($AA44<TODAY(), "Late", "On Schedule")) -> On Schedule | AG44: =U44+30 -> 46417 | AH44: 0 | AI44: =IF($AH44=1, "Completed", IF($AG44<TODAY(), "Late", "On Schedule")) -> On Schedule | AK44: =IFERROR(SUMPRODUCT(($M$1:$AH$1),(M44:AH44))/SUMIF((M44:AH44),"<>",($M$1:$AH$1)),"") -> 0.17857143 | AL44: =IF($AK44=1, "Completed", IF($K44<TODAY(), "Late", "On Schedule")) -> Late | AN44: =_xlfn.XLOOKUP($E44,'00 MASTER WORK REGISTER'!B:B,'00 MASTER WORK REGISTER'!N:N,"") | AS44: MDW-39308 | AT44: MDW-69367 | AU44: MDW-69368
A45: 42 | B45: 42 | C45: =_xlfn.XLOOKUP($E45,'00 MASTER WORK REGISTER'!B:B,'00 MASTER WORK REGISTER'!L:L) -> MDW-39200-31 | D45: Lot01 | E45: GEN3 | F45: GEN | G45: =_xlfn.XLOOKUP($E45,'00 MASTER WORK REGISTER'!B:B,'00 MASTER WORK REGISTER'!H:H) -> Cable Containment Modification | H45: =_xlfn.XLOOKUP($E45,'00 MASTER WORK REGISTER'!B:B,'00 MASTER WORK REGISTER'!$I:$I,"") -> - | K45: =_xlfn.XLOOKUP($E45,'00 MASTER WORK REGISTER'!$B:$B,'00 MASTER WORK REGISTER'!$M:$M,"") -> 45805 | AK45: =IFERROR(SUMPRODUCT(($M$1:$AH$1),(M45:AH45))/SUMIF((M45:AH45),"<>",($M$1:$AH$1)),"") | AN45: =_xlfn.XLOOKUP($E45,'00 MASTER WORK REGISTER'!B:B,'00 MASTER WORK REGISTER'!N:N,"") -> 0 | AP45: =_xlfn.XLOOKUP($F45,#REF!,#REF!,"") -> #REF! | AS45: MDW-39200 | AT45: =_xlfn.XLOOKUP($AS45,'02 Design'!F:F,'02 Design'!AE:AE," ") | AU45: =_xlfn.XLOOKUP($AS45,'02 Design'!F:F,'02 Design'!AF:AF," ")
A46: 43 | B46: 43 | C46: =_xlfn.XLOOKUP($E46,'00 MASTER WORK REGISTER'!B:B,'00 MASTER WORK REGISTER'!L:L) -> - | D46: Lot01 | E46: GEN4 | F46: GEN | G46: =_xlfn.XLOOKUP($E46,'00 MASTER WORK REGISTER'!B:B,'00 MASTER WORK REGISTER'!H:H) -> Training Room and Workshop Room | H46: =_xlfn.XLOOKUP($E46,'00 MASTER WORK REGISTER'!B:B,'00 MASTER WORK REGISTER'!$I:$I,"") -> - | K46: =_xlfn.XLOOKUP($E46,'00 MASTER WORK REGISTER'!$B:$B,'00 MASTER WORK REGISTER'!$M:$M,"") -> 46113 | AN46: =_xlfn.XLOOKUP($E46,'00 MASTER WORK REGISTER'!B:B,'00 MASTER WORK REGISTER'!N:N,"") -> 0 | AP46: =_xlfn.XLOOKUP($F46,#REF!,#REF!,"") -> #REF! | AT46: =_xlfn.XLOOKUP($AS46,'02 Design'!F:F,'02 Design'!AE:AE," ") -> 0 | AU46: =_xlfn.XLOOKUP($AS46,'02 Design'!F:F,'02 Design'!AF:AF," ") -> 0
A47: 44 | B47: 44 | C47: =_xlfn.XLOOKUP($E47,'00 MASTER WORK REGISTER'!B:B,'00 MASTER WORK REGISTER'!L:L) -> MDW-39242 | D47: Lot01 | E47: GEN4.0 | F47: GEN | G47: =_xlfn.XLOOKUP($E47,'00 MASTER WORK REGISTER'!B:B,'00 MASTER WORK REGISTER'!H:H) -> Modification Works for Training Room at Ratchada Station | H47: =_xlfn.XLOOKUP($E47,'00 MASTER WORK REGISTER'!B:B,'00 MASTER WORK REGISTER'!$I:$I,"") -> ประธาน | K47: =_xlfn.XLOOKUP($E47,'00 MASTER WORK REGISTER'!$B:$B,'00 MASTER WORK REGISTER'!$M:$M,"") -> 46113 | L47: 46021 | M47: 1 | N47: =IF($M47=1, "Completed", IF($L47<TODAY(), "Late", "On Schedule")) -> Completed | O47: 46053 | P47: 1 | Q47: =IF($P47=1, "Completed", IF($O47<TODAY(), "Late", "On Schedule")) -> Completed | U47: 46112 | V47: 1 | W47: =IF($V47=1, "Completed", IF($U47<TODAY(), "Late", "On Schedule")) -> Completed | AA47: 46097 | AB47: 1 | AC47: =IF($AB47=1, "Completed", IF($AA47<TODAY(), "Late", "On Schedule")) -> Completed | AD47: 46295 | AE47: 1 | AF47: =IF($AE47=1, "Completed", IF($AD47<TODAY(), "Late", "On Schedule")) -> Completed | AG47: =AD47+21 -> 46316 | AH47: 1 | AI47: =IF($AH47=1, "Completed", IF($AG47<TODAY(), "Late", "On Schedule")) -> Completed | AK47: =IFERROR(SUMPRODUCT(($M$1:$AH$1),(M47:AH47))/SUMIF((M47:AH47),"<>",($M$1:$AH$1)),"") -> 1 | AL47: =IF($AK47=1, "Completed", IF($K47<TODAY(), "Late", "On Schedule")) -> Completed | AN47: =_xlfn.XLOOKUP($E47,'00 MASTER WORK REGISTER'!B:B,'00 MASTER WORK REGISTER'!N:N,"") -> 0 | AO47: จัดเตรียมห้อง Training Room and Workshop Room ที่สถานีรัชดา BL19 (เพิ่มท่อน้ำ เพิ่มถังดักไขมัน) | AP47: =_xlfn.XLOOKUP($F47,#REF!,#REF!,"") -> #REF! | AS47: MDW-39242 | AT47: =_xlfn.XLOOKUP($AS47,'02 Design'!F:F,'02 Design'!AE:AE," ") -> MDW-69251 | AU47: =_xlfn.XLOOKUP($AS47,'02 Design'!F:F,'02 Design'!AF:AF," ") -> MDW-69252
A48: 45 | B48: 45 | C48: =_xlfn.XLOOKUP($E48,'00 MASTER WORK REGISTER'!B:B,'00 MASTER WORK REGISTER'!L:L) -> MDW-39244 | D48: Lot01 | E48: GEN4.1 | F48: GEN | G48: =_xlfn.XLOOKUP($E48,'00 MASTER WORK REGISTER'!B:B,'00 MASTER WORK REGISTER'!H:H) -> AFC Training Room Modification - Civil & AR | H48: =_xlfn.XLOOKUP($E48,'00 MASTER WORK REGISTER'!B:B,'00 MASTER WORK REGISTER'!$I:$I,"") -> สหชาติ | K48: =_xlfn.XLOOKUP($E48,'00 MASTER WORK REGISTER'!$B:$B,'00 MASTER WORK REGISTER'!$M:$M,"") -> 46255 | L48: 46295 | M48: 0.1 | N48: =IF($M48=1, "Completed", IF($L48<TODAY(), "Late", "On Schedule")) -> Late | O48: 46310 | P48: 1 | Q48: =IF($P48=1, "Completed", IF($O48<TODAY(), "Late", "On Schedule")) -> Completed | U48: 46341 | V48: 0 | W48: =IF($V48=1, "Completed", IF($U48<TODAY(), "Late", "On Schedule")) -> On Schedule | AA48: =U48-15 -> 46326 | AB48: 0 | AC48: =IF($AB48=1, "Completed", IF($AA48<TODAY(), "Late", "On Schedule")) -> On Schedule | AD48: =U48+7 -> 46348 | AE48: 0 | AF48: =IF($AE48=1, "Completed", IF($AD48<TODAY(), "Late", "On Schedule")) -> On Schedule | AG48: 46371 | AH48: 0 | AI48: =IF($AH48=1, "Completed", IF($AG48<TODAY(), "Late", "On Schedule")) -> On Schedule | AK48: =IFERROR(SUMPRODUCT(($M$1:$AH$1),(M48:AH48))/SUMIF((M48:AH48),"<>",($M$1:$AH$1)),"") -> 0.12941176 | AL48: Late | AM48: อยู่ระหว่างจัดทำแบบก่อสร้าง | AN48: =_xlfn.XLOOKUP($E48,'00 MASTER WORK REGISTER'!B:B,'00 MASTER WORK REGISTER'!N:N,"") -> 0 | AO48: จัดเตรียมห้อง Training Room and Workshop Room ที่สถานีรัชดา BL19 (เพิ่มท่อน้ำ เพิ่มถังดักไขมัน) | AQ48: CV/AR | AS48: MDW-39244 | AT48: =_xlfn.XLOOKUP($AS48,'02 Design'!F:F,'02 Design'!AE:AE," ") -> MDW-69255 | AU48: =_xlfn.XLOOKUP($AS48,'02 Design'!F:F,'02 Design'!AF:AF," ") -> MDW-69256
A49: 46 | B49: 46 | C49: =_xlfn.XLOOKUP($E49,'00 MASTER WORK REGISTER'!B:B,'00 MASTER WORK REGISTER'!L:L) -> MDW-39245 | D49: Lot01 | E49: GEN4.2 | F49: GEN | G49: =_xlfn.XLOOKUP($E49,'00 MASTER WORK REGISTER'!B:B,'00 MASTER WORK REGISTER'!H:H) -> AFC Training Room Modification - Building Services | H49: =_xlfn.XLOOKUP($E49,'00 MASTER WORK REGISTER'!B:B,'00 MASTER WORK REGISTER'!$I:$I,"") -> ประธาน | K49: =_xlfn.XLOOKUP($E49,'00 MASTER WORK REGISTER'!$B:$B,'00 MASTER WORK REGISTER'!$M:$M,"") -> 46255 | L49: 46021 | M49: 1 | N49: =IF($M49=1, "Completed", IF($L49<TODAY(), "Late", "On Schedule")) -> Completed | O49: 46053 | P49: 1 | Q49: =IF($P49=1, "Completed", IF($O49<TODAY(), "Late", "On Schedule")) -> Completed | U49: 46112 | V49: 1 | W49: =IF($V49=1, "Completed", IF($U49<TODAY(), "Late", "On Schedule")) -> Completed | AA49: 46105 | AB49: 1 | AC49: =IF($AB49=1, "Completed", IF($AA49<TODAY(), "Late", "On Schedule")) -> Completed | AD49: 46241 | AE49: 1 | AF49: =IF($AE49=1, "Completed", IF($AD49<TODAY(), "Late", "On Schedule")) -> Completed | AG49: 46295 | AH49: 0 | AI49: =IF($AH49=1, "Completed", IF($AG49<TODAY(), "Late", "On Schedule")) -> Late | AK49: =IFERROR(SUMPRODUCT(($M$1:$AH$1),(M49:AH49))/SUMIF((M49:AH49),"<>",($M$1:$AH$1)),"") -> 0.96470588 | AL49: Late | AN49: =_xlfn.XLOOKUP($E49,'00 MASTER WORK REGISTER'!B:B,'00 MASTER WORK REGISTER'!N:N,"") -> 0 | AO49: จัดเตรียมห้อง Training Room and Workshop Room ที่สถานีรัชดา BL19 (เพิ่มท่อน้ำ เพิ่มถังดักไขมัน) | AP49: =_xlfn.XLOOKUP($F49,#REF!,#REF!,"") -> #REF! | AQ49: E&M | AS49: MDW-39245 | AT49: =_xlfn.XLOOKUP($AS49,'02 Design'!F:F,'02 Design'!AE:AE," ") -> MDW-69257 | AU49: =_xlfn.XLOOKUP($AS49,'02 Design'!F:F,'02 Design'!AF:AF," ") -> MDW-69258
A50: 47 | B50: 47 | C50: =_xlfn.XLOOKUP($E50,'00 MASTER WORK REGISTER'!B:B,'00 MASTER WORK REGISTER'!L:L) -> MDW-39235 | D50: Lot01 | E50: GEN5 | F50: GEN | G50: =_xlfn.XLOOKUP($E50,'00 MASTER WORK REGISTER'!B:B,'00 MASTER WORK REGISTER'!H:H) -> Raised Floor | H50: =_xlfn.XLOOKUP($E50,'00 MASTER WORK REGISTER'!B:B,'00 MASTER WORK REGISTER'!$I:$I,"") -> สหชาติ | K50: =_xlfn.XLOOKUP($E50,'00 MASTER WORK REGISTER'!$B:$B,'00 MASTER WORK REGISTER'!$M:$M,"") -> 46174 | L50: 45792 | M50: 1 | N50: =IF($M50=1, "Completed", IF($L50<TODAY(), "Late", "On Schedule")) -> Completed | O50: 45640 | P50: 1 | Q50: =IF($P50=1, "Completed", IF($O50<TODAY(), "Late", "On Schedule")) -> Completed | R50: 45873 | S50: 1 | T50: =IF($S50=1, "Completed", IF($R50<TODAY(), "Late", "On Schedule")) -> Completed | U50: 46019 | V50: 1 | W50: =IF($V50=1, "Completed", IF($U50<TODAY(), "Late", "On Schedule")) -> Completed | AA50: 45989 | AB50: 1 | AC50: =IF($AB50=1, "Completed", IF($AA50<TODAY(), "Late", "On Schedule")) -> Completed | AD50: 46295 | AE50: 0 | AF50: =IF($AE50=1, "Completed", IF($AD50<TODAY(), "Late", "On Schedule")) -> Late | AG50: =AD50+21 -> 46316 | AH50: 0 | AI50: =IF($AH50=1, "Completed", IF($AG50<TODAY(), "Late", "On Schedule")) -> Late | AK50: =IFERROR(SUMPRODUCT(($M$1:$AH$1),(M50:AH50))/SUMIF((M50:AH50),"<>",($M$1:$AH$1)),"") -> 0.95789474 | AL50: Late | AN50: =_xlfn.XLOOKUP($E50,'00 MASTER WORK REGISTER'!B:B,'00 MASTER WORK REGISTER'!N:N,"") -> 0 | AO50: จัดเตรียมและปรับปรุง Raised Floor สำหรับ M&E rooms | AP50: =_xlfn.XLOOKUP($F50,#REF!,#REF!,"") -> #REF! | AQ50: CV/AR | AS50: MDW-39235 | AT50: =_xlfn.XLOOKUP($AS50,'02 Design'!F:F,'02 Design'!AE:AE," ") -> MDW-69237 | AU50: =_xlfn.XLOOKUP($AS50,'02 Design'!F:F,'02 Design'!AF:AF," ") -> MDW-69238
A51: 48 | B51: 48 | C51: =_xlfn.XLOOKUP($E51,'00 MASTER WORK REGISTER'!B:B,'00 MASTER WORK REGISTER'!L:L) -> MDW-39271 | D51: Lot01 | E51: GEN6 | F51: GEN | G51: =_xlfn.XLOOKUP($E51,'00 MASTER WORK REGISTER'!B:B,'00 MASTER WORK REGISTER'!H:H) -> Wayside Cable Containment in Depot | H51: =_xlfn.XLOOKUP($E51,'00 MASTER WORK REGISTER'!B:B,'00 MASTER WORK REGISTER'!$I:$I,"") -> - | J51: Depot | K51: =_xlfn.XLOOKUP($E51,'00 MASTER WORK REGISTER'!$B:$B,'00 MASTER WORK REGISTER'!$M:$M,"") -> 46075 | L51: 45792 | M51: 1 | N51: =IF($M51=1, "Completed", IF($L51<TODAY(), "Late", "On Schedule")) -> Completed | O51: 45640 | P51: 1 | Q51: =IF($P51=1, "Completed", IF($O51<TODAY(), "Late", "On Schedule")) -> Completed | R51: 45873 | S51: 1 | T51: =IF($S51=1, "Completed", IF($R51<TODAY(), "Late", "On Schedule")) -> Completed | U51: 46019 | V51: 1 | W51: =IF($V51=1, "Completed", IF($U51<TODAY(), "Late", "On Schedule")) -> Completed | AA51: 46260 | AB51: 1 | AC51: =IF($AB51=1, "Completed", IF($AA51<TODAY(), "Late", "On Schedule")) -> Completed | AD51: 46295 | AE51: 0 | AF51: =IF($AE51=1, "Completed", IF($AD51<TODAY(), "Late", "On Schedule")) -> Late | AG51: 46316 | AH51: 0 | AI51: =IF($AH51=1, "Completed", IF($AG51<TODAY(), "Late", "On Schedule")) -> Late | AK51: =IFERROR(SUMPRODUCT(($M$1:$AH$1),(M51:AH51))/SUMIF((M51:AH51),"<>",($M$1:$AH$1)),"") -> 0.95789474 | AL51: Late | AN51: =_xlfn.XLOOKUP($E51,'00 MASTER WORK REGISTER'!B:B,'00 MASTER WORK REGISTER'!N:N,"") -> 0 | AO51: จัดเตรียมและติดตั้ง cable containment | AP51: =_xlfn.XLOOKUP($F51,#REF!,#REF!,"") -> #REF! | AS51: MDW-39271 | AT51: =_xlfn.XLOOKUP($AS51,'02 Design'!F:F,'02 Design'!AE:AE," ") -> MDW-69297 | AU51: =_xlfn.XLOOKUP($AS51,'02 Design'!F:F,'02 Design'!AF:AF," ") -> MDW-69298
A52: 49 | B52: 49 | C52: =_xlfn.XLOOKUP($E52,'00 MASTER WORK REGISTER'!B:B,'00 MASTER WORK REGISTER'!L:L) -> MDW-39269 | D52: Lot01 | E52: GEN6.1 | F52: GEN | G52: =_xlfn.XLOOKUP($E52,'00 MASTER WORK REGISTER'!B:B,'00 MASTER WORK REGISTER'!H:H) -> PSY Wayside Cable Containment for 24 Kv Cable under the Depot slab | H52: =_xlfn.XLOOKUP($E52,'00 MASTER WORK REGISTER'!B:B,'00 MASTER WORK REGISTER'!$I:$I,"") -> ประธาน | J52: Depot | K52: =_xlfn.XLOOKUP($E52,'00 MASTER WORK REGISTER'!$B:$B,'00 MASTER WORK REGISTER'!$M:$M,"") -> 46075 | AK52: =IFERROR(SUMPRODUCT(($M$1:$AH$1),(M52:AH52))/SUMIF((M52:AH52),"<>",($M$1:$AH$1)),"") | AN52: =_xlfn.XLOOKUP($E52,'00 MASTER WORK REGISTER'!B:B,'00 MASTER WORK REGISTER'!N:N,"") -> CANCLE | AO52: งานท่อสาย (PSY) เชื่อมระหว่างอาคารใน Depot | AP52: =_xlfn.XLOOKUP($F52,#REF!,#REF!,"") -> #REF! | AS52: MDW-39269 | AT52: =_xlfn.XLOOKUP($AS52,'02 Design'!F:F,'02 Design'!AE:AE," ") -> MDW-69293 | AU52: =_xlfn.XLOOKUP($AS52,'02 Design'!F:F,'02 Design'!AF:AF," ") -> MDW-69294
A53: 50 | B53: 50 | C53: =_xlfn.XLOOKUP($E53,'00 MASTER WORK REGISTER'!B:B,'00 MASTER WORK REGISTER'!L:L) -> MDW-39270 | D53: Lot01 | E53: GEN6.2 | F53: GEN | G53: =_xlfn.XLOOKUP($E53,'00 MASTER WORK REGISTER'!B:B,'00 MASTER WORK REGISTER'!H:H) -> COM/SIG Wayside Cable Containment in the Depot | H53: =_xlfn.XLOOKUP($E53,'00 MASTER WORK REGISTER'!B:B,'00 MASTER WORK REGISTER'!$I:$I,"") -> มนตรี/ประธาน | J53: Depot | K53: =_xlfn.XLOOKUP($E53,'00 MASTER WORK REGISTER'!$B:$B,'00 MASTER WORK REGISTER'!$M:$M,"") -> 46075 | AK53: =IFERROR(SUMPRODUCT(($M$1:$AH$1),(M53:AH53))/SUMIF((M53:AH53),"<>",($M$1:$AH$1)),"") | AN53: =_xlfn.XLOOKUP($E53,'00 MASTER WORK REGISTER'!B:B,'00 MASTER WORK REGISTER'!N:N,"") -> CANCLE | AO53: งานท่อ HDPE (COM/SIG)/tray เชื่อมระหว่างอาคารใน Depot | AP53: =_xlfn.XLOOKUP($F53,#REF!,#REF!,"") -> #REF! | AS53: MDW-39270 | AT53: =_xlfn.XLOOKUP($AS53,'02 Design'!F:F,'02 Design'!AE:AE," ") -> MDW-69295 | AU53: =_xlfn.XLOOKUP($AS53,'02 Design'!F:F,'02 Design'!AF:AF," ") -> MDW-69296
A54: 51 | B54: 51 | C54: =_xlfn.XLOOKUP($E54,'00 MASTER WORK REGISTER'!B:B,'00 MASTER WORK REGISTER'!L:L) -> - | D54: Lot01 | E54: GEN7 | F54: GEN | G54: =_xlfn.XLOOKUP($E54,'00 MASTER WORK REGISTER'!B:B,'00 MASTER WORK REGISTER'!H:H) -> Dangerous Waste Storage Building in Depot | H54: - | J54: Depot | K54: =_xlfn.XLOOKUP($E54,'00 MASTER WORK REGISTER'!$B:$B,'00 MASTER WORK REGISTER'!$M:$M,"") -> 46285 | AK54: =IFERROR(SUMPRODUCT(($M$1:$AH$1),(M54:AH54))/SUMIF((M54:AH54),"<>",($M$1:$AH$1)),"") | AN54: =_xlfn.XLOOKUP($E54,'00 MASTER WORK REGISTER'!B:B,'00 MASTER WORK REGISTER'!N:N,"") -> 0 | AO54: ก่อสร้างอาคารและงานระบบ Dangerous Waste Storage | AP54: =_xlfn.XLOOKUP($F54,#REF!,#REF!,"") -> #REF! | AT54: =_xlfn.XLOOKUP($AS54,'02 Design'!F:F,'02 Design'!AE:AE," ") -> 0 | AU54: =_xlfn.XLOOKUP($AS54,'02 Design'!F:F,'02 Design'!AF:AF," ") -> 0
A55: 52 | B55: 52 | C55: =_xlfn.XLOOKUP($E55,'00 MASTER WORK REGISTER'!B:B,'00 MASTER WORK REGISTER'!L:L) -> DWE-39024 | D55: Lot01 | E55: GEN7.1 | F55: GEN | G55: =_xlfn.XLOOKUP($E55,'00 MASTER WORK REGISTER'!B:B,'00 MASTER WORK REGISTER'!H:H) -> Dangerous Waste Storage Building in Depot - Civil & AR | H55: =_xlfn.XLOOKUP($E55,'00 MASTER WORK REGISTER'!B:B,'00 MASTER WORK REGISTER'!$I:$I,"") -> สหชาติ | J55: Depot | K55: =_xlfn.XLOOKUP($E55,'00 MASTER WORK REGISTER'!$B:$B,'00 MASTER WORK REGISTER'!$M:$M,"") -> 46285 | L55: 45930 | M55: 1 | N55: =IF($M55=1, "Completed", IF($L55<TODAY(), "Late", "On Schedule")) -> Completed | O55: 46096 | P55: 1 | Q55: =IF($P55=1, "Completed", IF($O55<TODAY(), "Late", "On Schedule")) -> Completed | U55: 46142 | V55: 1 | W55: =IF($V55=1, "Completed", IF($U55<TODAY(), "Late", "On Schedule")) -> Completed | AA55: 46218 | AB55: 1 | AC55: =IF($AB55=1, "Completed", IF($AA55<TODAY(), "Late", "On Schedule")) -> Completed | AD55: 46181 | AE55: 1 | AF55: =IF($AE55=1, "Completed", IF($AD55<TODAY(), "Late", "On Schedule")) -> Completed | AG55: 46295 | AH55: 0 | AI55: =IF($AH55=1, "Completed", IF($AG55<TODAY(), "Late", "On Schedule")) -> Late | AK55: =IFERROR(SUMPRODUCT(($M$1:$AH$1),(M55:AH55))/SUMIF((M55:AH55),"<>",($M$1:$AH$1)),"") -> 0.96470588 | AL55: On Schedule | AN55: =_xlfn.XLOOKUP($E55,'00 MASTER WORK REGISTER'!B:B,'00 MASTER WORK REGISTER'!N:N,"") -> 0 | AO55: ก่อสร้างอาคาร Dangerous Waste Storage(เพิ่มขนาดอาคารเป็น 100 ตร.ม.) | AP55: =_xlfn.XLOOKUP($F55,#REF!,#REF!,"") -> #REF! | AQ55: CV/AR+E&M | AS55: DWE-39024 | AT55: =_xlfn.XLOOKUP($AS55,'02 Design'!F:F,'02 Design'!AE:AE," ") -> DWE-69024 | AU55: =_xlfn.XLOOKUP($AS55,'02 Design'!F:F,'02 Design'!AF:AF," ") -> DWE-69124
A56: 53 | B56: 53 | C56: =_xlfn.XLOOKUP($E56,'00 MASTER WORK REGISTER'!B:B,'00 MASTER WORK REGISTER'!L:L) -> DWE-39025 | D56: Lot01 | E56: GEN7.2 | F56: GEN | G56: =_xlfn.XLOOKUP($E56,'00 MASTER WORK REGISTER'!B:B,'00 MASTER WORK REGISTER'!H:H) -> Dangerous Waste Storage Building in Depot - Building service | H56: =_xlfn.XLOOKUP($E56,'00 MASTER WORK REGISTER'!B:B,'00 MASTER WORK REGISTER'!$I:$I,"") -> ประธาน | J56: Depot | K56: =_xlfn.XLOOKUP($E56,'00 MASTER WORK REGISTER'!$B:$B,'00 MASTER WORK REGISTER'!$M:$M,"") -> 46285 | L56: 45930 | M56: 1 | N56: =IF($M56=1, "Completed", IF($L56<TODAY(), "Late", "On Schedule")) -> Completed | O56: 46096 | P56: 1 | Q56: =IF($P56=1, "Completed", IF($O56<TODAY(), "Late", "On Schedule")) -> Completed | U56: 46203 | V56: 1 | W56: =IF($V56=1, "Completed", IF($U56<TODAY(), "Late", "On Schedule")) -> Completed | AA56: 46132 | AB56: 1 | AC56: =IF($AB56=1, "Completed", IF($AA56<TODAY(), "Late", "On Schedule")) -> Completed | AD56: 46181 | AE56: 1 | AF56: =IF($AE56=1, "Completed", IF($AD56<TODAY(), "Late", "On Schedule")) -> Completed | AG56: 46295 | AH56: 0 | AI56: =IF($AH56=1, "Completed", IF($AG56<TODAY(), "Late", "On Schedule")) -> Late | AK56: =IFERROR(SUMPRODUCT(($M$1:$AH$1),(M56:AH56))/SUMIF((M56:AH56),"<>",($M$1:$AH$1)),"") -> 0.96470588 | AL56: On Schedule | AN56: =_xlfn.XLOOKUP($E56,'00 MASTER WORK REGISTER'!B:B,'00 MASTER WORK REGISTER'!N:N,"") -> 0 | AO56: เพิ่มงานระบบ Dangerous Waste Storage(เพิ่มระบบZero waste) | AP56: =_xlfn.XLOOKUP($F56,#REF!,#REF!,"") -> #REF! | AQ56: CV/AR+E&M | AS56: DWE-39025 | AT56: =_xlfn.XLOOKUP($AS56,'02 Design'!F:F,'02 Design'!AE:AE," ") -> DWE-69025 | AU56: =_xlfn.XLOOKUP($AS56,'02 Design'!F:F,'02 Design'!AF:AF," ") -> DWE-69125
A57: 54 | B57: 54 | C57: =_xlfn.XLOOKUP($E57,'00 MASTER WORK REGISTER'!B:B,'00 MASTER WORK REGISTER'!L:L) -> - | D57: Lot01 | E57: GEN8 | F57: GEN | G57: =_xlfn.XLOOKUP($E57,'00 MASTER WORK REGISTER'!B:B,'00 MASTER WORK REGISTER'!H:H) -> General Waste Storage Building in Depot | H57: - | J57: Depot | K57: =_xlfn.XLOOKUP($E57,'00 MASTER WORK REGISTER'!$B:$B,'00 MASTER WORK REGISTER'!$M:$M,"") -> 46285 | AK57: =IFERROR(SUMPRODUCT(($M$1:$AH$1),(M57:AH57))/SUMIF((M57:AH57),"<>",($M$1:$AH$1)),"") | AN57: =_xlfn.XLOOKUP($E57,'00 MASTER WORK REGISTER'!B:B,'00 MASTER WORK REGISTER'!N:N,"") -> 0 | AO57: ก่อสร้างอาคารและงานระบบ General Waste Storage | AP57: =_xlfn.XLOOKUP($F57,#REF!,#REF!,"") -> #REF! | AT57: =_xlfn.XLOOKUP($AS57,'02 Design'!F:F,'02 Design'!AE:AE," ") -> 0 | AU57: =_xlfn.XLOOKUP($AS57,'02 Design'!F:F,'02 Design'!AF:AF," ") -> 0
A58: 55 | B58: 55 | C58: =_xlfn.XLOOKUP($E58,'00 MASTER WORK REGISTER'!B:B,'00 MASTER WORK REGISTER'!L:L) -> DWE-39026 | D58: Lot01 | E58: GEN8.1 | F58: GEN | G58: =_xlfn.XLOOKUP($E58,'00 MASTER WORK REGISTER'!B:B,'00 MASTER WORK REGISTER'!H:H) -> General Waste Storage Building in Depot - Civil & AR | H58: =_xlfn.XLOOKUP($E58,'00 MASTER WORK REGISTER'!B:B,'00 MASTER WORK REGISTER'!$I:$I,"") -> สหชาติ | J58: Depot | K58: =_xlfn.XLOOKUP($E58,'00 MASTER WORK REGISTER'!$B:$B,'00 MASTER WORK REGISTER'!$M:$M,"") -> 46285 | L58: 45930 | M58: 1 | N58: =IF($M58=1, "Completed", IF($L58<TODAY(), "Late", "On Schedule")) -> Completed | O58: 46096 | P58: 1 | Q58: =IF($P58=1, "Completed", IF($O58<TODAY(), "Late", "On Schedule")) -> Completed | U58: 46142 | V58: 1 | W58: =IF($V58=1, "Completed", IF($U58<TODAY(), "Late", "On Schedule")) -> Completed | AA58: 46218 | AB58: 1 | AC58: =IF($AB58=1, "Completed", IF($AA58<TODAY(), "Late", "On Schedule")) -> Completed | AD58: 46181 | AE58: 1 | AF58: =IF($AE58=1, "Completed", IF($AD58<TODAY(), "Late", "On Schedule")) -> Completed | AG58: 46295 | AH58: 0 | AI58: =IF($AH58=1, "Completed", IF($AG58<TODAY(), "Late", "On Schedule")) -> Late | AK58: =IFERROR(SUMPRODUCT(($M$1:$AH$1),(M58:AH58))/SUMIF((M58:AH58),"<>",($M$1:$AH$1)),"") -> 0.96470588 | AL58: On Schedule | AN58: =_xlfn.XLOOKUP($E58,'00 MASTER WORK REGISTER'!B:B,'00 MASTER WORK REGISTER'!N:N,"") -> 0 | AO58: ก่อสร้างอาคาร General Waste Storage | AP58: =_xlfn.XLOOKUP($F58,#REF!,#REF!,"") -> #REF! | AQ58: CV/AR+E&M | AS58: DWE-39026 | AT58: =_xlfn.XLOOKUP($AS58,'02 Design'!F:F,'02 Design'!AE:AE," ") -> DWE-69026 | AU58: =_xlfn.XLOOKUP($AS58,'02 Design'!F:F,'02 Design'!AF:AF," ") -> DWE-69126
A59: 56 | B59: 56 | C59: =_xlfn.XLOOKUP($E59,'00 MASTER WORK REGISTER'!B:B,'00 MASTER WORK REGISTER'!L:L) -> DWE-39025 | D59: Lot01 | E59: GEN8.2 | F59: GEN | G59: =_xlfn.XLOOKUP($E59,'00 MASTER WORK REGISTER'!B:B,'00 MASTER WORK REGISTER'!H:H) -> General Waste Storage Building in Depot - Building service | H59: =_xlfn.XLOOKUP($E59,'00 MASTER WORK REGISTER'!B:B,'00 MASTER WORK REGISTER'!$I:$I,"") -> ประธาน | J59: Depot | K59: =_xlfn.XLOOKUP($E59,'00 MASTER WORK REGISTER'!$B:$B,'00 MASTER WORK REGISTER'!$M:$M,"") -> 46285 | L59: 45930 | M59: 1 | N59: =IF($M59=1, "Completed", IF($L59<TODAY(), "Late", "On Schedule")) -> Completed | O59: 46096 | P59: 1 | Q59: =IF($P59=1, "Completed", IF($O59<TODAY(), "Late", "On Schedule")) -> Completed | U59: 46203 | V59: 1 | W59: =IF($V59=1, "Completed", IF($U59<TODAY(), "Late", "On Schedule")) -> Completed | AA59: 46132 | AB59: 1 | AC59: =IF($AB59=1, "Completed", IF($AA59<TODAY(), "Late", "On Schedule")) -> Completed | AD59: 46181 | AE59: 1 | AF59: =IF($AE59=1, "Completed", IF($AD59<TODAY(), "Late", "On Schedule")) -> Completed | AG59: 46295 | AH59: 0 | AI59: =IF($AH59=1, "Completed", IF($AG59<TODAY(), "Late", "On Schedule")) -> Late | AK59: =IFERROR(SUMPRODUCT(($M$1:$AH$1),(M59:AH59))/SUMIF((M59:AH59),"<>",($M$1:$AH$1)),"") -> 0.96470588 | AL59: On Schedule | AN59: =_xlfn.XLOOKUP($E59,'00 MASTER WORK REGISTER'!B:B,'00 MASTER WORK REGISTER'!N:N,"") -> 0 | AO59: เพิ่มงานระบบ General Waste Storage | AP59: =_xlfn.XLOOKUP($F59,#REF!,#REF!,"") -> #REF! | AQ59: CV/AR+E&M | AS59: DWE-39025 | AT59: =_xlfn.XLOOKUP($AS59,'02 Design'!F:F,'02 Design'!AE:AE," ") -> DWE-69025 | AU59: =_xlfn.XLOOKUP($AS59,'02 Design'!F:F,'02 Design'!AF:AF," ") -> DWE-69125
A60: 57 | B60: 57 | C60: =_xlfn.XLOOKUP($E60,'00 MASTER WORK REGISTER'!B:B,'00 MASTER WORK REGISTER'!L:L) -> DWE-39021 | D60: Lot01 | E60: GEN9 | F60: GEN | G60: =_xlfn.XLOOKUP($E60,'00 MASTER WORK REGISTER'!B:B,'00 MASTER WORK REGISTER'!H:H) -> Operation Support Equipment | H60: =_xlfn.XLOOKUP($E60,'00 MASTER WORK REGISTER'!B:B,'00 MASTER WORK REGISTER'!$I:$I,"") -> สมศักดิ์ | J60: Depot | K60: =_xlfn.XLOOKUP($E60,'00 MASTER WORK REGISTER'!$B:$B,'00 MASTER WORK REGISTER'!$M:$M,"") -> 46255 | L60: 45718 | M60: 1 | N60: =IF($M60=1, "Completed", IF($L60<TODAY(), "Late", "On Schedule")) -> Completed | O60: 45963 | P60: 1 | Q60: =IF($P60=1, "Completed", IF($O60<TODAY(), "Late", "On Schedule")) -> Completed | R60: 46342 | S60: 0.9 | T60: =IF($S60=1, "Completed", IF($R60<TODAY(), "Late", "On Schedule")) -> On Schedule | AA60: 46312 | AB60: 0 | AC60: =IF($AB60=1, "Completed", IF($AA60<TODAY(), "Late", "On Schedule")) -> Late | AD60: =R60+7 -> 46349 | AE60: 0 | AF60: =IF($AE60=1, "Completed", IF($AD60<TODAY(), "Late", "On Schedule")) -> On Schedule | AG60: 46372 | AH60: 0 | AI60: =IF($AH60=1, "Completed", IF($AG60<TODAY(), "Late", "On Schedule")) -> On Schedule | AK60: =IFERROR(SUMPRODUCT(($M$1:$AH$1),(M60:AH60))/SUMIF((M60:AH60),"<>",($M$1:$AH$1)),"") -> 0.82857143 | AL60: Late | AM60: คงเหลือจัดส่ง Signal Lamp | AN60: =_xlfn.XLOOKUP($E60,'00 MASTER WORK REGISTER'!B:B,'00 MASTER WORK REGISTER'!N:N,"") -> 0 | AO60: จัดเตรียม Short Circuit Device(236 set), Voltage Detector(118 set), Signal Lamp(248 set) | AP60: =_xlfn.XLOOKUP($F60,#REF!,#REF!,"") -> #REF! | AS60: DWE-39021 | AT60: =_xlfn.XLOOKUP($AS60,'02 Design'!F:F,'02 Design'!AE:AE," ") -> DWE-69021 | AU60: =_xlfn.XLOOKUP($AS60,'02 Design'!F:F,'02 Design'!AF:AF," ") -> DWE-69121
A61: 58 | B61: 58 | C61: =_xlfn.XLOOKUP($E61,'00 MASTER WORK REGISTER'!B:B,'00 MASTER WORK REGISTER'!L:L) -> GRS-39001-40 | D61: Lot01 | E61: GEN10.1 | F61: GEN | G61: =_xlfn.XLOOKUP($E61,'00 MASTER WORK REGISTER'!B:B,'00 MASTER WORK REGISTER'!H:H) -> Graphic and Signage Station | H61: =_xlfn.XLOOKUP($E61,'00 MASTER WORK REGISTER'!B:B,'00 MASTER WORK REGISTER'!$I:$I,"") -> สหชาติ | K61: =_xlfn.XLOOKUP($E61,'00 MASTER WORK REGISTER'!$B:$B,'00 MASTER WORK REGISTER'!$M:$M,"") -> 46255 | L61: 46203 | M61: 1 | N61: =IF($M61=1, "Completed", IF($L61<TODAY(), "Late", "On Schedule")) -> Completed | O61: 46173 | P61: 0.95 | Q61: =IF($P61=1, "Completed", IF($O61<TODAY(), "Late", "On Schedule")) -> Late | R61: 46418 | S61: 0.76 | T61: =IF($S61=1, "Completed", IF($R61<TODAY(), "Late", "On Schedule")) -> On Schedule | U61: 46446 | V61: 0.34 | W61: =IF($V61=1, "Completed", IF($U61<TODAY(), "Late", "On Schedule")) -> On Schedule | AK61: =IFERROR(SUMPRODUCT(($M$1:$AH$1),(M61:AH61))/SUMIF((M61:AH61),"<>",($M$1:$AH$1)),"") -> 0.52777778 | AL61: Late | AM61: GRS | AN61: =_xlfn.XLOOKUP($E61,'00 MASTER WORK REGISTER'!B:B,'00 MASTER WORK REGISTER'!N:N,"") -> 0 | AO61: จัดเตรียมงาน Graphic and Signage(ตะวันออก, ตะวันตก) ที่ station | AP61: =_xlfn.XLOOKUP($F61,#REF!,#REF!,"") -> #REF! | AQ61: CV/AR | AS61: GRS-39001 | AT61: =_xlfn.XLOOKUP($AS61,'02 Design'!F:F,'02 Design'!AE:AE," ") -> GRS-69001 | AU61: =_xlfn.XLOOKUP($AS61,'02 Design'!F:F,'02 Design'!AF:AF," ") -> GRS-69002
A62: 59 | B62: 59 | C62: =_xlfn.XLOOKUP($E62,'00 MASTER WORK REGISTER'!B:B,'00 MASTER WORK REGISTER'!L:L) -> GRS-39001-40 | D62: Lot01 | E62: GEN10.2 | F62: GEN | G62: =_xlfn.XLOOKUP($E62,'00 MASTER WORK REGISTER'!B:B,'00 MASTER WORK REGISTER'!H:H) -> Graphic and Signage Mainline & IVS,VS | H62: =_xlfn.XLOOKUP($E62,'00 MASTER WORK REGISTER'!B:B,'00 MASTER WORK REGISTER'!$I:$I,"") -> สหชาติ | K62: =_xlfn.XLOOKUP($E62,'00 MASTER WORK REGISTER'!$B:$B,'00 MASTER WORK REGISTER'!$M:$M,"") -> 46255 | L62: 46188 | M62: 0.79 | N62: =IF($M62=1, "Completed", IF($L62<TODAY(), "Late", "On Schedule")) -> Late | O62: 46173 | P62: 0.95 | Q62: =IF($P62=1, "Completed", IF($O62<TODAY(), "Late", "On Schedule")) -> Late | R62: 46234 | S62: 0 | T62: =IF($S62=1, "Completed", IF($R62<TODAY(), "Late", "On Schedule")) -> Late | U62: 46234 | V62: 0 | W62: =IF($V62=1, "Completed", IF($U62<TODAY(), "Late", "On Schedule")) -> Late | AK62: =IFERROR(SUMPRODUCT(($M$1:$AH$1),(M62:AH62))/SUMIF((M62:AH62),"<>",($M$1:$AH$1)),"") -> 0.19333333 | AL62: Late | AM62: GRS | AN62: =_xlfn.XLOOKUP($E62,'00 MASTER WORK REGISTER'!B:B,'00 MASTER WORK REGISTER'!N:N,"") -> 0 | AO62: จัดเตรียมงาน Graphic and Signage(ตะวันออก, ตะวันตก) ที่ mainline & IVS,VS | AS62: GRS-39001 | AT62: =_xlfn.XLOOKUP($AS62,'02 Design'!F:F,'02 Design'!AE:AE," ") -> GRS-69001 | AU62: =_xlfn.XLOOKUP($AS62,'02 Design'!F:F,'02 Design'!AF:AF," ") -> GRS-69002
A63: 60 | B63: 60 | C63: =_xlfn.XLOOKUP($E63,'00 MASTER WORK REGISTER'!B:B,'00 MASTER WORK REGISTER'!L:L) -> GRS-39001-40 | D63: Lot01 | E63: GEN10.3 | F63: GEN | G63: =_xlfn.XLOOKUP($E63,'00 MASTER WORK REGISTER'!B:B,'00 MASTER WORK REGISTER'!H:H) -> Graphic and Signage Depot | H63: =_xlfn.XLOOKUP($E63,'00 MASTER WORK REGISTER'!B:B,'00 MASTER WORK REGISTER'!$I:$I,"") -> สหชาติ | K63: =_xlfn.XLOOKUP($E63,'00 MASTER WORK REGISTER'!$B:$B,'00 MASTER WORK REGISTER'!$M:$M,"") -> 46255 | L63: 46249 | M63: 0.9 | N63: =IF($M63=1, "Completed", IF($L63<TODAY(), "Late", "On Schedule")) -> Late | O63: 46234 | P63: 0.93 | Q63: =IF($P63=1, "Completed", IF($O63<TODAY(), "Late", "On Schedule")) -> Late | R63: 46203 | S63: 0.56 | T63: =IF($S63=1, "Completed", IF($R63<TODAY(), "Late", "On Schedule")) -> Late | U63: 46203 | V63: 0.19 | W63: =IF($V63=1, "Completed", IF($U63<TODAY(), "Late", "On Schedule")) -> Late | AK63: =IFERROR(SUMPRODUCT(($M$1:$AH$1),(M63:AH63))/SUMIF((M63:AH63),"<>",($M$1:$AH$1)),"") -> 0.39222222 | AL63: Late | AM63: GRS | AN63: =_xlfn.XLOOKUP($E63,'00 MASTER WORK REGISTER'!B:B,'00 MASTER WORK REGISTER'!N:N,"") -> 0 | AO63: จัดเตรียมงาน Graphic and Signage(ตะวันออก, ตะวันตก) ที่ Depot | AS63: GRS-39001 | AT63: =_xlfn.XLOOKUP($AS63,'02 Design'!F:F,'02 Design'!AE:AE," ") -> GRS-69001 | AU63: =_xlfn.XLOOKUP($AS63,'02 Design'!F:F,'02 Design'!AF:AF," ") -> GRS-69002
A64: 61 | B64: 61 | C64: =_xlfn.XLOOKUP($E64,'00 MASTER WORK REGISTER'!B:B,'00 MASTER WORK REGISTER'!L:L) -> MDW-39289 | D64: Lot01 | E64: GEN11 | F64: GEN | G64: =_xlfn.XLOOKUP($E64,'00 MASTER WORK REGISTER'!B:B,'00 MASTER WORK REGISTER'!H:H) -> Earthing and Bonding Modification | H64: =_xlfn.XLOOKUP($E64,'00 MASTER WORK REGISTER'!B:B,'00 MASTER WORK REGISTER'!$I:$I,"") -> ประธาน | K64: =_xlfn.XLOOKUP($E64,'00 MASTER WORK REGISTER'!$B:$B,'00 MASTER WORK REGISTER'!$M:$M,"") -> 46082 | L64: 45688 | M64: 1 | N64: =IF($M64=1, "Completed", IF($L64<TODAY(), "Late", "On Schedule")) -> Completed | O64: 45930 | P64: 1 | Q64: =IF($P64=1, "Completed", IF($O64<TODAY(), "Late", "On Schedule")) -> Completed | U64: 46081 | V64: 1 | W64: =IF($V64=1, "Completed", IF($U64<TODAY(), "Late", "On Schedule")) -> Completed | X64: 46111 | Y64: 1 | Z64: =IF($Y64=1, "Completed", IF($X64<TODAY(), "Late", "On Schedule")) -> Completed | AA64: =AD64-7 -> 46288 | AB64: 0 | AC64: =IF($AB64=1, "Completed", IF($AA64<TODAY(), "Late", "On Schedule")) -> Late | AD64: 46295 | AE64: 0 | AF64: =IF($AE64=1, "Completed", IF($AD64<TODAY(), "Late", "On Schedule")) -> Late | AG64: =AD64+21 -> 46316 | AH64: 0 | AI64: =IF($AH64=1, "Completed", IF($AG64<TODAY(), "Late", "On Schedule")) -> Late | AK64: =IFERROR(SUMPRODUCT(($M$1:$AH$1),(M64:AH64))/SUMIF((M64:AH64),"<>",($M$1:$AH$1)),"") -> 0.94444444 | AL64: Late | AN64: =_xlfn.XLOOKUP($E64,'00 MASTER WORK REGISTER'!B:B,'00 MASTER WORK REGISTER'!N:N,"") -> 0 | AO64: จัดหาและติดตั้ง Earth Mat, Earth bus bar รวมถึงสายดิน | AP64: =_xlfn.XLOOKUP($F64,#REF!,#REF!,"") -> #REF! | AS64: MDW-39289 | AT64: =_xlfn.XLOOKUP($AS64,'02 Design'!F:F,'02 Design'!AE:AE," ") -> MDW-69329 | AU64: =_xlfn.XLOOKUP($AS64,'02 Design'!F:F,'02 Design'!AF:AF," ") -> MDW-69330
A65: 62 | B65: 62 | C65: =_xlfn.XLOOKUP($E65,'00 MASTER WORK REGISTER'!B:B,'00 MASTER WORK REGISTER'!L:L) -> - | D65: Lot01 | E65: GEN12 | F65: GEN | G65: =_xlfn.XLOOKUP($E65,'00 MASTER WORK REGISTER'!B:B,'00 MASTER WORK REGISTER'!H:H) -> Mainline Cable Trough Modification on East Section | H65: =_xlfn.XLOOKUP($E65,'00 MASTER WORK REGISTER'!B:B,'00 MASTER WORK REGISTER'!$I:$I,"") -> - | K65: =_xlfn.XLOOKUP($E65,'00 MASTER WORK REGISTER'!$B:$B,'00 MASTER WORK REGISTER'!$M:$M,"") -> 46195 | L65: 45961 | M65: 1 | N65: =IF($M65=1, "Completed", IF($L65<TODAY(), "Late", "On Schedule")) -> Completed | O65: 45991 | P65: 1 | Q65: =IF($P65=1, "Completed", IF($O65<TODAY(), "Late", "On Schedule")) -> Completed | R65: 46021 | S65: 1 | T65: =IF($S65=1, "Completed", IF($R65<TODAY(), "Late", "On Schedule")) -> Completed | U65: 46111 | V65: 1 | W65: =IF($V65=1, "Completed", IF($U65<TODAY(), "Late", "On Schedule")) -> Completed | AA65: 46295 | AB65: 0.8 | AC65: =IF($AB65=1, "Completed", IF($AA65<TODAY(), "Late", "On Schedule")) -> Late | AD65: =AA65+7 -> 46302 | AE65: 0 | AF65: =IF($AE65=1, "Completed", IF($AD65<TODAY(), "Late", "On Schedule")) -> Late | AG65: 46325 | AH65: 0 | AI65: =IF($AH65=1, "Completed", IF($AG65<TODAY(), "Late", "On Schedule")) -> On Schedule | AK65: =IFERROR(SUMPRODUCT(($M$1:$AH$1),(M65:AH65))/SUMIF((M65:AH65),"<>",($M$1:$AH$1)),"") -> 0.95578947 | AL65: Late | AN65: =_xlfn.XLOOKUP($E65,'00 MASTER WORK REGISTER'!B:B,'00 MASTER WORK REGISTER'!N:N,"") -> 0 | AO65: ปรับปรุง concrete cable trough เดิม | AP65: =_xlfn.XLOOKUP($F65,#REF!,#REF!,"") -> #REF! | AT65: =_xlfn.XLOOKUP($AS65,'02 Design'!F:F,'02 Design'!AE:AE," ") -> 0 | AU65: =_xlfn.XLOOKUP($AS65,'02 Design'!F:F,'02 Design'!AF:AF," ") -> 0
A66: 63 | B66: 63 | C66: =_xlfn.XLOOKUP($E66,'00 MASTER WORK REGISTER'!B:B,'00 MASTER WORK REGISTER'!L:L) -> MDW-39233 | D66: Lot01 | E66: GEN12.1 | F66: GEN | G66: =_xlfn.XLOOKUP($E66,'00 MASTER WORK REGISTER'!B:B,'00 MASTER WORK REGISTER'!H:H) -> Main Line Cable Trough Modification (PSY) | H66: =_xlfn.XLOOKUP($E66,'00 MASTER WORK REGISTER'!B:B,'00 MASTER WORK REGISTER'!$I:$I,"") -> มนต์ชัย | J66: Depot | K66: =_xlfn.XLOOKUP($E66,'00 MASTER WORK REGISTER'!$B:$B,'00 MASTER WORK REGISTER'!$M:$M,"") -> 46195 | L66: 45961 | M66: 1 | N66: =IF($M66=1, "Completed", IF($L66<TODAY(), "Late", "On Schedule")) -> Completed | O66: 45991 | P66: 1 | Q66: =IF($P66=1, "Completed", IF($O66<TODAY(), "Late", "On Schedule")) -> Completed | R66: 46021 | S66: 1 | T66: =IF($S66=1, "Completed", IF($R66<TODAY(), "Late", "On Schedule")) -> Completed | U66: 46111 | V66: 1 | W66: =IF($V66=1, "Completed", IF($U66<TODAY(), "Late", "On Schedule")) -> Completed | AA66: 46295 | AB66: 0.8 | AC66: =IF($AB66=1, "Completed", IF($AA66<TODAY(), "Late", "On Schedule")) -> Late | AD66: =AA66+7 -> 46302 | AE66: 0 | AF66: =IF($AE66=1, "Completed", IF($AD66<TODAY(), "Late", "On Schedule")) -> Late | AG66: 46325 | AH66: 0 | AI66: =IF($AH66=1, "Completed", IF($AG66<TODAY(), "Late", "On Schedule")) -> On Schedule | AK66: =IFERROR(SUMPRODUCT(($M$1:$AH$1),(M66:AH66))/SUMIF((M66:AH66),"<>",($M$1:$AH$1)),"") -> 0.95578947 | AL66: Late | AN66: =_xlfn.XLOOKUP($E66,'00 MASTER WORK REGISTER'!B:B,'00 MASTER WORK REGISTER'!N:N,"") -> 0 | AO66: แก้ Cable Trough เดิมบน ELEV Station 4จุด ต่อสถานี | AP66: =_xlfn.XLOOKUP($F66,#REF!,#REF!,"") -> #REF! | AS66: MDW-39233 | AT66: =_xlfn.XLOOKUP($AS66,'02 Design'!F:F,'02 Design'!AE:AE," ") | AU66: =_xlfn.XLOOKUP($AS66,'02 Design'!F:F,'02 Design'!AF:AF," ")
A67: 64 | B67: 64 | C67: =_xlfn.XLOOKUP($E67,'00 MASTER WORK REGISTER'!B:B,'00 MASTER WORK REGISTER'!L:L) -> MDW-39234 | D67: Lot01 | E67: GEN12.2 | F67: GEN | G67: =_xlfn.XLOOKUP($E67,'00 MASTER WORK REGISTER'!B:B,'00 MASTER WORK REGISTER'!H:H) -> Main Line Cable Trough Modification (SIG/COM) | H67: =_xlfn.XLOOKUP($E67,'00 MASTER WORK REGISTER'!B:B,'00 MASTER WORK REGISTER'!$I:$I,"") -> มนตรี | K67: =_xlfn.XLOOKUP($E67,'00 MASTER WORK REGISTER'!$B:$B,'00 MASTER WORK REGISTER'!$M:$M,"") -> 46195 | L67: 45961 | M67: 1 | N67: =IF($M67=1, "Completed", IF($L67<TODAY(), "Late", "On Schedule")) -> Completed | O67: 45991 | P67: 1 | Q67: =IF($P67=1, "Completed", IF($O67<TODAY(), "Late", "On Schedule")) -> Completed | R67: 46021 | S67: 1 | T67: =IF($S67=1, "Completed", IF($R67<TODAY(), "Late", "On Schedule")) -> Completed | U67: 46111 | V67: 1 | W67: =IF($V67=1, "Completed", IF($U67<TODAY(), "Late", "On Schedule")) -> Completed | AA67: 46295 | AB67: 0.8 | AC67: =IF($AB67=1, "Completed", IF($AA67<TODAY(), "Late", "On Schedule")) -> Late | AD67: =AA67+7 -> 46302 | AE67: 0 | AF67: =IF($AE67=1, "Completed", IF($AD67<TODAY(), "Late", "On Schedule")) -> Late | AG67: 46325 | AH67: 0 | AI67: =IF($AH67=1, "Completed", IF($AG67<TODAY(), "Late", "On Schedule")) -> On Schedule | AK67: =IFERROR(SUMPRODUCT(($M$1:$AH$1),(M67:AH67))/SUMIF((M67:AH67),"<>",($M$1:$AH$1)),"") -> 0.95578947 | AL67: Late | AM67: งานจบแล้ว | AN67: =_xlfn.XLOOKUP($E67,'00 MASTER WORK REGISTER'!B:B,'00 MASTER WORK REGISTER'!N:N,"") -> 0 | AO67: ทำ Cable Trough เพิ่มเติมในส่วนที่ Civil ทำไม่ครบ(OR24-25) | AP67: =_xlfn.XLOOKUP($F67,#REF!,#REF!,"") -> #REF! | AS67: MDW-39234 | AT67: =_xlfn.XLOOKUP($AS67,'02 Design'!F:F,'02 Design'!AE:AE," ") -> MDW-69234 | AU67: =_xlfn.XLOOKUP($AS67,'02 Design'!F:F,'02 Design'!AF:AF," ") -> MDW-69236
A68: 65 | B68: 65 | C68: =_xlfn.XLOOKUP($E68,'00 MASTER WORK REGISTER'!B:B,'00 MASTER WORK REGISTER'!L:L) -> MDW-39236 | D68: Lot01 | E68: GEN13 | F68: GEN | G68: =_xlfn.XLOOKUP($E68,'00 MASTER WORK REGISTER'!B:B,'00 MASTER WORK REGISTER'!H:H) -> Bird Protection System | H68: =_xlfn.XLOOKUP($E68,'00 MASTER WORK REGISTER'!B:B,'00 MASTER WORK REGISTER'!$I:$I,"") -> สหชาติ | K68: =_xlfn.XLOOKUP($E68,'00 MASTER WORK REGISTER'!$B:$B,'00 MASTER WORK REGISTER'!$M:$M,"") -> 46345 | L68: 45838 | M68: 1 | N68: =IF($M68=1, "Completed", IF($L68<TODAY(), "Late", "On Schedule")) -> Completed | O68: 45930 | P68: 1 | Q68: =IF($P68=1, "Completed", IF($O68<TODAY(), "Late", "On Schedule")) -> Completed | U68: 46048 | V68: 1 | W68: =IF($V68=1, "Completed", IF($U68<TODAY(), "Late", "On Schedule")) -> Completed | AA68: 46218 | AB68: 1 | AC68: =IF($AB68=1, "Completed", IF($AA68<TODAY(), "Late", "On Schedule")) -> Completed | AD68: 46295 | AE68: 1 | AF68: =IF($AE68=1, "Completed", IF($AD68<TODAY(), "Late", "On Schedule")) -> Completed | AG68: =AD68+21 -> 46316 | AH68: 0 | AI68: =IF($AH68=1, "Completed", IF($AG68<TODAY(), "Late", "On Schedule")) -> Late | AK68: =IFERROR(SUMPRODUCT(($M$1:$AH$1),(M68:AH68))/SUMIF((M68:AH68),"<>",($M$1:$AH$1)),"") -> 0.96470588 | AL68: On Schedule | AN68: =_xlfn.XLOOKUP($E68,'00 MASTER WORK REGISTER'!B:B,'00 MASTER WORK REGISTER'!N:N,"") -> 0 | AO68: จัดทำตาข่ายกันนก | AP68: =_xlfn.XLOOKUP($F68,#REF!,#REF!,"") -> #REF! | AQ68: CV/AR | AS68: MDW-39236 | AT68: =_xlfn.XLOOKUP($AS68,'02 Design'!F:F,'02 Design'!AE:AE," ") -> MDW-69239 | AU68: =_xlfn.XLOOKUP($AS68,'02 Design'!F:F,'02 Design'!AF:AF," ") -> MDW-69240
A69: 66 | B69: 66 | C69: =_xlfn.XLOOKUP($E69,'00 MASTER WORK REGISTER'!B:B,'00 MASTER WORK REGISTER'!L:L) -> - | D69: Lot01 | E69: GEN14 | F69: GEN | G69: =_xlfn.XLOOKUP($E69,'00 MASTER WORK REGISTER'!B:B,'00 MASTER WORK REGISTER'!H:H) -> Train Crew Office at Thailand Cultural Centre Station | H69: =_xlfn.XLOOKUP($E69,'00 MASTER WORK REGISTER'!B:B,'00 MASTER WORK REGISTER'!$I:$I,"") -> สหชาติ | K69: =_xlfn.XLOOKUP($E69,'00 MASTER WORK REGISTER'!$B:$B,'00 MASTER WORK REGISTER'!$M:$M,"") -> 46255 | L69: 45930 | M69: 1 | N69: =IF($M69=1, "Completed", IF($L69<TODAY(), "Late", "On Schedule")) -> Completed | O69: 46080 | P69: 1 | Q69: =IF($P69=1, "Completed", IF($O69<TODAY(), "Late", "On Schedule")) -> Completed | U69: 46173 | V69: 1 | W69: =IF($V69=1, "Completed", IF($U69<TODAY(), "Late", "On Schedule")) -> Completed | AA69: =AD69-7 -> 46288 | AB69: 0 | AC69: =IF($AB69=1, "Completed", IF($AA69<TODAY(), "Late", "On Schedule")) -> Late | AD69: 46295 | AE69: 0 | AF69: =IF($AE69=1, "Completed", IF($AD69<TODAY(), "Late", "On Schedule")) -> Late | AG69: =AD69+21 -> 46316 | AH69: 0 | AI69: =IF($AH69=1, "Completed", IF($AG69<TODAY(), "Late", "On Schedule")) -> Late | AK69: =IFERROR(SUMPRODUCT(($M$1:$AH$1),(M69:AH69))/SUMIF((M69:AH69),"<>",($M$1:$AH$1)),"") -> 0.94117647 | AL69: Late | AN69: =_xlfn.XLOOKUP($E69,'00 MASTER WORK REGISTER'!B:B,'00 MASTER WORK REGISTER'!N:N,"") -> 0 | AP69: =_xlfn.XLOOKUP($F69,#REF!,#REF!,"") -> #REF! | AT69: =_xlfn.XLOOKUP($AS69,'02 Design'!F:F,'02 Design'!AE:AE," ") -> 0 | AU69: =_xlfn.XLOOKUP($AS69,'02 Design'!F:F,'02 Design'!AF:AF," ") -> 0
A70: 67 | B70: 67 | C70: =_xlfn.XLOOKUP($E70,'00 MASTER WORK REGISTER'!B:B,'00 MASTER WORK REGISTER'!L:L) -> MDW-39240 | D70: Lot01 | E70: GEN14.1 | F70: GEN | G70: =_xlfn.XLOOKUP($E70,'00 MASTER WORK REGISTER'!B:B,'00 MASTER WORK REGISTER'!H:H) -> Driver Train Simulation Room and Train Crew Office at OR18 - Civil & AR | H70: =_xlfn.XLOOKUP($E70,'00 MASTER WORK REGISTER'!B:B,'00 MASTER WORK REGISTER'!$I:$I,"") -> สหชาติ | J70: Depot | K70: =_xlfn.XLOOKUP($E70,'00 MASTER WORK REGISTER'!$B:$B,'00 MASTER WORK REGISTER'!$M:$M,"") -> 46255 | L70: 45930 | M70: 1 | N70: =IF($M70=1, "Completed", IF($L70<TODAY(), "Late", "On Schedule")) -> Completed | O70: 46081 | P70: 1 | Q70: =IF($P70=1, "Completed", IF($O70<TODAY(), "Late", "On Schedule")) -> Completed | U70: 46142 | V70: 1 | W70: =IF($V70=1, "Completed", IF($U70<TODAY(), "Late", "On Schedule")) -> Completed | AA70: 46218 | AB70: 1 | AC70: =IF($AB70=1, "Completed", IF($AA70<TODAY(), "Late", "On Schedule")) -> Completed | AD70: 46241 | AE70: 1 | AF70: =IF($AE70=1, "Completed", IF($AD70<TODAY(), "Late", "On Schedule")) -> Completed | AG70: 46295 | AH70: 0 | AI70: =IF($AH70=1, "Completed", IF($AG70<TODAY(), "Late", "On Schedule")) -> Late | AK70: =IFERROR(SUMPRODUCT(($M$1:$AH$1),(M70:AH70))/SUMIF((M70:AH70),"<>",($M$1:$AH$1)),"") -> 0.96470588 | AL70: Late | AN70: =_xlfn.XLOOKUP($E70,'00 MASTER WORK REGISTER'!B:B,'00 MASTER WORK REGISTER'!N:N,"") -> 0 | AO70: จัดเตรียมห้องสำนักงานสำหรับพนักงานรถไฟฟ้า รวมห้องน้ำช-ญ รองรับพนักงาน 200 คน (พื้นที่อย่างน้อย 400 ตร.ม.) | AP70: =_xlfn.XLOOKUP($F70,#REF!,#REF!,"") -> #REF! | AQ70: CV/AR+E&M | AS70: MDW-39240 | AT70: =_xlfn.XLOOKUP($AS70,'02 Design'!F:F,'02 Design'!AE:AE," ") -> MDW-69247 | AU70: =_xlfn.XLOOKUP($AS70,'02 Design'!F:F,'02 Design'!AF:AF," ") -> MDW-69248
A71: 68 | B71: 68 | C71: =_xlfn.XLOOKUP($E71,'00 MASTER WORK REGISTER'!B:B,'00 MASTER WORK REGISTER'!L:L) -> MDW-39241 | D71: Lot01 | E71: GEN14.2 | F71: GEN | G71: =_xlfn.XLOOKUP($E71,'00 MASTER WORK REGISTER'!B:B,'00 MASTER WORK REGISTER'!H:H) -> Driver Train Simulation Room and Train Crew Office at OR18 - Building Services | H71: =_xlfn.XLOOKUP($E71,'00 MASTER WORK REGISTER'!B:B,'00 MASTER WORK REGISTER'!$I:$I,"") -> ประธาน | K71: =_xlfn.XLOOKUP($E71,'00 MASTER WORK REGISTER'!$B:$B,'00 MASTER WORK REGISTER'!$M:$M,"") -> 46255 | L71: 45930 | M71: 1 | N71: =IF($M71=1, "Completed", IF($L71<TODAY(), "Late", "On Schedule")) -> Completed | O71: 46081 | P71: 1 | Q71: =IF($P71=1, "Completed", IF($O71<TODAY(), "Late", "On Schedule")) -> Completed | U71: 46142 | V71: 1 | W71: =IF($V71=1, "Completed", IF($U71<TODAY(), "Late", "On Schedule")) -> Completed | AA71: 46093 | AB71: 1 | AC71: =IF($AB71=1, "Completed", IF($AA71<TODAY(), "Late", "On Schedule")) -> Completed | AD71: 46241 | AE71: 1 | AF71: =IF($AE71=1, "Completed", IF($AD71<TODAY(), "Late", "On Schedule")) -> Completed | AG71: 46295 | AH71: 0 | AI71: =IF($AH71=1, "Completed", IF($AG71<TODAY(), "Late", "On Schedule")) -> Late | AK71: =IFERROR(SUMPRODUCT(($M$1:$AH$1),(M71:AH71))/SUMIF((M71:AH71),"<>",($M$1:$AH$1)),"") -> 0.96470588 | AL71: Late | AN71: =_xlfn.XLOOKUP($E71,'00 MASTER WORK REGISTER'!B:B,'00 MASTER WORK REGISTER'!N:N,"") -> 0 | AO71: จัดเตรียมห้องสำนักงานสำหรับพนักงานรถไฟฟ้า รวมห้องน้ำช-ญ รองรับพนักงาน 200 คน (พื้นที่อย่างน้อย 400 ตร.ม.) | AP71: =_xlfn.XLOOKUP($F71,#REF!,#REF!,"") -> #REF! | AQ71: CV/AR+E&M | AS71: MDW-39241 | AT71: =_xlfn.XLOOKUP($AS71,'02 Design'!F:F,'02 Design'!AE:AE," ") -> MDW-69249 | AU71: =_xlfn.XLOOKUP($AS71,'02 Design'!F:F,'02 Design'!AF:AF," ") -> MDW-69250
A72: 69 | B72: 69 | C72: =_xlfn.XLOOKUP($E72,'00 MASTER WORK REGISTER'!B:B,'00 MASTER WORK REGISTER'!L:L) -> MDW-39239 | D72: Lot01 | E72: GEN15 | F72: GEN | G72: =_xlfn.XLOOKUP($E72,'00 MASTER WORK REGISTER'!B:B,'00 MASTER WORK REGISTER'!H:H) -> Access Panel Closeout for Traction Substation Room in Main Workshop | H72: =_xlfn.XLOOKUP($E72,'00 MASTER WORK REGISTER'!B:B,'00 MASTER WORK REGISTER'!$I:$I,"") -> สหชาติ | K72: =_xlfn.XLOOKUP($E72,'00 MASTER WORK REGISTER'!$B:$B,'00 MASTER WORK REGISTER'!$M:$M,"") -> 46105 | L72: 46052 | M72: 1 | N72: =IF($M72=1, "Completed", IF($L72<TODAY(), "Late", "On Schedule")) -> Completed | O72: 46082 | P72: 1 | Q72: =IF($P72=1, "Completed", IF($O72<TODAY(), "Late", "On Schedule")) -> Completed | U72: 46112 | V72: 1 | W72: =IF($V72=1, "Completed", IF($U72<TODAY(), "Late", "On Schedule")) -> Completed | AA72: 46218 | AB72: 1 | AC72: =IF($AB72=1, "Completed", IF($AA72<TODAY(), "Late", "On Schedule")) -> Completed | AD72: 46295 | AE72: 1 | AF72: =IF($AE72=1, "Completed", IF($AD72<TODAY(), "Late", "On Schedule")) -> Completed | AG72: =AD72+21 -> 46316 | AH72: 0 | AI72: =IF($AH72=1, "Completed", IF($AG72<TODAY(), "Late", "On Schedule")) -> Late | AK72: =IFERROR(SUMPRODUCT(($M$1:$AH$1),(M72:AH72))/SUMIF((M72:AH72),"<>",($M$1:$AH$1)),"") -> 0.96470588 | AL72: Late | AN72: =_xlfn.XLOOKUP($E72,'00 MASTER WORK REGISTER'!B:B,'00 MASTER WORK REGISTER'!N:N,"") -> 0 | AO72: ออกแบบ จัดเตรียมแผงปิดทางเข้าห้อง TSS ที่ MWS | AP72: =_xlfn.XLOOKUP($F72,#REF!,#REF!,"") -> #REF! | AQ72: CV/AR | AS72: MDW-39239 | AT72: =_xlfn.XLOOKUP($AS72,'02 Design'!F:F,'02 Design'!AE:AE," ") -> MDW-69245 | AU72: =_xlfn.XLOOKUP($AS72,'02 Design'!F:F,'02 Design'!AF:AF," ") -> MDW-69246
A73: 70 | B73: 70 | C73: =_xlfn.XLOOKUP($E73,'00 MASTER WORK REGISTER'!B:B,'00 MASTER WORK REGISTER'!L:L) -> MDW-39232 | D73: Lot01 | E73: GEN16 | F73: GEN | G73: =_xlfn.XLOOKUP($E73,'00 MASTER WORK REGISTER'!B:B,'00 MASTER WORK REGISTER'!H:H) -> Level Crossing at Turnout | H73: =_xlfn.XLOOKUP($E73,'00 MASTER WORK REGISTER'!B:B,'00 MASTER WORK REGISTER'!$I:$I,"") -> กำพล | K73: =_xlfn.XLOOKUP($E73,'00 MASTER WORK REGISTER'!$B:$B,'00 MASTER WORK REGISTER'!$M:$M,"") -> 46255 | L73: 46295 | M73: 1 | N73: =IF($M73=1, "Completed", IF($L73<TODAY(), "Late", "On Schedule")) -> Completed | O73: 46295 | P73: 1 | Q73: =IF($P73=1, "Completed", IF($O73<TODAY(), "Late", "On Schedule")) -> Completed | U73: 46341 | V73: 0.46 | W73: =IF($V73=1, "Completed", IF($U73<TODAY(), "Late", "On Schedule")) -> On Schedule | AB73: 0 | AC73: =IF($AB73=1, "Completed", IF($AA73<TODAY(), "Late", "On Schedule")) -> On Schedule | AE73: 0 | AF73: =IF($AE73=1, "Completed", IF($AD73<TODAY(), "Late", "On Schedule")) -> On Schedule | AH73: 0 | AI73: =IF($AH73=1, "Completed", IF($AG73<TODAY(), "Late", "On Schedule")) -> On Schedule | AK73: =IFERROR(SUMPRODUCT(($M$1:$AH$1),(M73:AH73))/SUMIF((M73:AH73),"<>",($M$1:$AH$1)),"") -> 0.56 | AL73: On Schedule | AO73: ติดตั้ง Level Crossing บริเวณ Turnout | AP73: =_xlfn.XLOOKUP($F73,#REF!,#REF!,"") -> #REF! | AS73: MDW-39232 | AT73: =_xlfn.XLOOKUP($AS73,'02 Design'!F:F,'02 Design'!AE:AE," ") -> MDW-69232 | AU73: =_xlfn.XLOOKUP($AS73,'02 Design'!F:F,'02 Design'!AF:AF," ") -> MDW-69233
A74: 71 | B74: 71 | C74: =_xlfn.XLOOKUP($E74,'00 MASTER WORK REGISTER'!B:B,'00 MASTER WORK REGISTER'!L:L) -> MDW-39232 | D74: Lot01 | E74: GEN17 | F74: GEN | G74: =_xlfn.XLOOKUP($E74,'00 MASTER WORK REGISTER'!B:B,'00 MASTER WORK REGISTER'!H:H) -> Track Slab Crossing | H74: =_xlfn.XLOOKUP($E74,'00 MASTER WORK REGISTER'!B:B,'00 MASTER WORK REGISTER'!$I:$I,"") -> ชฎิล/กำพล | K74: =_xlfn.XLOOKUP($E74,'00 MASTER WORK REGISTER'!$B:$B,'00 MASTER WORK REGISTER'!$M:$M,"") -> 46255 | AK74: =IFERROR(SUMPRODUCT(($M$1:$AH$1),(M74:AH74))/SUMIF((M74:AH74),"<>",($M$1:$AH$1)),"") | AN74: =_xlfn.XLOOKUP($E74,'00 MASTER WORK REGISTER'!B:B,'00 MASTER WORK REGISTER'!N:N,"") -> CANCLE | AO74: ปิดช่องว่างระหว่าง Track Slab | AP74: =_xlfn.XLOOKUP($F74,#REF!,#REF!,"") -> #REF! | AS74: MDW-39232 | AT74: =_xlfn.XLOOKUP($AS74,'02 Design'!F:F,'02 Design'!AE:AE," ") -> MDW-69232 | AU74: =_xlfn.XLOOKUP($AS74,'02 Design'!F:F,'02 Design'!AF:AF," ") -> MDW-69233
A75: 72 | B75: 72 | C75: =_xlfn.XLOOKUP($E75,'00 MASTER WORK REGISTER'!B:B,'00 MASTER WORK REGISTER'!L:L) -> MDW-39243 | D75: Lot01 | E75: GEN18 | F75: GEN | G75: =_xlfn.XLOOKUP($E75,'00 MASTER WORK REGISTER'!B:B,'00 MASTER WORK REGISTER'!H:H) -> Eye Adaptation Lighting (Lighting at Tunnel to Expose) | H75: =_xlfn.XLOOKUP($E75,'00 MASTER WORK REGISTER'!B:B,'00 MASTER WORK REGISTER'!$I:$I,"") -> ประธาน | K75: =_xlfn.XLOOKUP($E75,'00 MASTER WORK REGISTER'!$B:$B,'00 MASTER WORK REGISTER'!$M:$M,"") -> 46345 | L75: 45930 | M75: 1 | N75: =IF($M75=1, "Completed", IF($L75<TODAY(), "Late", "On Schedule")) -> Completed | O75: 45960 | P75: 1 | Q75: =IF($P75=1, "Completed", IF($O75<TODAY(), "Late", "On Schedule")) -> Completed | U75: 46125 | V75: 1 | W75: =IF($V75=1, "Completed", IF($U75<TODAY(), "Late", "On Schedule")) -> Completed | AA75: 46071 | AB75: 1 | AC75: =IF($AB75=1, "Completed", IF($AA75<TODAY(), "Late", "On Schedule")) -> Completed | AD75: =AD65 -> 46302 | AE75: 0 | AF75: =IF($AE75=1, "Completed", IF($AD75<TODAY(), "Late", "On Schedule")) -> Late | AG75: 46325 | AH75: 0 | AI75: =IF($AH75=1, "Completed", IF($AG75<TODAY(), "Late", "On Schedule")) -> On Schedule | AK75: =IFERROR(SUMPRODUCT(($M$1:$AH$1),(M75:AH75))/SUMIF((M75:AH75),"<>",($M$1:$AH$1)),"") -> 0.95294118 | AL75: On Schedule | AM75: Progress DPA1 : 100% Progress DPA2 : 100% Progress Cut&Cover OR22 : 95% | AN75: =_xlfn.XLOOKUP($E75,'00 MASTER WORK REGISTER'!B:B,'00 MASTER WORK REGISTER'!N:N,"") -> 0 | AO75: จัดเตรียมไฟส่องสว่างบริเวณ Approach Ramp จากอุโมงค์ไปทางวิ่งยกระดับ / จากอุโมงค์เข้า Depot (2จุด) | AP75: =_xlfn.XLOOKUP($F75,#REF!,#REF!,"") -> #REF! | AS75: MDW-39243 | AT75: =_xlfn.XLOOKUP($AS75,'02 Design'!F:F,'02 Design'!AE:AE," ") -> MDW-69253 | AU75: =_xlfn.XLOOKUP($AS75,'02 Design'!F:F,'02 Design'!AF:AF," ") -> MDW-69254
A76: 73 | B76: 73 | C76: =_xlfn.XLOOKUP($E76,'00 MASTER WORK REGISTER'!B:B,'00 MASTER WORK REGISTER'!L:L) -> - | D76: Lot01 | E76: GEN19 | F76: GEN | G76: =_xlfn.XLOOKUP($E76,'00 MASTER WORK REGISTER'!B:B,'00 MASTER WORK REGISTER'!H:H) -> Train Simulation Room and AFC Training Room | H76: - | K76: =_xlfn.XLOOKUP($E76,'00 MASTER WORK REGISTER'!$B:$B,'00 MASTER WORK REGISTER'!$M:$M,"") -> 46255 | AK76: =IFERROR(SUMPRODUCT(($M$1:$AH$1),(M76:AH76))/SUMIF((M76:AH76),"<>",($M$1:$AH$1)),"") | AM76: Progress DPA2 : 100% | AN76: =_xlfn.XLOOKUP($E76,'00 MASTER WORK REGISTER'!B:B,'00 MASTER WORK REGISTER'!N:N,"") -> 0 | AP76: =_xlfn.XLOOKUP($F76,#REF!,#REF!,"") -> #REF! | AT76: =_xlfn.XLOOKUP($AS76,'02 Design'!F:F,'02 Design'!AE:AE," ") -> 0 | AU76: =_xlfn.XLOOKUP($AS76,'02 Design'!F:F,'02 Design'!AF:AF," ") -> 0
A77: 74 | B77: 74 | C77: =_xlfn.XLOOKUP($E77,'00 MASTER WORK REGISTER'!B:B,'00 MASTER WORK REGISTER'!L:L) -> MDW-39244 | D77: Lot01 | E77: GEN19.1 | F77: GEN | G77: =_xlfn.XLOOKUP($E77,'00 MASTER WORK REGISTER'!B:B,'00 MASTER WORK REGISTER'!H:H) -> Modification AFC Training Center at OR19 - Civil & AR | H77: =_xlfn.XLOOKUP($E77,'00 MASTER WORK REGISTER'!B:B,'00 MASTER WORK REGISTER'!$I:$I,"") -> สหชาติ | K77: =_xlfn.XLOOKUP($E77,'00 MASTER WORK REGISTER'!$B:$B,'00 MASTER WORK REGISTER'!$M:$M,"") -> 46356 | L77: 46295 | M77: 1 | N77: =IF($M77=1, "Completed", IF($L77<TODAY(), "Late", "On Schedule")) -> Completed | O77: 46326 | P77: 0.58 | Q77: =IF($P77=1, "Completed", IF($O77<TODAY(), "Late", "On Schedule")) -> On Schedule | U77: 46356 | V77: 0 | W77: =IF($V77=1, "Completed", IF($U77<TODAY(), "Late", "On Schedule")) -> On Schedule | AA77: =U77-30 -> 46326 | AB77: 0 | AC77: =IF($AB77=1, "Completed", IF($AA77<TODAY(), "Late", "On Schedule")) -> On Schedule | AD77: =U77+7 -> 46363 | AE77: 0 | AF77: =IF($AE77=1, "Completed", IF($AD77<TODAY(), "Late", "On Schedule")) -> On Schedule | AG77: =AD77+21 -> 46384 | AH77: 0 | AI77: =IF($AH77=1, "Completed", IF($AG77<TODAY(), "Late", "On Schedule")) -> On Schedule | AK77: =IFERROR(SUMPRODUCT(($M$1:$AH$1),(M77:AH77))/SUMIF((M77:AH77),"<>",($M$1:$AH$1)),"") -> 0.18588235 | AL77: On Schedule | AM77: Progress Cut&Cover OR22 : 95% | AN77: =_xlfn.XLOOKUP($E77,'00 MASTER WORK REGISTER'!B:B,'00 MASTER WORK REGISTER'!N:N,"") -> 0 | AP77: =_xlfn.XLOOKUP($F77,#REF!,#REF!,"") -> #REF! | AQ77: CV/AR+E&M | AS77: MDW-39244 | AT77: =_xlfn.XLOOKUP($AS77,'02 Design'!F:F,'02 Design'!AE:AE," ") -> MDW-69255 | AU77: =_xlfn.XLOOKUP($AS77,'02 Design'!F:F,'02 Design'!AF:AF," ") -> MDW-69256
A78: 75 | B78: 75 | C78: =_xlfn.XLOOKUP($E78,'00 MASTER WORK REGISTER'!B:B,'00 MASTER WORK REGISTER'!L:L) -> MDW-39245 | D78: Lot01 | E78: GEN19.2 | F78: GEN | G78: =_xlfn.XLOOKUP($E78,'00 MASTER WORK REGISTER'!B:B,'00 MASTER WORK REGISTER'!H:H) -> Modification AFC Training Center at OR19 - Building Services | H78: =_xlfn.XLOOKUP($E78,'00 MASTER WORK REGISTER'!B:B,'00 MASTER WORK REGISTER'!$I:$I,"") -> ประธาน | I78: บัณฑิต | K78: =_xlfn.XLOOKUP($E78,'00 MASTER WORK REGISTER'!$B:$B,'00 MASTER WORK REGISTER'!$M:$M,"") -> 46356 | L78: 46295 | M78: 1 | N78: =IF($M78=1, "Completed", IF($L78<TODAY(), "Late", "On Schedule")) -> Completed | O78: 46326 | P78: 1 | Q78: =IF($P78=1, "Completed", IF($O78<TODAY(), "Late", "On Schedule")) -> Completed | U78: 46356 | V78: 0 | W78: =IF($V78=1, "Completed", IF($U78<TODAY(), "Late", "On Schedule")) -> On Schedule | AA78: =U78-30 -> 46326 | AB78: 0 | AC78: =IF($AB78=1, "Completed", IF($AA78<TODAY(), "Late", "On Schedule")) -> On Schedule | AD78: =U78+7 -> 46363 | AE78: 0 | AF78: =IF($AE78=1, "Completed", IF($AD78<TODAY(), "Late", "On Schedule")) -> On Schedule | AG78: 46384 | AH78: 0 | AI78: =IF($AH78=1, "Completed", IF($AG78<TODAY(), "Late", "On Schedule")) -> On Schedule | AK78: =IFERROR(SUMPRODUCT(($M$1:$AH$1),(M78:AH78))/SUMIF((M78:AH78),"<>",($M$1:$AH$1)),"") -> 0.23529412 | AL78: On Schedule | AN78: =_xlfn.XLOOKUP($E78,'00 MASTER WORK REGISTER'!B:B,'00 MASTER WORK REGISTER'!N:N,"") -> 0 | AP78: =_xlfn.XLOOKUP($F78,#REF!,#REF!,"") -> #REF! | AQ78: CV/AR+E&M | AS78: MDW-39245 | AT78: =_xlfn.XLOOKUP($AS78,'02 Design'!F:F,'02 Design'!AE:AE," ") -> MDW-69257 | AU78: =_xlfn.XLOOKUP($AS78,'02 Design'!F:F,'02 Design'!AF:AF," ") -> MDW-69258
A79: 76 | B79: 76 | C79: =_xlfn.XLOOKUP($E79,'00 MASTER WORK REGISTER'!B:B,'00 MASTER WORK REGISTER'!L:L) -> - | D79: Lot01 | E79: GEN20 | F79: GEN | G79: =_xlfn.XLOOKUP($E79,'00 MASTER WORK REGISTER'!B:B,'00 MASTER WORK REGISTER'!H:H) -> Dormitory Cable Containments (if any) | H79: =_xlfn.XLOOKUP($E79,'00 MASTER WORK REGISTER'!B:B,'00 MASTER WORK REGISTER'!$I:$I,"") -> - | K79: =_xlfn.XLOOKUP($E79,'00 MASTER WORK REGISTER'!$B:$B,'00 MASTER WORK REGISTER'!$M:$M,"") -> - | AK79: =IFERROR(SUMPRODUCT(($M$1:$AH$1),(M79:AH79))/SUMIF((M79:AH79),"<>",($M$1:$AH$1)),"") | AN79: =_xlfn.XLOOKUP($E79,'00 MASTER WORK REGISTER'!B:B,'00 MASTER WORK REGISTER'!N:N,"") -> CANCLE | AP79: =_xlfn.XLOOKUP($F79,#REF!,#REF!,"") -> #REF! | AT79: =_xlfn.XLOOKUP($AS79,'02 Design'!F:F,'02 Design'!AE:AE," ") -> 0 | AU79: =_xlfn.XLOOKUP($AS79,'02 Design'!F:F,'02 Design'!AF:AF," ") -> 0
A80: 77 | B80: 77 | C80: =_xlfn.XLOOKUP($E80,'00 MASTER WORK REGISTER'!B:B,'00 MASTER WORK REGISTER'!L:L) | D80: Lot01 | E80: GEN21 | F80: GEN | G80: =_xlfn.XLOOKUP($E80,'00 MASTER WORK REGISTER'!B:B,'00 MASTER WORK REGISTER'!H:H) -> Project Information Management System (PIMS) | H80: =_xlfn.XLOOKUP($E80,'00 MASTER WORK REGISTER'!B:B,'00 MASTER WORK REGISTER'!$I:$I,"") -> บัณฑิต | K80: =_xlfn.XLOOKUP($E80,'00 MASTER WORK REGISTER'!$B:$B,'00 MASTER WORK REGISTER'!$M:$M,"") -> 45565 | L80: 45514 | M80: 1 | N80: =IF($M80=1, "Completed", IF($L80<TODAY(), "Late", "On Schedule")) -> Completed | O80: 45519 | P80: 1 | Q80: =IF($P80=1, "Completed", IF($O80<TODAY(), "Late", "On Schedule")) -> Completed | U80: 45539 | V80: 1 | W80: =IF($V80=1, "Completed", IF($U80<TODAY(), "Late", "On Schedule")) -> Completed | X80: 45549 | Y80: 1 | Z80: =IF($Y80=1, "Completed", IF($X80<TODAY(), "Late", "On Schedule")) -> Completed | AA80: =AD80-7 -> 46288 | AB80: 0 | AC80: =IF($AB80=1, "Completed", IF($AA80<TODAY(), "Late", "On Schedule")) -> Late | AD80: 46295 | AE80: 0 | AF80: =IF($AE80=1, "Completed", IF($AD80<TODAY(), "Late", "On Schedule")) -> Late | AG80: =AD80+21 -> 46316 | AH80: 0 | AI80: =IF($AH80=1, "Completed", IF($AG80<TODAY(), "Late", "On Schedule")) -> Late | AK80: =IFERROR(SUMPRODUCT(($M$1:$AH$1),(M80:AH80))/SUMIF((M80:AH80),"<>",($M$1:$AH$1)),"") -> 0.94444444 | AL80: Late | AM80: งานจบแล้ว | AN80: =_xlfn.XLOOKUP($E80,'00 MASTER WORK REGISTER'!B:B,'00 MASTER WORK REGISTER'!N:N,"") -> 0 | AP80: =_xlfn.XLOOKUP($F80,#REF!,#REF!,"") -> #REF! | AT80: =_xlfn.XLOOKUP($AS80,'02 Design'!F:F,'02 Design'!AE:AE," ") | AU80: =_xlfn.XLOOKUP($AS80,'02 Design'!F:F,'02 Design'!AF:AF," ")
A81: 78 | B81: 78 | C81: =_xlfn.XLOOKUP($E81,'00 MASTER WORK REGISTER'!B:B,'00 MASTER WORK REGISTER'!L:L) -> MDW-39237 | D81: Lot01 | E81: GEN22 | F81: GEN | G81: =_xlfn.XLOOKUP($E81,'00 MASTER WORK REGISTER'!B:B,'00 MASTER WORK REGISTER'!H:H) -> Central BEMS for the MRT Orange Line System | H81: =_xlfn.XLOOKUP($E81,'00 MASTER WORK REGISTER'!B:B,'00 MASTER WORK REGISTER'!$I:$I,"") -> บัณฑิต | K81: =_xlfn.XLOOKUP($E81,'00 MASTER WORK REGISTER'!$B:$B,'00 MASTER WORK REGISTER'!$M:$M,"") -> 46255 | L81: 46142 | M81: 0 | N81: =IF($M81=1, "Completed", IF($L81<TODAY(), "Late", "On Schedule")) -> Late | O81: 46203 | P81: 0 | Q81: =IF($P81=1, "Completed", IF($O81<TODAY(), "Late", "On Schedule")) -> Late | U81: 46249 | V81: 0 | W81: =IF($V81=1, "Completed", IF($U81<TODAY(), "Late", "On Schedule")) -> Late | X81: 46265 | Y81: 0 | Z81: =IF($Y81=1, "Completed", IF($X81<TODAY(), "Late", "On Schedule")) -> Late | AA81: 46356 | AB81: 0 | AC81: =IF($AB81=1, "Completed", IF($AA81<TODAY(), "Late", "On Schedule")) -> On Schedule | AD81: 46394 | AE81: 0 | AF81: =IF($AE81=1, "Completed", IF($AD81<TODAY(), "Late", "On Schedule")) -> On Schedule | AG81: 46415 | AH81: 0 | AI81: =IF($AH81=1, "Completed", IF($AG81<TODAY(), "Late", "On Schedule")) -> On Schedule | AK81: =IFERROR(SUMPRODUCT(($M$1:$AH$1),(M81:AH81))/SUMIF((M81:AH81),"<>",($M$1:$AH$1)),"") -> 0 | AL81: Late | AM81: PPR Oct-26 กำลังเปรียบเทียบ Spec | AN81: =_xlfn.XLOOKUP($E81,'00 MASTER WORK REGISTER'!B:B,'00 MASTER WORK REGISTER'!N:N,"") -> 0 | AO81: เตรียม Workstation Server (Software by BEM) | AP81: =_xlfn.XLOOKUP($F81,#REF!,#REF!,"") -> #REF! | AS81: MDW-39237 | AT81: =_xlfn.XLOOKUP($AS81,'02 Design'!F:F,'02 Design'!AE:AE," ") -> MDW-69241 | AU81: =_xlfn.XLOOKUP($AS81,'02 Design'!F:F,'02 Design'!AF:AF," ") -> MDW-69242
A82: 79 | B82: 79 | C82: =_xlfn.XLOOKUP($E82,'00 MASTER WORK REGISTER'!B:B,'00 MASTER WORK REGISTER'!L:L) | D82: Lot01 | E82: GEN23 | F82: GEN | G82: =_xlfn.XLOOKUP($E82,'00 MASTER WORK REGISTER'!B:B,'00 MASTER WORK REGISTER'!H:H) -> Asset Information | H82: =_xlfn.XLOOKUP($E82,'00 MASTER WORK REGISTER'!B:B,'00 MASTER WORK REGISTER'!$I:$I,"") -> บัณฑิต | K82: =_xlfn.XLOOKUP($E82,'00 MASTER WORK REGISTER'!$B:$B,'00 MASTER WORK REGISTER'!$M:$M,"") -> 46345 | O82: 46264 | P82: 1 | Q82: =IF($P82=1, "Completed", IF($O82<TODAY(), "Late", "On Schedule")) -> Completed | AK82: =IFERROR(SUMPRODUCT(($M$1:$AH$1),(M82:AH82))/SUMIF((M82:AH82),"<>",($M$1:$AH$1)),"") -> 1 | AL82: Completed | AN82: =_xlfn.XLOOKUP($E82,'00 MASTER WORK REGISTER'!B:B,'00 MASTER WORK REGISTER'!N:N,"") -> 0 | AO82: งานซื้ออุปกรณ์ให้ BEM (โต๊ะ คอม ฯลฯ) รอตรวจสอบข้อมูลและรายการ | AP82: =_xlfn.XLOOKUP($F82,#REF!,#REF!,"") -> #REF! | AT82: =_xlfn.XLOOKUP($AS82,'02 Design'!F:F,'02 Design'!AE:AE," ") | AU82: =_xlfn.XLOOKUP($AS82,'02 Design'!F:F,'02 Design'!AF:AF," ")
A83: 80 | B83: 80 | C83: =_xlfn.XLOOKUP($E83,'00 MASTER WORK REGISTER'!B:B,'00 MASTER WORK REGISTER'!L:L) -> MDW-39282 | D83: Lot01 | E83: PSD1 | F83: PSD | G83: =_xlfn.XLOOKUP($E83,'00 MASTER WORK REGISTER'!B:B,'00 MASTER WORK REGISTER'!H:H) -> Holes for PSD Cable Wiring | H83: =_xlfn.XLOOKUP($E83,'00 MASTER WORK REGISTER'!B:B,'00 MASTER WORK REGISTER'!$I:$I,"") -> กำพล | K83: =_xlfn.XLOOKUP($E83,'00 MASTER WORK REGISTER'!$B:$B,'00 MASTER WORK REGISTER'!$M:$M,"") -> 46255 | AK83: =IFERROR(SUMPRODUCT(($M$1:$AH$1),(M83:AH83))/SUMIF((M83:AH83),"<>",($M$1:$AH$1)),"") | AN83: =_xlfn.XLOOKUP($E83,'00 MASTER WORK REGISTER'!B:B,'00 MASTER WORK REGISTER'!N:N,"") -> CANCLE | AO83: เจาะรูเพื่อการเดินสายของระบบ PSD | AP83: =_xlfn.XLOOKUP($F83,#REF!,#REF!,"") -> #REF! | AS83: MDW-39282 | AT83: =_xlfn.XLOOKUP($AS83,'02 Design'!F:F,'02 Design'!AE:AE," ") -> MDW-69315 | AU83: =_xlfn.XLOOKUP($AS83,'02 Design'!F:F,'02 Design'!AF:AF," ") -> MDW-69316
A84: 81 | B84: 81 | C84: =_xlfn.XLOOKUP($E84,'00 MASTER WORK REGISTER'!B:B,'00 MASTER WORK REGISTER'!L:L) -> MDW-39004 | D84: Lot01 | E84: PSD2 | F84: PSD | G84: =_xlfn.XLOOKUP($E84,'00 MASTER WORK REGISTER'!B:B,'00 MASTER WORK REGISTER'!H:H) -> Rubber Gap Fillers on Platform Edge | H84: =_xlfn.XLOOKUP($E84,'00 MASTER WORK REGISTER'!B:B,'00 MASTER WORK REGISTER'!$I:$I,"") -> กำพล | K84: =_xlfn.XLOOKUP($E84,'00 MASTER WORK REGISTER'!$B:$B,'00 MASTER WORK REGISTER'!$M:$M,"") -> 46255 | L84: 45868 | M84: 1 | N84: =IF($M84=1, "Completed", IF($L84<TODAY(), "Late", "On Schedule")) -> Completed | O84: 46053 | P84: 1 | Q84: =IF($P84=1, "Completed", IF($O84<TODAY(), "Late", "On Schedule")) -> Completed | U84: 46265 | V84: 0.4 | W84: =IF($V84=1, "Completed", IF($U84<TODAY(), "Late", "On Schedule")) -> Late | AA84: 46295 | AB84: 0.25 | AC84: =IF($AB84=1, "Completed", IF($AA84<TODAY(), "Late", "On Schedule")) -> Late | AD84: =AA84+7 -> 46302 | AE84: 0 | AF84: =IF($AE84=1, "Completed", IF($AD84<TODAY(), "Late", "On Schedule")) -> Late | AG84: 46325 | AH84: 0.5 | AI84: =IF($AH84=1, "Completed", IF($AG84<TODAY(), "Late", "On Schedule")) -> On Schedule | AK84: =IFERROR(SUMPRODUCT(($M$1:$AH$1),(M84:AH84))/SUMIF((M84:AH84),"<>",($M$1:$AH$1)),"") -> 0.53823529 | AL84: Late | AM84: แผนเข้าติดตั้ง 1/10/26-30/11/26 | AN84: =_xlfn.XLOOKUP($E84,'00 MASTER WORK REGISTER'!B:B,'00 MASTER WORK REGISTER'!N:N,"") -> 0 | AO84: ออกแบบ, จัดหา และติดตั้งวัสดุยางปิดช่องว่างระหว่างขอบชานชาลาและประตูรถไฟฟ้า | AP84: =_xlfn.XLOOKUP($F84,#REF!,#REF!,"") -> #REF! | AS84: MDW-39004 | AT84: =_xlfn.XLOOKUP($AS84,'02 Design'!F:F,'02 Design'!AE:AE," ") -> MDW-69007 | AU84: =_xlfn.XLOOKUP($AS84,'02 Design'!F:F,'02 Design'!AF:AF," ") -> MDW-69008
A85: 82 | B85: 82 | C85: =_xlfn.XLOOKUP($E85,'00 MASTER WORK REGISTER'!B:B,'00 MASTER WORK REGISTER'!L:L) -> MDW-39280 | D85: Lot01 | E85: PSD3 | F85: PSD | G85: =_xlfn.XLOOKUP($E85,'00 MASTER WORK REGISTER'!B:B,'00 MASTER WORK REGISTER'!H:H) -> Platform Finishing | H85: =_xlfn.XLOOKUP($E85,'00 MASTER WORK REGISTER'!B:B,'00 MASTER WORK REGISTER'!$I:$I,"") -> กำพล | K85: =_xlfn.XLOOKUP($E85,'00 MASTER WORK REGISTER'!$B:$B,'00 MASTER WORK REGISTER'!$M:$M,"") -> 46255 | L85: 45868 | M85: 1 | N85: =IF($M85=1, "Completed", IF($L85<TODAY(), "Late", "On Schedule")) -> Completed | O85: 45916 | P85: 1 | Q85: =IF($P85=1, "Completed", IF($O85<TODAY(), "Late", "On Schedule")) -> Completed | U85: 46029 | V85: 1 | W85: =IF($V85=1, "Completed", IF($U85<TODAY(), "Late", "On Schedule")) -> Completed | AA85: 46251 | AB85: 1 | AC85: =IF($AB85=1, "Completed", IF($AA85<TODAY(), "Late", "On Schedule")) -> Completed | AD85: 46295 | AE85: 0 | AF85: =IF($AE85=1, "Completed", IF($AD85<TODAY(), "Late", "On Schedule")) -> Late | AG85: =AD85+21 -> 46316 | AH85: 0 | AI85: =IF($AH85=1, "Completed", IF($AG85<TODAY(), "Late", "On Schedule")) -> Late | AK85: =IFERROR(SUMPRODUCT(($M$1:$AH$1),(M85:AH85))/SUMIF((M85:AH85),"<>",($M$1:$AH$1)),"") -> 0.95294118 | AL85: Late | AN85: =_xlfn.XLOOKUP($E85,'00 MASTER WORK REGISTER'!B:B,'00 MASTER WORK REGISTER'!N:N,"") -> 0 | AO85: จัดเตรียมและปรับปรุงงานพื้น finishing ชั้น Platform | AP85: =_xlfn.XLOOKUP($F85,#REF!,#REF!,"") -> #REF! | AS85: MDW-39280 | AT85: =_xlfn.XLOOKUP($AS85,'02 Design'!F:F,'02 Design'!AE:AE," ") -> MDW-69311 | AU85: =_xlfn.XLOOKUP($AS85,'02 Design'!F:F,'02 Design'!AF:AF," ") -> MDW-69312
A86: 83 | B86: 83 | C86: =_xlfn.XLOOKUP($E86,'00 MASTER WORK REGISTER'!B:B,'00 MASTER WORK REGISTER'!L:L) -> MDW-39281 | D86: Lot01 | E86: PSD4 | F86: PSD | G86: =_xlfn.XLOOKUP($E86,'00 MASTER WORK REGISTER'!B:B,'00 MASTER WORK REGISTER'!H:H) -> Cladding Barrier between EWD and Station Structure | H86: =_xlfn.XLOOKUP($E86,'00 MASTER WORK REGISTER'!B:B,'00 MASTER WORK REGISTER'!$I:$I,"") -> กำพล | K86: =_xlfn.XLOOKUP($E86,'00 MASTER WORK REGISTER'!$B:$B,'00 MASTER WORK REGISTER'!$M:$M,"") -> 46255 | L86: 46081 | M86: 1 | N86: =IF($M86=1, "Completed", IF($L86<TODAY(), "Late", "On Schedule")) -> Completed | O86: 46096 | P86: 1 | Q86: =IF($P86=1, "Completed", IF($O86<TODAY(), "Late", "On Schedule")) -> Completed | U86: 46249 | V86: 1 | W86: =IF($V86=1, "Completed", IF($U86<TODAY(), "Late", "On Schedule")) -> Completed | AA86: =AD86-7 -> 46288 | AB86: 0 | AC86: =IF($AB86=1, "Completed", IF($AA86<TODAY(), "Late", "On Schedule")) -> Late | AD86: 46295 | AE86: 0 | AF86: =IF($AE86=1, "Completed", IF($AD86<TODAY(), "Late", "On Schedule")) -> Late | AG86: =AD86+21 -> 46316 | AH86: 0 | AI86: =IF($AH86=1, "Completed", IF($AG86<TODAY(), "Late", "On Schedule")) -> Late | AK86: =IFERROR(SUMPRODUCT(($M$1:$AH$1),(M86:AH86))/SUMIF((M86:AH86),"<>",($M$1:$AH$1)),"") -> 0.94117647 | AL86: Late | AN86: =_xlfn.XLOOKUP($E86,'00 MASTER WORK REGISTER'!B:B,'00 MASTER WORK REGISTER'!N:N,"") -> 0 | AO86: ทำแผงกั้นเสริมระหว่าง EWD และโครงสร้างสถานี | AP86: =_xlfn.XLOOKUP($F86,#REF!,#REF!,"") -> #REF! | AS86: MDW-39281 | AT86: =_xlfn.XLOOKUP($AS86,'02 Design'!F:F,'02 Design'!AE:AE," ") -> MDW-69313 | AU86: =_xlfn.XLOOKUP($AS86,'02 Design'!F:F,'02 Design'!AF:AF," ") -> MDW-69314
A87: 84 | B87: 84 | C87: =_xlfn.XLOOKUP($E87,'00 MASTER WORK REGISTER'!B:B,'00 MASTER WORK REGISTER'!L:L) -> - | D87: Lot01 | E87: AFC1 | F87: AFC | G87: =_xlfn.XLOOKUP($E87,'00 MASTER WORK REGISTER'!B:B,'00 MASTER WORK REGISTER'!H:H) -> Park and Ride System | H87: =_xlfn.XLOOKUP($E87,'00 MASTER WORK REGISTER'!B:B,'00 MASTER WORK REGISTER'!$I:$I,"") -> บัณฑิต/สหชาติ | K87: =_xlfn.XLOOKUP($E87,'00 MASTER WORK REGISTER'!$B:$B,'00 MASTER WORK REGISTER'!$M:$M,"") -> 46315 | AK87: =IFERROR(SUMPRODUCT(($M$1:$AH$1),(M87:AH87))/SUMIF((M87:AH87),"<>",($M$1:$AH$1)),"") | AN87: =_xlfn.XLOOKUP($E87,'00 MASTER WORK REGISTER'!B:B,'00 MASTER WORK REGISTER'!N:N,"") -> CANCLE | AO87: ปรับปรุง Park and Ride ที่ OR14 | AP87: =_xlfn.XLOOKUP($F87,#REF!,#REF!,"") -> #REF! | AT87: =_xlfn.XLOOKUP($AS87,'02 Design'!F:F,'02 Design'!AE:AE," ") -> 0 | AU87: =_xlfn.XLOOKUP($AS87,'02 Design'!F:F,'02 Design'!AF:AF," ") -> 0
A88: 85 | B88: 85 | C88: =_xlfn.XLOOKUP($E88,'00 MASTER WORK REGISTER'!B:B,'00 MASTER WORK REGISTER'!L:L) -> MDW-39276 | D88: Lot01 | E88: AFC2 | F88: AFC | G88: =_xlfn.XLOOKUP($E88,'00 MASTER WORK REGISTER'!B:B,'00 MASTER WORK REGISTER'!H:H) -> Ticket Issuing Machine (TIM) Wall Opening and Closing | H88: =_xlfn.XLOOKUP($E88,'00 MASTER WORK REGISTER'!B:B,'00 MASTER WORK REGISTER'!$I:$I,"") -> สหชาติ | K88: =_xlfn.XLOOKUP($E88,'00 MASTER WORK REGISTER'!$B:$B,'00 MASTER WORK REGISTER'!$M:$M,"") -> 46285 | L88: 46052 | M88: 1 | N88: =IF($M88=1, "Completed", IF($L88<TODAY(), "Late", "On Schedule")) -> Completed | O88: 46096 | P88: 0.5 | Q88: =IF($P88=1, "Completed", IF($O88<TODAY(), "Late", "On Schedule")) -> Late | U88: 46216 | V88: 1 | W88: =IF($V88=1, "Completed", IF($U88<TODAY(), "Late", "On Schedule")) -> Completed | AA88: 46295 | AB88: 0.5 | AC88: =IF($AB88=1, "Completed", IF($AA88<TODAY(), "Late", "On Schedule")) -> Late | AD88: =AA88+7 -> 46302 | AE88: 0 | AF88: =IF($AE88=1, "Completed", IF($AD88<TODAY(), "Late", "On Schedule")) -> Late | AG88: 46325 | AH88: 0 | AI88: =IF($AH88=1, "Completed", IF($AG88<TODAY(), "Late", "On Schedule")) -> On Schedule | AK88: =IFERROR(SUMPRODUCT(($M$1:$AH$1),(M88:AH88))/SUMIF((M88:AH88),"<>",($M$1:$AH$1)),"") -> 0.88823529 | AL88: On Schedule | AM88: มีแก้ไขตำแหน่ง OR14,17,18,23 | AN88: =_xlfn.XLOOKUP($E88,'00 MASTER WORK REGISTER'!B:B,'00 MASTER WORK REGISTER'!N:N,"") -> 0 | AO88: เปิด/ปิดช่องว่างระหว่างกำแพงสำหรับเครื่อง TIM | AP88: =_xlfn.XLOOKUP($F88,#REF!,#REF!,"") -> #REF! | AQ88: CV/AR | AS88: MDW-39276 | AT88: =_xlfn.XLOOKUP($AS88,'02 Design'!F:F,'02 Design'!AE:AE," ") -> MDW-69303 | AU88: =_xlfn.XLOOKUP($AS88,'02 Design'!F:F,'02 Design'!AF:AF," ") -> MDW-69304
A89: 86 | B89: 86 | C89: =_xlfn.XLOOKUP($E89,'00 MASTER WORK REGISTER'!B:B,'00 MASTER WORK REGISTER'!L:L) -> MDW-39279 | D89: Lot01 | E89: AFC3 | F89: AFC | G89: =_xlfn.XLOOKUP($E89,'00 MASTER WORK REGISTER'!B:B,'00 MASTER WORK REGISTER'!H:H) -> Balustrade Modification Along AFC Gate Line | H89: =_xlfn.XLOOKUP($E89,'00 MASTER WORK REGISTER'!B:B,'00 MASTER WORK REGISTER'!$I:$I,"") -> สหชาติ | K89: =_xlfn.XLOOKUP($E89,'00 MASTER WORK REGISTER'!$B:$B,'00 MASTER WORK REGISTER'!$M:$M,"") -> 46285 | L89: 46203 | M89: 0.1 | N89: =IF($M89=1, "Completed", IF($L89<TODAY(), "Late", "On Schedule")) -> Late | O89: 46249 | P89: 0.5 | Q89: =IF($P89=1, "Completed", IF($O89<TODAY(), "Late", "On Schedule")) -> Late | U89: 46332 | V89: 0 | W89: =IF($V89=1, "Completed", IF($U89<TODAY(), "Late", "On Schedule")) -> On Schedule | AA89: 46302 | AB89: 0 | AC89: =IF($AB89=1, "Completed", IF($AA89<TODAY(), "Late", "On Schedule")) -> Late | AD89: =U89+7 -> 46339 | AE89: 0 | AF89: =IF($AE89=1, "Completed", IF($AD89<TODAY(), "Late", "On Schedule")) -> On Schedule | AG89: 46356 | AH89: 0 | AI89: =IF($AH89=1, "Completed", IF($AG89<TODAY(), "Late", "On Schedule")) -> On Schedule | AK89: =IFERROR(SUMPRODUCT(($M$1:$AH$1),(M89:AH89))/SUMIF((M89:AH89),"<>",($M$1:$AH$1)),"") -> 0.070588235 | AL89: On Schedule | AM89: จัดเตรียมแบบ ออกPPR Oct-26 | AN89: =_xlfn.XLOOKUP($E89,'00 MASTER WORK REGISTER'!B:B,'00 MASTER WORK REGISTER'!N:N,"") -> 0 | AO89: ปรับตำแหน่ง Gate Line ที่สถานี | AP89: =_xlfn.XLOOKUP($F89,#REF!,#REF!,"") -> #REF! | AQ89: CV/AR | AS89: MDW-39279 | AT89: =_xlfn.XLOOKUP($AS89,'02 Design'!F:F,'02 Design'!AE:AE," ") -> MDW-69309 | AU89: =_xlfn.XLOOKUP($AS89,'02 Design'!F:F,'02 Design'!AF:AF," ") -> MDW-69310
A90: 87 | B90: 87 | C90: =_xlfn.XLOOKUP($E90,'00 MASTER WORK REGISTER'!B:B,'00 MASTER WORK REGISTER'!L:L) -> MDW-39278 | D90: Lot01 | E90: AFC4 | F90: AFC | G90: =_xlfn.XLOOKUP($E90,'00 MASTER WORK REGISTER'!B:B,'00 MASTER WORK REGISTER'!H:H) -> Underfloor Embedded Duct Modification for AFC Gates Line | H90: =_xlfn.XLOOKUP($E90,'00 MASTER WORK REGISTER'!B:B,'00 MASTER WORK REGISTER'!$I:$I,"") -> สหชาติ | J90: Depot | K90: =_xlfn.XLOOKUP($E90,'00 MASTER WORK REGISTER'!$B:$B,'00 MASTER WORK REGISTER'!$M:$M,"") -> 46285 | L90: 46052 | M90: 1 | N90: =IF($M90=1, "Completed", IF($L90<TODAY(), "Late", "On Schedule")) -> Completed | O90: 46114 | P90: 0.67 | Q90: =IF($P90=1, "Completed", IF($O90<TODAY(), "Late", "On Schedule")) -> Late | U90: 46304 | V90: 0.81 | W90: =IF($V90=1, "Completed", IF($U90<TODAY(), "Late", "On Schedule")) -> Late | AA90: =AD90-16 -> 46295 | AB90: 0 | AC90: =IF($AB90=1, "Completed", IF($AA90<TODAY(), "Late", "On Schedule")) -> Late | AD90: =U90+7 -> 46311 | AE90: 0 | AF90: =IF($AE90=1, "Completed", IF($AD90<TODAY(), "Late", "On Schedule")) -> Late | AG90: 46319 | AH90: 0 | AI90: =IF($AH90=1, "Completed", IF($AG90<TODAY(), "Late", "On Schedule")) -> Late | AK90: =IFERROR(SUMPRODUCT(($M$1:$AH$1),(M90:AH90))/SUMIF((M90:AH90),"<>",($M$1:$AH$1)),"") -> 0.76823529 | AL90: Late | AN90: =_xlfn.XLOOKUP($E90,'00 MASTER WORK REGISTER'!B:B,'00 MASTER WORK REGISTER'!N:N,"") -> 0 | AO90: แก้ไขตำแหน่งท่อสายใต้ประตู AFC ที่สถานี | AP90: =_xlfn.XLOOKUP($F90,#REF!,#REF!,"") -> #REF! | AQ90: CV/AR | AS90: MDW-39278 | AT90: =_xlfn.XLOOKUP($AS90,'02 Design'!F:F,'02 Design'!AE:AE," ") -> MDW-69307 | AU90: =_xlfn.XLOOKUP($AS90,'02 Design'!F:F,'02 Design'!AF:AF," ") -> MDW-69308
A91: 88 | B91: 88 | C91: =_xlfn.XLOOKUP($E91,'00 MASTER WORK REGISTER'!B:B,'00 MASTER WORK REGISTER'!L:L) -> MDW-39002 | D91: Lot01 | E91: SIG1 | F91: SIG | G91: =_xlfn.XLOOKUP($E91,'00 MASTER WORK REGISTER'!B:B,'00 MASTER WORK REGISTER'!H:H) -> Test Track Shelters and Test Track Building | H91: =_xlfn.XLOOKUP($E91,'00 MASTER WORK REGISTER'!B:B,'00 MASTER WORK REGISTER'!$I:$I,"") -> สหชาติ | K91: =_xlfn.XLOOKUP($E91,'00 MASTER WORK REGISTER'!$B:$B,'00 MASTER WORK REGISTER'!$M:$M,"") -> 46195 | L91: 45983 | M91: 1 | N91: =IF($M91=1, "Completed", IF($L91<TODAY(), "Late", "On Schedule")) -> Completed | O91: 46040 | P91: 1 | Q91: =IF($P91=1, "Completed", IF($O91<TODAY(), "Late", "On Schedule")) -> Completed | R91: 46081 | S91: 1 | T91: =IF($S91=1, "Completed", IF($R91<TODAY(), "Late", "On Schedule")) -> Completed | U91: 46127 | V91: 1 | W91: =IF($V91=1, "Completed", IF($U91<TODAY(), "Late", "On Schedule")) -> Completed | AA91: 46157 | AB91: 1 | AC91: =IF($AB91=1, "Completed", IF($AA91<TODAY(), "Late", "On Schedule")) -> Completed | AD91: 46181 | AE91: 1 | AF91: =IF($AE91=1, "Completed", IF($AD91<TODAY(), "Late", "On Schedule")) -> Completed | AG91: 46295 | AH91: 0 | AI91: =IF($AH91=1, "Completed", IF($AG91<TODAY(), "Late", "On Schedule")) -> Late | AK91: =IFERROR(SUMPRODUCT(($M$1:$AH$1),(M91:AH91))/SUMIF((M91:AH91),"<>",($M$1:$AH$1)),"") -> 0.96842105 | AL91: Late | AN91: =_xlfn.XLOOKUP($E91,'00 MASTER WORK REGISTER'!B:B,'00 MASTER WORK REGISTER'!N:N,"") -> 0 | AO91: ออกแบบ, จัดหา และก่อสร้างอาคารและที่กำบัง Test Track | AP91: =_xlfn.XLOOKUP($F91,#REF!,#REF!,"") -> #REF! | AS91: MDW-39002 | AT91: =_xlfn.XLOOKUP($AS91,'02 Design'!F:F,'02 Design'!AE:AE," ") -> MDW-69003 | AU91: =_xlfn.XLOOKUP($AS91,'02 Design'!F:F,'02 Design'!AF:AF," ") -> MDW-69004
A92: 89 | B92: 89 | C92: =_xlfn.XLOOKUP($E92,'00 MASTER WORK REGISTER'!B:B,'00 MASTER WORK REGISTER'!L:L) -> MDW-39293 | D92: Lot01 | E92: SIG2 | F92: SIG | G92: =_xlfn.XLOOKUP($E92,'00 MASTER WORK REGISTER'!B:B,'00 MASTER WORK REGISTER'!H:H) -> Rearrangement of track crossing walkway at stabling yard to consistent with the layout of 4-car train parking | H92: =_xlfn.XLOOKUP($E92,'00 MASTER WORK REGISTER'!B:B,'00 MASTER WORK REGISTER'!$I:$I,"") -> กำพล | J92: Depot | K92: =_xlfn.XLOOKUP($E92,'00 MASTER WORK REGISTER'!$B:$B,'00 MASTER WORK REGISTER'!$M:$M,"") -> 46195 | L92: 45991 | M92: 1 | N92: =IF($M92=1, "Completed", IF($L92<TODAY(), "Late", "On Schedule")) -> Completed | O92: 46021 | P92: 1 | Q92: =IF($P92=1, "Completed", IF($O92<TODAY(), "Late", "On Schedule")) -> Completed | U92: 46111 | V92: 1 | W92: =IF($V92=1, "Completed", IF($U92<TODAY(), "Late", "On Schedule")) -> Completed | AA92: 46295 | AB92: 0.5 | AC92: =IF($AB92=1, "Completed", IF($AA92<TODAY(), "Late", "On Schedule")) -> Late | AD92: =AA92+7 -> 46302 | AE92: 0 | AF92: =IF($AE92=1, "Completed", IF($AD92<TODAY(), "Late", "On Schedule")) -> Late | AG92: 46325 | AH92: 0 | AI92: =IF($AH92=1, "Completed", IF($AG92<TODAY(), "Late", "On Schedule")) -> On Schedule | AK92: =IFERROR(SUMPRODUCT(($M$1:$AH$1),(M92:AH92))/SUMIF((M92:AH92),"<>",($M$1:$AH$1)),"") -> 0.94705882 | AL92: Late | AN92: =_xlfn.XLOOKUP($E92,'00 MASTER WORK REGISTER'!B:B,'00 MASTER WORK REGISTER'!N:N,"") -> 0 | AO92: ปรับปรุง ทางเดินข้ามรางในลานจอดรถไฟ เพื่อให้รองรับการจอดแบบ4car | AP92: =_xlfn.XLOOKUP($F92,#REF!,#REF!,"") -> #REF! | AS92: MDW-39293 | AT92: =_xlfn.XLOOKUP($AS92,'02 Design'!F:F,'02 Design'!AE:AE," ") -> MDW-69337 | AU92: =_xlfn.XLOOKUP($AS92,'02 Design'!F:F,'02 Design'!AF:AF," ") -> MDW-69338
A93: 90 | B93: 90 | C93: =_xlfn.XLOOKUP($E93,'00 MASTER WORK REGISTER'!B:B,'00 MASTER WORK REGISTER'!L:L) -> MDW-39288 | D93: Lot01 | E93: SIG3 | F93: SIG | G93: =_xlfn.XLOOKUP($E93,'00 MASTER WORK REGISTER'!B:B,'00 MASTER WORK REGISTER'!H:H) -> Point Machine Foundation Construction | H93: =_xlfn.XLOOKUP($E93,'00 MASTER WORK REGISTER'!B:B,'00 MASTER WORK REGISTER'!$I:$I,"") -> กำพล | K93: =_xlfn.XLOOKUP($E93,'00 MASTER WORK REGISTER'!$B:$B,'00 MASTER WORK REGISTER'!$M:$M,"") -> 46255 | L93: 45982 | M93: 1 | N93: =IF($M93=1, "Completed", IF($L93<TODAY(), "Late", "On Schedule")) -> Completed | O93: 46021 | P93: 1 | Q93: =IF($P93=1, "Completed", IF($O93<TODAY(), "Late", "On Schedule")) -> Completed | U93: 46100 | V93: 1 | W93: =IF($V93=1, "Completed", IF($U93<TODAY(), "Late", "On Schedule")) -> Completed | AA93: =AD93-7 -> 46288 | AB93: 0.25 | AC93: =IF($AB93=1, "Completed", IF($AA93<TODAY(), "Late", "On Schedule")) -> Late | AD93: 46295 | AE93: 0 | AF93: =IF($AE93=1, "Completed", IF($AD93<TODAY(), "Late", "On Schedule")) -> Late | AG93: =AD93+21 -> 46316 | AH93: 0 | AI93: =IF($AH93=1, "Completed", IF($AG93<TODAY(), "Late", "On Schedule")) -> Late | AK93: =IFERROR(SUMPRODUCT(($M$1:$AH$1),(M93:AH93))/SUMIF((M93:AH93),"<>",($M$1:$AH$1)),"") -> 0.94411765 | AL93: Late | AN93: =_xlfn.XLOOKUP($E93,'00 MASTER WORK REGISTER'!B:B,'00 MASTER WORK REGISTER'!N:N,"") -> 0 | AO93: ออกแบบและก่อสร้างฐานสาหรับการติดตั้ง Point Machine | AP93: =_xlfn.XLOOKUP($F93,#REF!,#REF!,"") -> #REF! | AS93: MDW-39288 | AT93: =_xlfn.XLOOKUP($AS93,'02 Design'!F:F,'02 Design'!AE:AE," ") -> MDW-69327 | AU93: =_xlfn.XLOOKUP($AS93,'02 Design'!F:F,'02 Design'!AF:AF," ") -> MDW-69328
A94: 91 | B94: 91 | C94: =_xlfn.XLOOKUP($E94,'00 MASTER WORK REGISTER'!B:B,'00 MASTER WORK REGISTER'!L:L) -> MDW-39001 | D94: Lot01 | E94: SIG4 | F94: SIG | G94: =_xlfn.XLOOKUP($E94,'00 MASTER WORK REGISTER'!B:B,'00 MASTER WORK REGISTER'!H:H) -> Modification of Depot Track Route Line to Stabling Yard | H94: =_xlfn.XLOOKUP($E94,'00 MASTER WORK REGISTER'!B:B,'00 MASTER WORK REGISTER'!$I:$I,"") -> สู่โชค | J94: Depot | K94: =_xlfn.XLOOKUP($E94,'00 MASTER WORK REGISTER'!$B:$B,'00 MASTER WORK REGISTER'!$M:$M,"") -> 46195 | L94: 45960 | M94: 1 | N94: =IF($M94=1, "Completed", IF($L94<TODAY(), "Late", "On Schedule")) -> Completed | O94: 45990 | P94: 1 | Q94: =IF($P94=1, "Completed", IF($O94<TODAY(), "Late", "On Schedule")) -> Completed | U94: 46170 | V94: 0.95 | W94: =IF($V94=1, "Completed", IF($U94<TODAY(), "Late", "On Schedule")) -> Late | AA94: 46295 | AB94: 0.5 | AC94: =IF($AB94=1, "Completed", IF($AA94<TODAY(), "Late", "On Schedule")) -> Late | AD94: =AA94+7 -> 46302 | AE94: 0 | AF94: =IF($AE94=1, "Completed", IF($AD94<TODAY(), "Late", "On Schedule")) -> Late | AG94: 46325 | AH94: 0 | AI94: =IF($AH94=1, "Completed", IF($AG94<TODAY(), "Late", "On Schedule")) -> On Schedule | AK94: =IFERROR(SUMPRODUCT(($M$1:$AH$1),(M94:AH94))/SUMIF((M94:AH94),"<>",($M$1:$AH$1)),"") -> 0.91176471 | AL94: Late | AM94: คงเหลือเก็บงาน Progress by ช.ธนัท | AN94: =_xlfn.XLOOKUP($E94,'00 MASTER WORK REGISTER'!B:B,'00 MASTER WORK REGISTER'!N:N,"") -> 0 | AO94: ปรับปรุงเส้นทางรถไฟใน Depot จนถึง ลานจอดรถไฟ ให้เข้า Stabling ได้2ทาง | AP94: =_xlfn.XLOOKUP($F94,#REF!,#REF!,"") -> #REF! | AS94: MDW-39001 | AT94: =_xlfn.XLOOKUP($AS94,'02 Design'!F:F,'02 Design'!AE:AE," ") -> MDW-69001 | AU94: =_xlfn.XLOOKUP($AS94,'02 Design'!F:F,'02 Design'!AF:AF," ") -> MDW-69002
A95: 92 | B95: 92 | C95: =_xlfn.XLOOKUP($E95,'00 MASTER WORK REGISTER'!B:B,'00 MASTER WORK REGISTER'!L:L) -> MDW-39287 | D95: Lot01 | E95: SIG5 | F95: SIG | G95: =_xlfn.XLOOKUP($E95,'00 MASTER WORK REGISTER'!B:B,'00 MASTER WORK REGISTER'!H:H) -> Strobe Light at Buffer Stops | H95: =_xlfn.XLOOKUP($E95,'00 MASTER WORK REGISTER'!B:B,'00 MASTER WORK REGISTER'!$I:$I,"") -> ประธาน | J95: Depot | K95: =_xlfn.XLOOKUP($E95,'00 MASTER WORK REGISTER'!$B:$B,'00 MASTER WORK REGISTER'!$M:$M,"") -> 46255 | L95: 46172 | M95: 1 | N95: =IF($M95=1, "Completed", IF($L95<TODAY(), "Late", "On Schedule")) -> Completed | O95: 46202 | P95: 1 | Q95: =IF($P95=1, "Completed", IF($O95<TODAY(), "Late", "On Schedule")) -> Completed | U95: 46262 | V95: 1 | W95: =IF($V95=1, "Completed", IF($U95<TODAY(), "Late", "On Schedule")) -> Completed | AA95: 46095 | AB95: 1 | AC95: =IF($AB95=1, "Completed", IF($AA95<TODAY(), "Late", "On Schedule")) -> Completed | AD95: 46203 | AE95: 0 | AF95: =IF($AE95=1, "Completed", IF($AD95<TODAY(), "Late", "On Schedule")) -> Late | AG95: =AG91 -> 46295 | AH95: 0 | AI95: =IF($AH95=1, "Completed", IF($AG95<TODAY(), "Late", "On Schedule")) -> Late | AK95: =IFERROR(SUMPRODUCT(($M$1:$AH$1),(M95:AH95))/SUMIF((M95:AH95),"<>",($M$1:$AH$1)),"") -> 0.95294118 | AL95: Late | AN95: =_xlfn.XLOOKUP($E95,'00 MASTER WORK REGISTER'!B:B,'00 MASTER WORK REGISTER'!N:N,"") -> 0 | AO95: ออกแบบ, จัดหา และติดตั้งโคมดวงไฟ(Red Strobe Ligjt) | AP95: =_xlfn.XLOOKUP($F95,#REF!,#REF!,"") -> #REF! | AS95: MDW-39287 | AT95: =_xlfn.XLOOKUP($AS95,'02 Design'!F:F,'02 Design'!AE:AE," ") -> MDW-69323 | AU95: =_xlfn.XLOOKUP($AS95,'02 Design'!F:F,'02 Design'!AF:AF," ") -> MDW-69324
A96: 93 | B96: 93 | C96: =_xlfn.XLOOKUP($E96,'00 MASTER WORK REGISTER'!B:B,'00 MASTER WORK REGISTER'!L:L) -> DWE-39016 | D96: Lot01 | E96: DWE1 | F96: DWE | G96: =_xlfn.XLOOKUP($E96,'00 MASTER WORK REGISTER'!B:B,'00 MASTER WORK REGISTER'!H:H) -> Diesel Fuel Storage Tank for Maintenance Vehicle | H96: =_xlfn.XLOOKUP($E96,'00 MASTER WORK REGISTER'!B:B,'00 MASTER WORK REGISTER'!$I:$I,"") -> สมศักดิ์ | J96: Depot | K96: =_xlfn.XLOOKUP($E96,'00 MASTER WORK REGISTER'!$B:$B,'00 MASTER WORK REGISTER'!$M:$M,"") -> 46285 | L96: 46008 | M96: 1 | N96: Completed | O96: 46038 | P96: 1 | Q96: Completed | R96: 46203 | S96: 1 | T96: =IF($S96=1, "Completed", IF($R96<TODAY(), "Late", "On Schedule")) -> Completed | U96: 46234 | V96: 1 | W96: =IF($V96=1, "Completed", IF($U96<TODAY(), "Late", "On Schedule")) -> Completed | X96: 46243 | Y96: 0 | Z96: =IF($Y96=1, "Completed", IF($X96<TODAY(), "Late", "On Schedule")) -> Late | AK96: =IFERROR(SUMPRODUCT(($M$1:$AH$1),(M96:AH96))/SUMIF((M96:AH96),"<>",($M$1:$AH$1)),"") -> 0.94736842 | AL96: Late | AM96: Test ช่วงต้น Nov-26 | AN96: =_xlfn.XLOOKUP($E96,'00 MASTER WORK REGISTER'!B:B,'00 MASTER WORK REGISTER'!N:N,"") -> 0 | AO96: ออกแบบ, จัดหา, ขอใบอนุญาต และติดตั้งระบบถังเก็บน้ำมันดีเซล | AP96: =_xlfn.XLOOKUP($F96,#REF!,#REF!,"") -> #REF! | AS96: DWE-39016 | AT96: =_xlfn.XLOOKUP($AS96,'02 Design'!F:F,'02 Design'!AE:AE," ") -> DWE-69016 | AU96: =_xlfn.XLOOKUP($AS96,'02 Design'!F:F,'02 Design'!AF:AF," ") -> DWE-69116
A97: 94 | B97: 94 | C97: =_xlfn.XLOOKUP($E97,'00 MASTER WORK REGISTER'!B:B,'00 MASTER WORK REGISTER'!L:L) -> DWE-39011 | D97: Lot01 | E97: DWE2 | F97: DWE | G97: =_xlfn.XLOOKUP($E97,'00 MASTER WORK REGISTER'!B:B,'00 MASTER WORK REGISTER'!H:H) -> Movable Height Maintenance Platform Vehicle (Boom Lift) | H97: =_xlfn.XLOOKUP($E97,'00 MASTER WORK REGISTER'!B:B,'00 MASTER WORK REGISTER'!$I:$I,"") -> สมศักดิ์ | J97: Depot | K97: =_xlfn.XLOOKUP($E97,'00 MASTER WORK REGISTER'!$B:$B,'00 MASTER WORK REGISTER'!$M:$M,"") -> 46285 | L97: 46008 | M97: 1 | N97: =IF($M97=1, "Completed", IF($L97<TODAY(), "Late", "On Schedule")) -> Completed | O97: 45875 | P97: 1 | Q97: =IF($P97=1, "Completed", IF($O97<TODAY(), "Late", "On Schedule")) -> Completed | R97: 46022 | S97: 1 | T97: =IF($S97=1, "Completed", IF($R97<TODAY(), "Late", "On Schedule")) -> Completed | U97: 46203 | V97: 1 | W97: =IF($V97=1, "Completed", IF($U97<TODAY(), "Late", "On Schedule")) -> Completed | X97: 46212 | Y97: 0 | Z97: =IF($Y97=1, "Completed", IF($X97<TODAY(), "Late", "On Schedule")) -> Late | AA97: 46164 | AB97: 1 | AC97: =IF($AB97=1, "Completed", IF($AA97<TODAY(), "Late", "On Schedule")) -> Completed | AD97: 46295 | AE97: 0 | AF97: =IF($AE97=1, "Completed", IF($AD97<TODAY(), "Late", "On Schedule")) -> Late | AG97: 46316 | AH97: 0 | AI97: =IF($AH97=1, "Completed", IF($AG97<TODAY(), "Late", "On Schedule")) -> Late | AK97: =IFERROR(SUMPRODUCT(($M$1:$AH$1),(M97:AH97))/SUMIF((M97:AH97),"<>",($M$1:$AH$1)),"") -> 0.91 | AL97: Late | AM97: Test 9-15/11/26 | AN97: =_xlfn.XLOOKUP($E97,'00 MASTER WORK REGISTER'!B:B,'00 MASTER WORK REGISTER'!N:N,"") -> 0 | AO97: จัดหารถแพลตฟอร์มบำรุงรักษาความสูงเคลื่อนย้ายได้ | AP97: =_xlfn.XLOOKUP($F97,#REF!,#REF!,"") -> #REF! | AS97: DWE-39011 | AT97: =_xlfn.XLOOKUP($AS97,'02 Design'!F:F,'02 Design'!AE:AE," ") -> DWE-69011 | AU97: =_xlfn.XLOOKUP($AS97,'02 Design'!F:F,'02 Design'!AF:AF," ") -> DWE-69111
A98: 95 | B98: 95 | C98: =_xlfn.XLOOKUP($E98,'00 MASTER WORK REGISTER'!B:B,'00 MASTER WORK REGISTER'!L:L) -> DWE-39012 | D98: Lot01 | E98: DWE3 | F98: DWE | G98: =_xlfn.XLOOKUP($E98,'00 MASTER WORK REGISTER'!B:B,'00 MASTER WORK REGISTER'!H:H) -> Fork Lift Vehicle | H98: =_xlfn.XLOOKUP($E98,'00 MASTER WORK REGISTER'!B:B,'00 MASTER WORK REGISTER'!$I:$I,"") -> สมศักดิ์ | J98: Depot | K98: =_xlfn.XLOOKUP($E98,'00 MASTER WORK REGISTER'!$B:$B,'00 MASTER WORK REGISTER'!$M:$M,"") -> 46285 | L98: 46008 | M98: 1 | N98: =IF($M98=1, "Completed", IF($L98<TODAY(), "Late", "On Schedule")) -> Completed | O98: 45747 | P98: 1 | Q98: =IF($P98=1, "Completed", IF($O98<TODAY(), "Late", "On Schedule")) -> Completed | R98: 46174 | S98: 1 | T98: =IF($S98=1, "Completed", IF($R98<TODAY(), "Late", "On Schedule")) -> Completed | U98: 46203 | V98: 1 | W98: =IF($V98=1, "Completed", IF($U98<TODAY(), "Late", "On Schedule")) -> Completed | X98: 46233 | Y98: 0 | Z98: =IF($Y98=1, "Completed", IF($X98<TODAY(), "Late", "On Schedule")) -> Late | AA98: 46295 | AB98: 0 | AC98: =IF($AB98=1, "Completed", IF($AA98<TODAY(), "Late", "On Schedule")) -> Late | AD98: 46302 | AE98: 0 | AF98: =IF($AE98=1, "Completed", IF($AD98<TODAY(), "Late", "On Schedule")) -> Late | AG98: 46323 | AH98: 0 | AI98: =IF($AH98=1, "Completed", IF($AG98<TODAY(), "Late", "On Schedule")) -> Late | AK98: =IFERROR(SUMPRODUCT(($M$1:$AH$1),(M98:AH98))/SUMIF((M98:AH98),"<>",($M$1:$AH$1)),"") -> 0.9 | AL98: Late | AM98: Test 9-15/11/26 | AN98: =_xlfn.XLOOKUP($E98,'00 MASTER WORK REGISTER'!B:B,'00 MASTER WORK REGISTER'!N:N,"") -> 0 | AO98: จัดหารถโฟล์คลิฟต์ (Fork Lift) และคอร์สฝึกอบรม | AP98: =_xlfn.XLOOKUP($F98,#REF!,#REF!,"") -> #REF! | AS98: DWE-39012 | AT98: =_xlfn.XLOOKUP($AS98,'02 Design'!F:F,'02 Design'!AE:AE," ") -> DWE-69012 | AU98: =_xlfn.XLOOKUP($AS98,'02 Design'!F:F,'02 Design'!AF:AF," ") -> DWE-69112
A99: 96 | B99: 96 | C99: =_xlfn.XLOOKUP($E99,'00 MASTER WORK REGISTER'!B:B,'00 MASTER WORK REGISTER'!L:L) -> DWE-39015 | D99: Lot01 | E99: DWE4 | F99: DWE | G99: =_xlfn.XLOOKUP($E99,'00 MASTER WORK REGISTER'!B:B,'00 MASTER WORK REGISTER'!H:H) -> Compressed Air System and Portable Air Compressor for Depot | H99: =_xlfn.XLOOKUP($E99,'00 MASTER WORK REGISTER'!B:B,'00 MASTER WORK REGISTER'!$I:$I,"") -> สมศักดิ์ | J99: Depot | K99: =_xlfn.XLOOKUP($E99,'00 MASTER WORK REGISTER'!$B:$B,'00 MASTER WORK REGISTER'!$M:$M,"") -> 46285 | L99: 46008 | M99: 1 | N99: Completed | O99: 46032 | P99: 1 | Q99: Completed | R99: 46068 | S99: 1 | T99: =IF($S99=1, "Completed", IF($R99<TODAY(), "Late", "On Schedule")) -> Completed | U99: 46284 | V99: 0 | W99: =IF($V99=1, "Completed", IF($U99<TODAY(), "Late", "On Schedule")) -> Late | X99: 46294 | Y99: 0 | Z99: =IF($Y99=1, "Completed", IF($X99<TODAY(), "Late", "On Schedule")) -> Late | AK99: =IFERROR(SUMPRODUCT(($M$1:$AH$1),(M99:AH99))/SUMIF((M99:AH99),"<>",($M$1:$AH$1)),"") -> 0.31578947 | AL99: Late | AM99: Forecast Install 1/11-30-11/26 | AN99: =_xlfn.XLOOKUP($E99,'00 MASTER WORK REGISTER'!B:B,'00 MASTER WORK REGISTER'!N:N,"") -> 0 | AO99: จัดหาระบบอากาศและเครื่องอัดอากาศ (รวม Piping) | AP99: =_xlfn.XLOOKUP($F99,#REF!,#REF!,"") -> #REF! | AS99: DWE-39015 | AT99: =_xlfn.XLOOKUP($AS99,'02 Design'!F:F,'02 Design'!AE:AE," ") -> DWE-69015 | AU99: =_xlfn.XLOOKUP($AS99,'02 Design'!F:F,'02 Design'!AF:AF," ") -> DWE-69115
A100: 97 | B100: 97 | C100: =_xlfn.XLOOKUP($E100,'00 MASTER WORK REGISTER'!B:B,'00 MASTER WORK REGISTER'!L:L) -> DWE-39017 | D100: Lot01 | E100: DWE5 | F100: DWE | G100: =_xlfn.XLOOKUP($E100,'00 MASTER WORK REGISTER'!B:B,'00 MASTER WORK REGISTER'!H:H) -> Pallet Storage Shelves in Hazardous Storage | H100: =_xlfn.XLOOKUP($E100,'00 MASTER WORK REGISTER'!B:B,'00 MASTER WORK REGISTER'!$I:$I,"") -> สมศักดิ์ | J100: Depot | K100: =_xlfn.XLOOKUP($E100,'00 MASTER WORK REGISTER'!$B:$B,'00 MASTER WORK REGISTER'!$M:$M,"") -> 46285 | L100: 46008 | M100: 1 | N100: =IF($M100=1, "Completed", IF($L100<TODAY(), "Late", "On Schedule")) -> Completed | O100: 46007 | P100: 1 | Q100: =IF($P100=1, "Completed", IF($O100<TODAY(), "Late", "On Schedule")) -> Completed | R100: 46081 | S100: 1 | T100: =IF($S100=1, "Completed", IF($R100<TODAY(), "Late", "On Schedule")) -> Completed | U100: 46173 | V100: 1 | W100: =IF($V100=1, "Completed", IF($U100<TODAY(), "Late", "On Schedule")) -> Completed | X100: 46178 | Y100: 0 | Z100: =IF($Y100=1, "Completed", IF($X100<TODAY(), "Late", "On Schedule")) -> Late | AA100: 46220 | AB100: 1 | AC100: =IF($AB100=1, "Completed", IF($AA100<TODAY(), "Late", "On Schedule")) -> Completed | AD100: 46295 | AE100: 0 | AF100: =IF($AE100=1, "Completed", IF($AD100<TODAY(), "Late", "On Schedule")) -> Late | AG100: =AD100+21 -> 46316 | AH100: 0 | AI100: =IF($AH100=1, "Completed", IF($AG100<TODAY(), "Late", "On Schedule")) -> Late | AK100: =IFERROR(SUMPRODUCT(($M$1:$AH$1),(M100:AH100))/SUMIF((M100:AH100),"<>",($M$1:$AH$1)),"") -> 0.91 | AL100: Late | AM100: Test 26-30/10/26 | AN100: =_xlfn.XLOOKUP($E100,'00 MASTER WORK REGISTER'!B:B,'00 MASTER WORK REGISTER'!N:N,"") -> 0 | AO100: จัดหาชั้นวางจัดเก็บพาเลทในพื้นที่จัดเก็บอันตราย | AP100: =_xlfn.XLOOKUP($F100,#REF!,#REF!,"") -> #REF! | AS100: DWE-39017 | AT100: =_xlfn.XLOOKUP($AS100,'02 Design'!F:F,'02 Design'!AE:AE," ") -> DWE-69017 | AU100: =_xlfn.XLOOKUP($AS100,'02 Design'!F:F,'02 Design'!AF:AF," ") -> DWE-69117
...

Sheet ตามงาน
C2: บัณฑิต
B4: No. | C4: Design Submission | D4: Lot No. | E4: Code | F4: Activity Name | G4: CK Responsible Person | H4: Expected Completion Month | I4: Design (PLAN) | J4: Design (%) | K4: Design (Status) | L4: Procurement (PLAN) | M4: Procurement (%) | N4: Procurement (Status) | O4: Construction /Installation (PLAN) | P4: Construction /Installation (%) | Q4: Construction /Installation (Status) | R4: Note
B5: 113 | C5: MDW-39237 | D5: Lot01 | E5: GEN22 | F5: Central BEMS for the MRT Orange Line System | G5: บัณฑิต | H5: 46255 | I5: 46142 | J5: 0 | K5: Late | L5: 46203 | M5: 0 | N5: Late | O5: 46249 | P5: 0 | Q5: Late | R5: PPR Oct-26 กำลังเปรียบเทียบ Spec
C6: MDW-39283 | D6: Lot01 | E6: COM2 | F6: Intercom System in Cash Handling Room (if require) | G6: บัณฑิต | H6: 46375 | I6: 45930 | J6: 1 | K6: Completed | L6: 46203 | M6: 0.5 | N6: Late | O6: 46326 | P6: 0 | Q6: On Schedule | R6: รอพื้นที่เข้าติดตั้ง
C7: AFC-39001 | D7: Lot01 | E7: COM7 | F7: Mini Paging in Ticket Office | G7: บัณฑิต | H7: 46375 | I7: 45910 | J7: 1 | K7: Completed | L7: 46203 | M7: 1 | N7: Completed | O7: 46295 | P7: 0 | Q7: Late | R7: ของมาแล้ว รอพื้นที่เข้าติดตั้ง
C8: - | D8: Lot02 | E8: MO-BEM34 | F8: Access Gate (Full Height Turnstile) at 1st floor admin ORL | G8: บัณฑิต | H8: 46388 | I8: 46354 | J8: 1 | K8: Completed | L8: 46355 | M8: 1 | N8: Completed | O8: 46387 | P8: 0 | Q8: On Schedule
C9: - | D9: Lot02 | E9: MO-BEM35 | F9: Access Gate (Tripod with Swing Gate) at MWS Entrance | G9: บัณฑิต | H9: 46388 | I9: 46354 | J9: 1 | K9: Completed | L9: 46355 | M9: 1 | N9: Completed | O9: 46387 | P9: 0 | Q9: On Schedule | R9: TMD เริ่มเข้าทำช่วงเดือน Oct-26 (CIV จบ)
C10: - | D10: Lot02 | E10: MO-BEM36 | F10: Access Gate (Tripod with Swing Gate) at Admin 2nd floor connect to OCC | G10: บัณฑิต | H10: 46388 | I10: 46354 | J10: 1 | K10: Completed | L10: 46355 | M10: 1 | N10: Completed | O10: 46387 | P10: 0 | Q10: On Schedule | R10: TMD เริ่มเข้าทำช่วงเดือน Oct-26 (CIV จบ)
C11: - | D11: Lot02 | E11: MO-BEM37 | F11: Access Gate (Tripod with Swing Gate) on Klong Chourdyai bridge | G11: บัณฑิต | H11: 46388 | I11: 46354 | J11: 1 | K11: Completed | L11: 46355 | M11: 1 | N11: Completed | O11: 46387 | P11: 0 | Q11: On Schedule | R11: TMD เริ่มเข้าทำช่วงเดือน Oct-26 (CIV จบ)
C12: - | D12: Lot02 | E12: MO-BEM38 | F12: Access Gate (Tripod with roof covering) at parking lot OCC | G12: บัณฑิต | H12: 46388 | I12: 46354 | J12: 1 | K12: Completed | L12: 46355 | M12: 1 | N12: Completed | O12: 46387 | P12: 0 | Q12: On Schedule | R12: TMD เริ่มเข้าทำช่วงเดือน Oct-26 (CIV จบ)
C13: - | D13: Lot02 | E13: MO-BEM39 | F13: Access Gate (Tripod with roof covering) at Stair up to Depot slab | G13: บัณฑิต | H13: 46388 | I13: 46354 | J13: 1 | K13: Completed | L13: 46355 | M13: 1 | N13: Completed | O13: 46387 | P13: 0 | Q13: On Schedule | R13: TMD เริ่มเข้าทำช่วงเดือน Oct-26 (CIV จบ)
C14: - | D14: Lot02 | E14: MO-BEM40 | F14: Access Control (2 Factors, Card + Finger Print) at High Security rooms - CCR/PTR/Store | G14: บัณฑิต | H14: 46388 | I14: 46354 | J14: 1 | K14: Completed | L14: 46355 | M14: 1 | N14: Completed | O14: 46387 | P14: 0 | Q14: On Schedule | R14: STE เริ่มเข้าทำช่วงเดือน Oct-26
C15: - | D15: Lot02 | E15: MO-BEM41 | F15: Link CCTV Landscape of all depot ORL area for MMC BL monitoring. | G15: บัณฑิต | H15: 46388 | I15: 46354 | J15: 0 | K15: On Schedule | L15: 46355 | M15: 0 | N15: On Schedule | O15: 46387 | P15: 0 | Q15: On Schedule | R15: จัดจ้าง STE
C18: Design Submission | D18: Lot No. | E18: Code | F18: Activity Name | G18: CK Responsible Person | H18: Expected Completion Month | I18: T&C (PLAN) | J18: T&C (%) | K18: T&C (Status) | L18: Test Procedure (PLAN) | M18: Inspection (%) | N18: Test Procedure (Status) | O18: Inspection (PLAN) | P18: Inspection (%) | Q18: Inspection (Status) | R18: Test Report (PLAN) | S18: Test Report (%) | T18: Test Report (Status) | U18: Note
D19: Lot01 | E19: GEN21 | F19: Project Information Management System (PIMS) | G19: บัณฑิต | H19: 45565 | I19: 45549 | J19: 1 | K19: Completed | L19: =O19-7 -> 46288 | M19: 0 | N19: =IF($AB19=1, "Completed", IF($AA19<TODAY(), "Late", "On Schedule")) -> Late | O19: 46295 | P19: 0 | Q19: =IF($AE19=1, "Completed", IF($AD19<TODAY(), "Late", "On Schedule")) -> Late | R19: =O19+21 -> 46316 | S19: 0 | T19: =IF($AH19=1, "Completed", IF($AG19<TODAY(), "Late", "On Schedule")) -> Late | U19: งานจบแล้ว
C22: ประธาน
B23: 118
C24: Design Submission | D24: Lot No. | E24: Code | F24: Activity Name | G24: CK Responsible Person | H24: Expected Completion Month | I24: Design (PLAN) | J24: Design (%) | K24: Design (Status) | L24: Procurement (PLAN) | M24: Procurement (%) | N24: Procurement (Status) | O24: Construction /Installation (PLAN) | P24: Construction /Installation (%) | Q24: Construction /Installation (Status) | R24: Note
C25: 0 | D25: Lot02 | E25: MO-CK30 | F25: Lighting for sealed space under stairs and behind lift shaft at underground station | G25: ประธาน | H25: 46388 | I25: 46309 | J25: 0 | K25: Late | L25: 46340 | M25: 0 | N25: On Schedule | O25: 46387 | P25: 0 | Q25: On Schedule | R25: ไฟส่องสว่างสำหรับพื้นที่ปิดใต้บันไดและด้านหลังช่องลิฟต์ที่สถานีรถไฟใต้ดิน
C26: MDW-39518 | D26: Lot02 | E26: MO-BEM26 | F26: Street Lighting system area between MRTA Fence and Depot slab | G26: ประธาน | H26: 46235 | I26: 46126 | J26: 0.5 | K26: Late | L26: 46157 | M26: 0 | N26: Late | O26: 46234 | P26: 0 | Q26: Late | R26: อยู่ระหว่างจัดเตรียมแบบ งาน Construction จบ Mar-27
C27: MDW-39541 | D27: Lot02 | E27: MO-BEM48 | F27: Fire alarm manual call point cover in public area at all station | G27: ประธาน | H27: 46388 | I27: 46279 | J27: 0 | K27: Late | L27: 46325 | M27: 0 | N27: On Schedule | O27: 46387 | P27: 0 | Q27: On Schedule | R27: อยูระหว่างจัดเตรียมแบบ
C28: MDW-39289 | D28: Lot01 | E28: GEN11 | F28: Earthing and Bonding Modification | G28: ประธาน | H28: 46082 | I28: 45688 | J28: 1 | K28: Completed | L28: 45930 | M28: 0.67 | N28: Late | O28: 46081 | P28: 1 | Q28: Completed
C29: MDW-39296 | D29: Lot02 | E29: MO-CK15.2 | F29: Change Electrical Equipment to be Explosion-proof type - Building Services | G29: ประธาน | H29: 46143 | I29: 46004 | J29: 1 | K29: Completed | L29: 46050 | M29: 0.5 | N29: Late | O29: 46142 | P29: 0.9 | Q29: Late | R29: Fore cast Nov-26
C30: MDW-39256 | D30: Lot01 | E30: GEN1.8 | F30: Modification in Staff Mess Room at OR23-OR29 | G30: ประธาน | H30: 46235 | I30: 46235 | J30: 1 | K30: Completed | L30: 46265 | M30: 1 | N30: Completed | O30: 46295 | P30: 0.8 | Q30: Late
C31: MDW-39257 | D31: Lot01 | E31: GEN1.9 | F31: Modification of Air Conditioning in CER and SER at OR13-OR19 | G31: ประธาน | H31: 46235 | I31: 46235 | J31: 1 | K31: Completed | L31: 46265 | M31: 1 | N31: Completed | O31: 46295 | P31: 0.99 | Q31: Late
C32: MDW-39258 | D32: Lot01 | E32: GEN1.10 | F32: Modification of Air Conditioning in CER and SER at OR20-OR22 | G32: ประธาน | H32: 46235 | I32: 46235 | J32: 1 | K32: Completed | L32: 46265 | M32: 1 | N32: Completed | O32: 46295 | P32: 0.99 | Q32: Late
C33: MDW-39259 | D33: Lot01 | E33: GEN1.11 | F33: Modification of Air Conditioning in CER and SER at OR23-OR29 | G33: ประธาน | H33: 46235 | I33: 46235 | J33: 1 | K33: Completed | L33: 46265 | M33: 1 | N33: Completed | O33: 46295 | P33: 0.99 | Q33: Late
C34: MDW-39273 | D34: Lot01 | E34: GEN1.13 | F34: Modification of New M&E UPS Room at IVS15-IVS17 - Building Services | G34: ประธาน | H34: 46235 | I34: 46235 | J34: 1 | K34: Completed | L34: 46265 | M34: 1 | N34: Completed | O34: 46295 | P34: 0.99 | Q34: Late
C35: MDW-39299 | D35: Lot01 | E35: GEN1.15 | F35: Provision of Air Conditioning System in Commercial Room at OR13-OR19 | G35: ประธาน | H35: 46235 | I35: 46235 | J35: 1 | K35: Completed | L35: 46265 | M35: 1 | N35: Completed | O35: 46295 | P35: 0.98 | Q35: Late
C36: MDW-39296 | D36: Lot01 | E36: GEN2.19 | F36: Dangerous Goods Building in Depot - Building Services | G36: ประธาน | H36: 46235 | I36: 46004 | J36: 1 | K36: Completed | L36: 46050 | M36: 1 | N36: Completed | O36: 46142 | P36: 0.9 | Q36: Late
C37: MDW-39243 | D37: Lot01 | E37: GEN18 | F37: Eye Adaptation Lighting (Lighting at Tunnel to Expose) | G37: ประธาน | H37: 46345 | I37: 45930 | J37: 1 | K37: Completed | L37: 45960 | M37: 1 | N37: Completed | O37: 46125 | P37: 0.9 | Q37: Late | R37: Progress DPA1 : 100% Progress DPA2 : 100% Progress Cut&Cover OR22 : 95%
C38: MDW-39304 | D38: Lot01 | E38: COM5 | F38: MEA Radio | G38: ประธาน | H38: 46285 | I38: 46052 | J38: 1 | K38: Completed | L38: 46142 | M38: 1 | N38: Completed | O38: 46203 | P38: 0.9 | Q38: Late | R38: รอเฟอร์นิเจอร์ Fore cast Dec-26
C39: MDW-39501 | D39: Lot02 | E39: MO-CK1.2 | F39: Store Modification Works at Main Workshop - Building Services | G39: ประธาน | H39: 46177 | I39: 46065 | J39: 1 | K39: Completed | L39: 46111 | M39: 1 | N39: Completed | O39: 46170 | P39: 0.95 | Q39: Late | R39: รอสรุปตำแหน่ง Power Plug ชาร์จโฟลคลิฟท์ Oct-26
C40: MDW-39504 | D40: Lot02 | E40: MO-CK3 | F40: Move or link Workstation and control panel to MMC room at admin C 2nd floor | G40: ประธาน | H40: 46236 | I40: 46081 | J40: 1 | K40: Completed | L40: 46127 | M40: 1 | N40: Completed | O40: 46265 | P40: 0.88 | Q40: Late | R40: Fore cast Oct-26
C41: MDW-39506 | D41: Lot02 | E41: MO-BEM1.2 | F41: Walkway from Main Work Shop to Stabling Area - Building Services | G41: ประธาน | H41: 46236 | I41: 46140 | J41: 1 | K41: Completed | L41: 46171 | M41: 1 | N41: Completed | O41: 46295 | P41: 0 | Q41: Late | R41: รองานหลังคา CIV Oct-26
C42: MDW-39517 | D42: Lot02 | E42: MO-BEM14.2 | F42: Modification Works : Walkway Bridge between BL Depot and ORL Depot - Building Services | G42: ประธาน | H42: 46237 | I42: 46036 | J42: 1 | K42: Completed | L42: 46082 | M42: 1 | N42: Completed | O42: 46295 | P42: 0.1 | Q42: Late | R42: รองานหลังคา CIV Oct-26
C43: MDW-39520 | D43: Lot02 | E43: MO-BEM25.2 | F43: Chain Link Fence to divide controlled areas on Depot slab 3 m.x 485 m.- Building Services | G43: ประธาน | H43: 46296 | I43: 46187 | J43: 1 | K43: Completed | L43: 46233 | M43: 1 | N43: Completed | O43: 46295 | P43: 0 | Q43: Late | R43: Fore cast Oct-26
C45: Design Submission | D45: Lot No. | E45: Code | F45: Activity Name | G45: CK Responsible Person | H45: Expected Completion Month | I45: Test Procedure (PLAN) | J45: Test Procedure (%) | K45: Test Procedure (Status) | L45: Inspection (PLAN) | M45: Inspection (%) | N45: Inspection (Status) | O45: Test Report (PLAN) | P45: Test Report (%) | Q45: Test Report (Status) | R45: Note
C46: MDW-39242 | D46: Lot01 | E46: GEN4.0 | F46: Modification Works for Training Room at Ratchada Station | G46: ประธาน | H46: 46113 | I46: 46097 | J46: 0.5 | K46: Late | L46: 46295 | M46: 0 | N46: Late | O46: 46316 | P46: 0 | Q46: Late
C47: MDW-39245 | D47: Lot01 | E47: GEN4.2 | F47: AFC Training Room Modification - Building Services | G47: ประธาน | H47: 46255 | I47: 46105 | J47: 1 | K47: Completed | L47: 46241 | M47: 1 | N47: Completed | O47: 46295 | P47: 0 | Q47: Late
C48: DWE-39025 | D48: Lot01 | E48: GEN7.2 | F48: Dangerous Waste Storage Building in Depot - Building service | G48: ประธาน | H48: 46285 | I48: 46132 | J48: 1 | K48: Completed | L48: 46181 | M48: 1 | N48: Completed | O48: 46295 | P48: 0 | Q48: Late
C49: DWE-39025 | D49: Lot01 | E49: GEN8.2 | F49: General Waste Storage Building in Depot - Building service | G49: ประธาน | H49: 46285 | I49: 46132 | J49: 1 | K49: Completed | L49: 46181 | M49: 1 | N49: Completed | O49: 46295 | P49: 0 | Q49: Late
C50: MDW-39289 | D50: Lot01 | E50: GEN11 | F50: Earthing and Bonding Modification | G50: ประธาน | H50: 46082 | I50: 46288 | J50: 0 | K50: Late | L50: 46295 | M50: 0 | N50: Late | O50: 46316 | P50: 0 | Q50: Late
C51: MDW-39241 | D51: Lot01 | E51: GEN14.2 | F51: Driver Train Simulation Room and Train Crew Office at OR18 - Building Services | G51: ประธาน | H51: 46255 | I51: 46093 | J51: 1 | K51: Completed | L51: 46241 | M51: 1 | N51: Completed | O51: 46295 | P51: 0 | Q51: Late
C52: MDW-39287 | D52: Lot01 | E52: SIG5 | F52: Strobe Light at Buffer Stops | G52: ประธาน | H52: 46255 | I52: 46095 | J52: 1 | K52: Completed | L52: 46203 | M52: 1 | N52: Completed | O52: 46295 | P52: 0 | Q52: Late
C53: MDW-39556 | D53: Lot02 | E53: MO-CK7 | F53: Addition small power for lounge and pantry room at 2nd floor and Hall and observation room at 3nd floor | G53: ประธาน | H53: 46238 | I53: 46147 | J53: 1 | K53: Completed | L53: 46295 | M53: 0.5 | N53: Late | O53: 46316 | P53: 0 | Q53: Late
C54: MDW-39548 | D54: Lot02 | E54: MO-CK8 | F54: Air Condition for using store room to be pantry room. 2nd floor | G54: ประธาน | H54: 46239 | I54: 46105 | J54: 1 | K54: Completed | L54: 46295 | M54: 0.5 | N54: Late | O54: 46213 | P54: 1 | Q54: Completed
C55: MDW-39551 | D55: Lot02 | E55: MO-CK14 | F55: Modify Cleaner room at OR29 to be Train crew Standby office with facility system | G55: ประธาน | H55: 46204 | I55: 46295 | J55: 0 | K55: Late | L55: 46302 | M55: 0 | N55: Late | O55: 46325 | P55: 0 | Q55: On Schedule
C56: MDW-39512 | D56: Lot02 | E56: MO-BEM4.2 | F56: Maintenance Office Rooms at Main Workshop - Building Services | G56: ประธาน | H56: 46207 | I56: 46288 | J56: 0 | K56: Late | L56: 46295 | M56: 0 | N56: Late | O56: 46316 | P56: 0 | Q56: Late
C57: MDW-39526 | D57: Lot02 | E57: MO-BEM10 | F57: Relocate Fire Hose Cabinet to be outside of the clearance gauge zone 17 set | G57: ประธาน | H57: 46143 | I57: 46099 | J57: 1 | K57: Completed | L57: 46295 | M57: 0.5 | N57: Late | O57: 46157 | P57: 1 | Q57: Completed | R57: รอส่งงานกับ BEM
C58: MDW-39529 | D58: Lot02 | E58: MO-BEM11.2 | F58: Washing Area in Cleaning Staff Room at Stabling Yard - Building Services | G58: ประธาน | H58: 46238 | I58: 46112 | J58: 1 | K58: Completed | L58: 46204 | M58: 1 | N58: Completed | O58: 46213 | P58: 1 | Q58: Completed
C59: MDW-39515 | D59: Lot02 | E59: MO-BEM15.2 | F59: Roof for cars parking lots area (184 car) - Building Services | G59: ประธาน | H59: 46237 | I59: 46288 | J59: 0 | K59: Late | L59: 46295 | M59: 0 | N59: Late | O59: 46316 | P59: 0 | Q59: Late | R59: รอส่งงานกับ BEM
C60: MDW-39523 | D60: Lot02 | E60: MO-BEM20 | F60: Hose bib 1/2" 4 sets for Tree around Admin area | G60: ประธาน | H60: 46174 | I60: 46112 | J60: 1 | K60: Completed | L60: 46295 | M60: 0.5 | N60: Late | O60: 46213 | P60: 1 | Q60: Completed
C63: สมศักดิ์
C65: Design Submission | D65: Lot No. | E65: Code | F65: Activity Name | G65: CK Responsible Person | H65: Expected Completion Month | I65: Design (PLAN) | J65: Design (%) | K65: Design (Status) | L65: Procurement (PLAN) | M65: Procurement (%) | N65: Procurement (Status) | O65: Manufacturing / Delivery Process (PLAN) | P65: Manufacturing / Delivery Process (%) | Q65: Manufacturing / Delivery (Status) | R65: Construction /Installation (PLAN) | S65: Construction /Installation (%) | T65: Construction /Installation (Status) | U65: Note
C66: DWE-39002 | D66: Lot01 | E66: DWE19.2 | F66: Tunnel Inspection and Cleaning Vehicle | G66: สมศักดิ์ | H66: 46285 | I66: 45900 | J66: 0 | K66: Late | L66: 46009 | M66: 1 | N66: Completed | R66: 46306 | S66: 0 | T66: Late | U66: No Update
C67: DWE-39007 | D67: Lot01 | E67: DWE19.7 | F67: Rail Head Grinding Machine Vehicle | G67: สมศักดิ์ | H67: 46285 | I67: 45900 | J67: 0 | K67: Late | L67: 46009 | M67: 1 | N67: Completed | R67: 46630 | S67: 0 | T67: On Schedule
C68: DWE-39018 | D68: Lot01 | E68: DWE9 | F68: Repair Equipment | G68: สมศักดิ์ | H68: 46285 | I68: 46008 | J68: 1 | K68: =IF($M68=1, "Completed", IF($L68<TODAY(), "Late", "On Schedule")) -> Late | L68: 46234 | M68: 0.5 | N68: =IF($P68=1, "Completed", IF($O68<TODAY(), "Late", "On Schedule")) -> On Schedule | O68: 46325 | P68: 0.7 | Q68: =IF($S68=1, "Completed", IF($R68<TODAY(), "Late", "On Schedule")) -> On Schedule | R68: 46449 | S68: 0 | T68: =IF($V68=1, "Completed", IF($U68<TODAY(), "Late", "On Schedule")) -> On Schedule | U68: คงเหลือจัดส่งอุปกรณ์
C69: DWE-39016 | D69: Lot01 | E69: DWE1 | F69: Diesel Fuel Storage Tank for Maintenance Vehicle | G69: สมศักดิ์ | H69: 46285 | I69: 46008 | J69: 1 | K69: Completed | L69: 46038 | M69: 1 | N69: Completed | O69: 46203 | P69: 1 | Q69: Completed | R69: 46234 | S69: 0.99 | T69: Late | U69: คงเหลืองานร้อยสาย
C70: DWE-39015 | D70: Lot01 | E70: DWE4 | F70: Compressed Air System and Portable Air Compressor for Depot | G70: สมศักดิ์ | H70: 46285 | I70: 46008 | J70: 1 | K70: Completed | L70: 46032 | M70: 1 | N70: Completed | O70: 46068 | P70: 1 | Q70: Completed | R70: 46284 | S70: 0 | T70: Late | U70: Forecast 1/10-30-11/26
C71: EPS-39001 | D71: Lot01 | E71: PSY1 | F71: Diesel Fuel Storage Tanks for Power Generators | G71: สมศักดิ์ | H71: 46105 | I71: 46038 | J71: 1 | K71: Completed | L71: 46112 | M71: 1 | N71: Completed | O71: 46112 | P71: 1 | Q71: Completed | R71: 46203 | S71: 0.75 | T71: Late | U71: คงเหลืองานเดินท่อและ Pump น้ำมัน
C73: Design Submission | D73: Lot No. | E73: Code | F73: Activity Name | G73: CK Responsible Person | H73: Expected Completion Month | I73: T&C (PLAN) | J73: T&C (%) | K73: T&C (Status) | L73: Test Procedure (PLAN) | M73: Test Procedure (%) | N73: Test Procedure (Status) | O73: Inspection (PLAN) | P73: Inspection (%) | Q73: Inspection (Status) | R73: Test Report (PLAN) | S73: Test Report (%) | T73: Test Report (Status) | U73: Note
C74: DWE-39011 | D74: Lot01 | E74: DWE2 | F74: Movable Height Maintenance Platform Vehicle (Boom Lift) | G74: สมศักดิ์ | H74: 46285 | I74: 46212 | J74: 0 | K74: Late | L74: 46164 | M74: 1 | N74: Completed | O74: 46295 | P74: 0 | Q74: Late | R74: 46316 | S74: 0 | T74: Late
C75: DWE-39012 | D75: Lot01 | E75: DWE3 | F75: Fork Lift Vehicle | G75: สมศักดิ์ | H75: 46285 | I75: 46233 | J75: 0 | K75: Late | L75: 46295 | M75: 0 | N75: Late | O75: 46302 | P75: 0 | Q75: Late | R75: 46323 | S75: 0 | T75: On Schedule
C76: DWE-39017 | D76: Lot01 | E76: DWE5 | F76: Pallet Storage Shelves in Hazardous Storage | G76: สมศักดิ์ | H76: 46285 | I76: 46178 | J76: 0 | K76: Late | L76: 46220 | M76: 1 | N76: Completed | O76: 46295 | P76: 0 | Q76: Late | R76: 46316 | S76: 0 | T76: Late
C77: DWE-39017 | D77: Lot01 | E77: DWE6 | F77: Pallet Storage in Main Storage Room | G77: สมศักดิ์ | H77: 46285 | I77: 46178 | J77: 0 | K77: Late | L77: 46220 | M77: 1 | N77: Completed | O77: 46295 | P77: 0 | Q77: Late | R77: 46316 | S77: 0 | T77: Late
C78: DWE-39017 | D78: Lot01 | E78: DWE7 | F78: Two-Tier Shelf | G78: สมศักดิ์ | H78: 46285 | I78: 46178 | J78: 0 | K78: Late | L78: 46220 | M78: 1 | N78: Completed | O78: 46295 | P78: 0 | Q78: Late | R78: 46316 | S78: 0 | T78: Late
C79: DWE-39017 | D79: Lot01 | E79: DWE8 | F79: Tool Storage | G79: สมศักดิ์ | H79: 46285 | I79: 46178 | J79: 0 | K79: Late | L79: 46220 | M79: 1 | N79: Completed | O79: 46295 | P79: 0 | Q79: Late | R79: 46316 | S79: 0 | T79: Late
C80: DWE-39020 | D80: Lot01 | E80: DWE10 | F80: Oil & Grease Disposal | G80: สมศักดิ์ | H80: 46285 | I80: 46208 | J80: 0 | K80: Late | L80: 46295 | M80: 0 | N80: Late | O80: 46302 | P80: 0 | Q80: Late | R80: 46323 | S80: 0 | T80: On Schedule
C81: DWE-39020 | D81: Lot01 | E81: DWE11 | F81: Grease Dispensers | G81: สมศักดิ์ | H81: 46285 | I81: 46208 | J81: 0 | K81: Late | L81: 46295 | M81: 0 | N81: Late | O81: 46302 | P81: 0 | Q81: Late | R81: 46323 | S81: 0 | T81: On Schedule
C82: DWE-39020 | D82: Lot01 | E82: DWE12 | F82: Waste Disposal | G82: สมศักดิ์ | H82: 46285 | I82: 46208 | J82: 0 | K82: Late | L82: 46295 | M82: 0 | N82: Late | O82: 46302 | P82: 0 | Q82: Late | R82: 46323 | S82: 0 | T82: On Schedule
C85: สหชาติ
C87: Design Submission | D87: Lot No. | E87: Code | F87: Activity Name | G87: CK Responsible Person | H87: Expected Completion Month | I87: Design (PLAN) | J87: Design (%) | K87: Design (Status) | L87: Procurement (PLAN) | M87: Procurement (%) | N87: Procurement (Status) | O87: Manufacturing / Delivery Process (PLAN) | P87: Manufacturing / Delivery Process (%) | Q87: Manufacturing / Delivery (Status) | R87: Construction /Installation (PLAN) | S87: Construction /Installation (%) | T87: Construction /Installation (Status) | U87: Note
C88: MDW-39297 | D88: Lot01 | E88: GEN2.15 | F88: Training Room at Ratchada Station (Part 2) | G88: สหชาติ | H88: 46235 | I88: 46235 | J88: 0 | K88: Late | L88: 46265 | M88: 1 | N88: Completed | R88: 46295 | S88: 1 | T88: Completed
C89: MDW-39244 | D89: Lot01 | E89: GEN4.1 | F89: AFC Training Room Modification - Civil & AR | G89: สหชาติ | H89: 46255 | I89: 46295 | J89: 0.1 | K89: Late | L89: 46310 | M89: 1 | N89: Completed | R89: 46341 | S89: 0 | T89: On Schedule | U89: อยู่ระหว่างจัดทำแบบก่อสร้าง
C90: GRS-39001-40 | D90: Lot01 | E90: GEN10.2 | F90: Graphic and Signage Mainline & IVS,VS | G90: สหชาติ | H90: 46255 | I90: 46188 | J90: 0.79 | K90: Late | L90: 46173 | M90: 0.95 | N90: Late | O90: 46234 | P90: 0 | Q90: Late | R90: 46234 | S90: 0 | T90: Late | U90: GRS
C91: GRS-39001-40 | D91: Lot01 | E91: GEN10.3 | F91: Graphic and Signage Depot | G91: สหชาติ | H91: 46255 | I91: 46249 | J91: 0.9 | K91: Late | L91: 46234 | M91: 0.93 | N91: Late | O91: 46203 | P91: 0.56 | Q91: Late | R91: 46203 | S91: 0.19 | T91: Late | U91: GRS
C92: MDW-39279 | D92: Lot01 | E92: AFC3 | F92: Balustrade Modification Along AFC Gate Line | G92: สหชาติ | H92: 46285 | I92: 46203 | J92: 0.1 | K92: Late | L92: 46249 | M92: 0.5 | N92: Late | R92: 46332 | S92: 0 | T92: On Schedule | U92: จัดเตรียมแบบ ออกPPR Oct-26
C93: 0 | D93: Lot02 | E93: MO-CK18 | F93: Emergency escape route map | G93: สหชาติ | H93: 46388 | I93: 46295 | J93: 0 | K93: Late | L93: 46325 | M93: 0.5 | N93: On Schedule | O93: 46387 | P93: 0 | Q93: On Schedule | R93: 46387 | S93: 0 | T93: On Schedule | U93: GRS
C94: 0 | D94: Lot02 | E94: MO-CK22 | F94: Fire escape stairs level signs in the Depot, VS and IVS areas | G94: สหชาติ | H94: 46388 | I94: 46295 | J94: 0.5 | K94: Late | L94: 46326 | M94: 0 | N94: On Schedule | O94: 46315 | P94: 0 | Q94: Late | R94: 46387 | S94: 0 | T94: On Schedule | U94: GRS
C95: 0 | D95: Lot02 | E95: MO-CK25 | F95: Station Area sign 28 stations | G95: สหชาติ | H95: 46143 | I95: 46188 | J95: 0.8 | K95: Late | L95: 46203 | M95: 1 | N95: Completed | O95: 46295 | P95: 0 | Q95: Late | R95: 46376 | S95: 0 | T95: On Schedule | U95: GRS
C96: MDW-39532 | D96: Lot02 | E96: MO-CK27 | F96: Spike fence for Depot slab | G96: สหชาติ | H96: 46388 | I96: 46234 | J96: 0.7 | K96: Late | L96: 46265 | M96: 0 | N96: Late | R96: 46387 | S96: 0 | T96: On Schedule | U96: อยู่ระหว่างส่งขออนุมัติแบบรอ Approve
C97: 0 | D97: Lot02 | E97: MO-CK31 | F97: Modify the access door of sealed space (under-stairs room) with a Sump Pump or ESPS cabinet | G97: สหชาติ | H97: 46388 | I97: 46219 | J97: 0 | K97: Late | L97: 46250 | M97: 0 | N97: Late | R97: 46387 | S97: 0 | T97: On Schedule
C98: 0 | D98: Lot02 | E98: MO-BEM7 | F98: Modify maintenance service door to the roof building to easier access while maintaining safe operational standards | G98: สหชาติ | H98: 46388 | I98: 46314 | J98: 0.5 | K98: Late | L98: 46345 | M98: 0 | N98: On Schedule | R98: 46387 | S98: 0 | T98: On Schedule
C99: MDW-39532 | D99: Lot02 | E99: MO-BEM22 | F99: Addition Spike fence for MRTA fence and Chain link at Klong Chourdyai 400m. | G99: สหชาติ | H99: 46388 | I99: 46264 | J99: 0.7 | K99: Late | L99: 46295 | M99: 0 | N99: Late | R99: 46387 | S99: 0 | T99: On Schedule | U99: อยู่ระหว่างส่งขออนุมัติแบบรอ Approve
C100: MDW-39537 | D100: Lot02 | E100: MO-BEM43 | F100: Handrails for ladder at IVS and Vent buildings | G100: สหชาติ | H100: 46266 | I100: 46112 | J100: 0.7 | K100: Late | L100: 46143 | M100: 0 | N100: Late | R100: 46265 | S100: 0 | T100: Late | U100: อยู่ระหว่างส่งขออนุมัติแบบรอ Approve
C101: MDW-39539 | D101: Lot02 | E101: MO-BEM45 | F101: Roof for control panel on vent building | G101: สหชาติ | H101: 46388 | I101: 46279 | J101: 0.7 | K101: Late | L101: 46325 | M101: 0 | N101: On Schedule | R101: 46387 | S101: 0 | T101: On Schedule | U101: อยู่ระหว่างส่งขออนุมัติแบบรอ Approve
C102: MDW-39553 | D102: Lot02 | E102: MO-BEM46 | F102: Provide Standing plate or ladder to access the Fire Valve in at Omega points for all underground stations. | G102: สหชาติ | H102: 46388 | I102: 46279 | J102: 0 | K102: Late | L102: 46325 | M102: 0 | N102: On Schedule | R102: 46387 | S102: 0 | T102: On Schedule
C103: MDW-39540 | D103: Lot02 | E103: MO-BEM47 | F103: Water drop protection above UPS cabinet at station and Depot | G103: สหชาติ | H103: 46388 | I103: 46279 | J103: 0 | K103: Late | L103: 46325 | M103: 0 | N103: On Schedule | R103: 46387 | S103: 0 | T103: On Schedule
C104: MDW-39542 | D104: Lot02 | E104: MO-BEM49 | F104: Emergency stop button cover for escalator at all station. | G104: สหชาติ | H104: 46388 | I104: 46279 | J104: 0 | K104: Late | L104: 46325 | M104: 0 | N104: On Schedule | R104: 46387 | S104: 0 | T104: On Schedule
C105: GRS-39001-40 | D105: Lot01 | E105: GEN10.1 | F105: Graphic and Signage Station | G105: สหชาติ | H105: 46255 | I105: 46203 | J105: 1 | K105: Completed | L105: 46173 | M105: 0.95 | N105: Late | O105: 46418 | P105: 0.76 | Q105: On Schedule | R105: 46446 | S105: 0.34 | T105: On Schedule | U105: GRS
C106: MDW-39276 | D106: Lot01 | E106: AFC2 | F106: Ticket Issuing Machine (TIM) Wall Opening and Closing | G106: สหชาติ | H106: 46285 | I106: 46052 | J106: 1 | K106: Completed | L106: 46096 | M106: 0.5 | N106: Late | R106: 46216 | S106: 1 | T106: Completed | U106: มีแก้ไขตำแหน่ง OR14,17,18,23
C107: MDW-39278 | D107: Lot01 | E107: AFC4 | F107: Underfloor Embedded Duct Modification for AFC Gates Line | G107: สหชาติ | H107: 46285 | I107: 46052 | J107: 1 | K107: Completed | L107: 46114 | M107: 0.67 | N107: Late | R107: 46304 | S107: 0.81 | T107: Late
C108: PSY-39001-9 | D108: Lot01 | E108: PSY2 | F108: GIS and BSS Building and Other Facilities | G108: สหชาติ | H108: 46105 | I108: 45533 | J108: 1 | K108: Completed | L108: 45563 | M108: 0.69 | N108: Late | R108: 45995 | S108: 1 | T108: Completed
C109: PSY-39011 | D109: Lot01 | E109: PSY3 | F109: Steel Grating Raised Floor for EE Panel | G109: สหชาติ | H109: 46105 | I109: 45565 | J109: 1 | K109: Completed | L109: 45595 | M109: 0.75 | N109: Late | R109: 45852 | S109: 1 | T109: Completed
C110: MDW-39550 | D110: Lot02 | E110: MO-CK13.1 | F110: Satellite Store at OR21 - Civil & AR | G110: สหชาติ | H110: 46389 | I110: 46264 | J110: 1 | K110: Completed | L110: 46310 | M110: 0 | N110: Late | R110: 46387 | S110: 0 | T110: On Schedule
C111: MDW-39505 | D111: Lot02 | E111: MO-BEM1.1 | F111: Walkway from Main Work Shop to Stabling Area - Civil & AR | G111: สหชาติ | H111: 46236 | I111: 46140 | J111: 1 | K111: Completed | L111: 46171 | M111: 0.92 | N111: Late | R111: 46295 | S111: 0.85 | T111: Late | U111: คงเหลืองานมุงหลังคา Metal sheet
C112: MDW-39522 | D112: Lot02 | E112: MO-BEM13.1 | F112: Zero Discharge Water treatment in Depot - Civil & AR | G112: สหชาติ | H112: 46388 | I112: 46249 | J112: 1 | K112: Completed | L112: 46295 | M112: 0.75 | N112: Late | R112: 46387 | S112: 0.63 | T112: On Schedule | U112: คงเหลืองานประกอบและติดตั้งโครงหลงัคา
C113: - | D113: Lot02 | E113: MO-BEM21 | F113: Relocate Security Guard Box at Front Gate and Install Roof 3x5m. | G113: สหชาติ | H113: 46390 | I113: 46234 | J113: 1 | K113: Completed | L113: 46295 | M113: 0.75 | N113: Late | R113: 46387 | S113: 0 | T113: On Schedule
C114: MDW-39534 | D114: Lot02 | E114: MO-BEM21.1 | F114: Modification Works : Security Guard Box at ORL Depot Entrance - Civil & AR | G114: สหชาติ | H114: 46389 | I114: 46234 | J114: 1 | K114: Completed | L114: 46295 | M114: 0.67 | N114: Late | R114: 46387 | S114: 1 | T114: Completed
...

Sheet In
J10: Inspection (PLAN) | K10: ผู้รับผิดชอบ
B11: Lot01 | C11: ='01 Summary'!$C$126 -> PSY-39001-9 | D11: PSY2 | E11: PSY | F11: GIS and BSS1 Building and Other Facilities | G11: สหชาติ | I11: 46105 | J11: 46295 | K11: เกียรติพล
B12: Lot02 | C12: MDW-39503 | D12: Lot02 | E12: MO-CK2 | F12: New MMC at Admin Building - Civil&AR | G12: สหชาติ | H12: 46237 | I12: 46295 | J12: 46295 | K12: เกียรติพล
B13: Lot02 | C13: ='01 Summary'!$C$149 -> MDW-39543 | D13: MO-CK4 | E13: MO-CK | F13: Bird & Rain Protection for Open space Admin C | G13: สหชาติ | H13: Depot | I13: 46235 | J13: 46295 | K13: เกียรติพล
B14: Lot02 | C14: ='01 Summary'!$C$151 -> MDW-39547 | D14: MO-CK6 | E14: MO-CK | F14: Modify Lockset the emergency door to be used for passage between the 2nd and 3rd floors inside the building. | G14: สหชาติ | H14: Depot | I14: 46237 | J14: 46295 | K14: เกียรติพล
B15: Lot02 | C15: ='01 Summary'!$C$188 -> MDW-39507 | D15: MO-BEM2 | E15: MO-BEM | F15: High Roof at Main Work Shop Entrance and Store | G15: สหชาติ | H15: Depot | I15: 46235 | J15: 46295 | K15: เกียรติพล
B16: Lot02 | C16: ='01 Summary'!$C$189 -> MDW-39509 | D16: MO-BEM3 | E16: MO-BEM | F16: High Roof at the entrance and exit of the under floor wheel lathe | G16: สหชาติ | H16: Depot | I16: 46238 | J16: 46295 | K16: เกียรติพล
B17: Lot02 | C17: MDW-39536 | D17: Lot02 | E17: MO-BEM8 | F17: Company logo and Central Control Room sign in CCR room. | G17: สหชาติ | H17: 46143 | I17: 46302 | J17: 46302 | K17: เกียรติพล
B18: Lot02 | C18: MDW-39536 | D18: Lot02 | E18: MO-BEM9 | F18: Soundproof insulation on the wall and structure and equipment in the CCR room. | G18: สหชาติ | H18: 46143 | I18: 46302 | J18: 46302 | K18: เกียรติพล
B19: Lot02 | C19: MDW-39522 | D19: Lot02 | E19: MO-BEM12 | F19: Rain protection for Water treatment Building | G19: สหชาติ | H19: 46239 | I19: 46295 | J19: 46295 | K19: เกียรติพล
B20: Lot02 | C20: MDW-39514 | D20: Lot02 | E20: MO-BEM15.1 | F20: Roof for cars parking lots area (184 car)t - Civil & AR | G20: สหชาติ | H20: 46237 | I20: 46295 | J20: 46295 | K20: เกียรติพล
B21: Lot02 | C21: MDW-39514 | D21: Lot02 | E21: MO-BEM51 | F21: Modify existing car park to be 220 motorcycle parking lots including floor painting and parking roof | J21: 46295 | K21: เกียรติพล
Q24: Inspection (PLAN) | R24: ผู้รับผิดชอบ
M25: PSY-39001-9 | N25: Lot01 | O25: PSY2 | P25: GIS and BSS Building and Other Facilities | Q25: 46295 | R25: พรพรหม/ทินภัทร
M26: MDW-39545 | N26: Lot02 | O26: MO-CK11 | P26: Chain Link at Cut & Cover 600m. | Q26: 46295 | R26: พรพรหม/ก่อเกียรติ

Sheet Design
B2: Design
B4: No. | C4: Design Submission | D4: Lot No. | E4: Code | F4: System | G4: Activity Name | H4: CK Responsible Person | J4: Location | K4: Expected Completion Month | L4: Design (PLAN) | M4: Design (%) | N4: Design (Status) | O4: Note | Q4: Design Submission | R4: Procedure No. | S4: Test Report No.
B5: {=IF('01 Summary'!B4:N250=" "," ",'01 Summary'!B4:N250)} -> 1 | C5: MDW-39246-60 | D5: Lot01 | E5: GEN1 | F5: GEN | G5: Rooms and Building Service Systems Modification in Stations Area | H5: - | I5: 0 | J5: 0 | K5: 46235 | L5: 0 | M5: 0 | N5: 0 | Q5: MDW-39246 | R5: MDW-69259 | S5: MDW-69260
B6: 2 | C6: MDW-39246 | D6: Lot01 | E6: GEN1.1 | F6: GEN | G6: Power Outlet Installation in SOR, Ticket Office and Cash Handling for OR13 - OR17 | H6: ประธาน | I6: 0 | J6: 0 | K6: 46235 | L6: 46052 | M6: 1 | N6: Completed | Q6: MDW-39246 | R6: MDW-69259 | S6: MDW-69260
B7: 3 | C7: MDW-39247 | D7: Lot01 | E7: GEN1.2 | F7: GEN | G7: Power Outlet Installation in SOR, Ticket Office and Cash Handling for OR18 - OR22 | H7: ประธาน | I7: 0 | J7: 0 | K7: 46235 | L7: 46021 | M7: 1 | N7: Completed | Q7: MDW-39247 | R7: MDW-69259 | S7: MDW-69261
B8: 4 | C8: MDW-39248 | D8: Lot01 | E8: GEN1.3 | F8: GEN | G8: Power Outlet Installation in SOR, Ticket Office and Cash Handling for OR23 - OR29 | H8: ประธาน | I8: 0 | J8: 0 | K8: 46235 | L8: 46052 | M8: 1 | N8: Completed | Q8: MDW-39248 | R8: MDW-69259 | S8: MDW-69262
B9: 5 | C9: MDW-39252 | D9: Lot01 | E9: GEN1.4 | F9: GEN | G9: Modification of Fire Suppression System (N2) in Commerial Room at OR14 | H9: ประธาน | I9: 0 | J9: 0 | K9: 46235 | L9: 46021 | M9: 1 | N9: Completed | Q9: MDW-39252 | R9: MDW-69269 | S9: MDW-69270
B10: 6 | C10: MDW-39253 | D10: Lot01 | E10: GEN1.5 | F10: GEN | G10: Modification of Civil Work in Telecommunication Room at OR14 | H10: สหชาติ | I10: 0 | J10: 0 | K10: 46235 | L10: 46021 | M10: 1 | N10: Completed | Q10: MDW-39253 | R10: MDW-69271 | S10: MDW-69272
B11: 7 | C11: MDW-39254 | D11: Lot01 | E11: GEN1.6 | F11: GEN | G11: Modification in Staff Mess Room at OR13-OR17 | H11: ประธาน | I11: 0 | J11: 0 | K11: 46235 | L11: 46052 | M11: 1 | N11: Completed | Q11: MDW-39254 | R11: MDW-69273 | S11: MDW-69274
B12: 8 | C12: MDW-39255 | D12: Lot01 | E12: GEN1.7 | F12: GEN | G12: Modification in Staff Mess Room at OR18-OR22 | H12: ประธาน | I12: 0 | J12: 0 | K12: 46235 | L12: 46235 | M12: 1 | N12: Completed | Q12: MDW-39255 | R12: MDW-69273 | S12: MDW-69275
B13: 9 | C13: MDW-39256 | D13: Lot01 | E13: GEN1.8 | F13: GEN | G13: Modification in Staff Mess Room at OR23-OR29 | H13: ประธาน | I13: 0 | J13: 0 | K13: 46235 | L13: 46235 | M13: 1 | N13: Completed | Q13: MDW-39256 | R13: MDW-69273 | S13: MDW-69276
B14: 10 | C14: MDW-39257 | D14: Lot01 | E14: GEN1.9 | F14: GEN | G14: Modification of Air Conditioning in CER and SER at OR13-OR19 | H14: ประธาน | I14: 0 | J14: 0 | K14: 46235 | L14: 46235 | M14: 1 | N14: Completed | Q14: MDW-39257 | R14: MDW-69277 | S14: MDW-69278
B15: 11 | C15: MDW-39258 | D15: Lot01 | E15: GEN1.10 | F15: GEN | G15: Modification of Air Conditioning in CER and SER at OR20-OR22 | H15: ประธาน | I15: 0 | J15: 0 | K15: 46235 | L15: 46235 | M15: 1 | N15: Completed | Q15: MDW-39258 | R15: MDW-69277 | S15: MDW-69279
B16: 12 | C16: MDW-39259 | D16: Lot01 | E16: GEN1.11 | F16: GEN | G16: Modification of Air Conditioning in CER and SER at OR23-OR29 | H16: ประธาน | I16: 0 | J16: 0 | K16: 46235 | L16: 46235 | M16: 1 | N16: Completed | Q16: MDW-39259 | R16: MDW-69277 | S16: MDW-69280
B17: 13 | C17: MDW-39272 | D17: Lot01 | E17: GEN1.12 | F17: GEN | G17: Modification of New M&E Room at IVS15 - IVS17 Civil & AR | H17: สหชาติ | I17: 0 | J17: 0 | K17: 46235 | L17: 46235 | M17: 1 | N17: Completed | Q17: MDW-39272 | R17: MDW-69299 | S17: MDW-69300
... B24: 20 | C24: MDW-39250 | D24: Lot01 | E24: GEN1.19 | F24: GEN | G24: Ticket Office Modification on East Section | H24: สหชาติ | I24: 0 | J24: 0 | K24: 46235 | L24: 46235 | M24: 1 | N24: Completed | Q24: MDW-39250 | R24: MDW-69265 | S24: MDW-69266
B25: 21 | C25: MDW-39261 | D25: Lot01 | E25: GEN2 | F25: GEN | G25: Rooms and Building Service Systems Modification in Depot Area | H25: - | I25: 0 | J25: Depot | K25: 46235 | L25: 0 | M25: 0 | N25: 0 | Q25: MDW-39261 | R25: MDW-69283 | S25: MDW-69284
B26: 22 | C26: MDW-39260 | D26: Lot01 | E26: GEN2.1 | F26: GEN | G26: Modification of Air Conditioning in M&E Room at OCC Building | H26: ประธาน | I26: 0 | J26: 0 | K26: 46235 | L26: 46021 | M26: 1 | N26: Completed | Q26: MDW-39260 | R26: MDW-69281 | S26: MDW-69282
B27: 23 | C27: MDW-39261 | D27: Lot01 | E27: GEN2.2 | F27: GEN | G27: Provision of UPS for MDB Control at Main Workshop, OCC Building, Admin Building, Stabling Yard and Train Washing Plant | H27: ประธาน | I27: 0 | J27: 0 | K27: 46235 | L27: 46266 | M27: 1 | N27: Completed | Q27: MDW-39261 | R27: MDW-69283 | S27: MDW-69284
B28: 24 | C28: MDW-39262 | D28: Lot01 | E28: GEN2.3 | F28: GEN | G28: Provision of Redundant MDB at OCC Building, Admin Building and Canteen | H28: ประธาน | I28: 0 | J28: 0 | K28: 46235 | L28: 46266 | M28: 1 | N28: Completed | Q28: MDW-39262 | R28: MDW-69285 | S28: MDW-69286
B29: 25 | C29: MDW-39263 | D29: Lot01 | E29: GEN2.4 | F29: GEN | G29: Additonal Lighting System at Depot Area | H29: ประธาน | I29: 0 | J29: 0 | K29: 46235 | L29: 46113 | M29: 1 | N29: Completed | Q29: MDW-39263 | R29: MDW-69287 | S29: MDW-69288
